Workbook
Name Slicer_Gender: #N/A
Name Slicer_Sub_Category: #N/A
Name Slicer_Years__Order_Date: #N/A

Sheet Customer_Raw
A1: Customer_ID | B1: Name | C1: Age | D1: Gender | E1: City | F1: State | G1: Country | H1: Loyalty_Level
A2: CUST1000 | B2: sheena bonilla | C2: 55 | D2: Male | E2: Donaldton | F2: North Carolina | G2: USA
A3: CUST1001 | B3: Eugene Nelson | C3: 26 | D3: Female | E3: Phillipsmouth | F3: North Dakota | G3: USA | H3: Platinum
A4: CUST1002 | B4: dr. Benjamin Price | C4: 29 | D4: Female | E4: Kylebury | F4: Alabama | G4: USA | H4: Platinum
A5: CUST1003 | B5: jeremy harris | C5: 59 | D5: Female | E5: Thomastown | F5: Ohio | G5: USA | H5: Bronze
A6: CUST1004 | B6: Caroline Collins | C6: 64 | D6: Female | E6: Nicholasshire | F6: California | G6: USA | H6: Silver
A7: CUST1005 | B7: Christine Vaughn | C7: 24 | D7: Male | E7: East Amandamouth | F7: Oregon | G7: USA | H7: Bronze
A8: CUST1006 | B8: Amber Jackson | C8: 29 | D8: Female | E8: Deborahborough | F8: South Dakota | G8: USA | H8: Platinum
A9: CUST1007 | B9: Daniel Boyd | C9: 29 | D9: Female | E9: West Pamelafurt | F9: West Virginia | G9: USA | H9: Bronze
A10: CUST1008 | B10: Melissa Howard | C10: 53 | D10: Female | E10: Maynardton | F10: New Hampshire | G10: USA | H10: Gold
A11: CUST1009 | B11: Ms. Maria Leach | C11: 64 | D11: Male | E11: Melissashire | F11: Pennsylvania | G11: USA | H11: Platinum
A12: CUST1010 | B12: Dominic Page | C12: 53 | D12: Male | E12: Port Michaelburgh | F12: Pennsylvania | G12: USA | H12: Bronze
A13: CUST1011 | B13: Brian Lopez | C13: 28 | D13: Female | E13: East Krista | F13: New York | G13: USA | H13: Gold
A14: CUST1012 | B14: Kenneth Lambert | C14: 55 | D14: Female | E14: North Kathryn | F14: Kansas | G14: USA | H14: Platinum
... A19: CUST1017 | B19: Adam Cruz | C19: 60 | D19: Female | E19: Brandonville | F19: Georgia | G19: USA | H19: Platinum
A20: CUST1018 | B20: Rhonda Moss | C20: 43 | D20: Male | E20: South William | F20: Kansas | G20: USA
A21: CUST1019 | B21: Michael Torres | C21: 46 | D21: Female | E21: Gonzalezfort | F21: New Jersey | G21: USA | H21: Platinum
A22: CUST1020 | B22: Bridget Allen | C22: 59 | D22: Male | E22: Lake Shaneburgh | F22: Delaware | G22: USA | H22: Silver
A23: CUST1021 | B23: Jeff Martinez | C23: 36 | D23: Female | E23: Smithburgh | F23: Oklahoma | G23: USA | H23: Gold
A24: CUST1022 | B24: paul fox | C24: 33 | D24: Female | E24: Michaelton | F24: Hawaii | G24: USA | H24: Silver
A25: CUST1023 | B25: Jonathan Steele | C25: 52 | D25: Female | E25: Molinabury | F25: Oregon | G25: USA | H25: Silver
A26: CUST1024 | B26: Heather Collins | C26: 40 | D26: Male | E26: Rogerschester | F26: Idaho | G26: USA | H26: Platinum
A27: CUST1025 | B27: Diana Taylor | C27: 59 | D27: Female | E27: Vasqueztown | F27: California | G27: USA | H27: Bronze
A28: CUST1026 | B28: Amber Carlson | C28: 18 | D28: Female | E28: East Michellemouth | F28: Missouri | G28: USA | H28: Gold
A29: CUST1027 | B29: Leslie Johnson | C29: 31 | D29: Male | E29: Mollyshire | F29: Utah | G29: USA
A30: CUST1028 | B30: Joshua Ryan | C30: 27 | D30: Female | E30: New David | F30: New Jersey | G30: USA | H30: Platinum
A31: CUST1029 | B31: David Arnold | C31: 54 | D31: Female | E31: East Jennifer | F31: California | G31: USA | H31: Silver
A32: CUST1030 | B32: Jessica Acevedo | C32: 64 | D32: Female | E32: Amybury | F32: Pennsylvania | G32: USA | H32: Bronze
A33: CUST1031 | B33: Sarah Vance | C33: 41 | D33: Male | E33: Johnsonville | F33: Oregon | G33: USA | H33: Silver
A34: CUST1032 | B34: Mike Jennings | C34: 48 | D34: Female | E34: Fostermouth | F34: Arizona | G34: USA | H34: Gold
A35: CUST1033 | B35: Robert Jones DDS | C35: 25 | D35: Male | E35: Tristanton | F35: Oklahoma | G35: USA | H35: Platinum
A36: CUST1034 | B36: Christopher Olson | C36: 27 | D36: Female | E36: West Richard | F36: Maryland | G36: USA | H36: Platinum
A37: CUST1035 | B37: Rachel Myers | C37: 52 | D37: Male | E37: Robertberg | F37: North Dakota | G37: USA | H37: Silver
A38: CUST1036 | B38: Thomas Phillips | C38: 20 | D38: Female | E38: Luisfurt | F38: Georgia | G38: USA | H38: Gold
A39: CUST1037 | B39: Christopher Carter | C39: 27 | D39: Female | E39: Brendastad | F39: South Dakota | G39: USA
A40: CUST1038 | B40: Deanna Simpson | C40: 35 | D40: Female | E40: Brownport | F40: North Dakota | G40: USA | H40: Bronze
A41: CUST1039 | B41: Tonya Reynolds | C41: 55 | D41: Female | E41: Darleneton | F41: Michigan | G41: USA | H41: Gold
A42: CUST1040 | B42: Eric Vega | C42: 50 | D42: Male | E42: Williamsonland | F42: Kansas | G42: USA | H42: Gold
A43: CUST1041 | B43: James Gibbs | C43: 21 | D43: Male | E43: Mooneyshire | F43: Alaska | G43: USA | H43: Platinum
A44: CUST1042 | B44: William Martin | C44: 19 | D44: Male | E44: Ryanburgh | F44: Connecticut | G44: USA | H44: Platinum
A45: CUST1043 | B45: Joseph Snow | C45: 45 | D45: Male | E45: South Michaelfort | F45: Vermont | G45: USA | H45: Gold
A46: CUST1044 | B46: Denise Williams | C46: 34 | D46: Male | E46: Christianstad | F46: Hawaii | G46: USA | H46: Bronze
A47: CUST1045 | B47: Jordan Jackson DDS | C47: 54 | D47: Male | E47: North Johnview | F47: Arizona | G47: USA | H47: Gold
A48: CUST1046 | B48: Michelle Garcia DDS | C48: 55 | D48: Female | E48: Perezbury | F48: Ohio | G48: USA | H48: Platinum
A49: CUST1047 | B49: Gina Knight | C49: 54 | D49: Female | E49: Lake Roberthaven | F49: Nevada | G49: USA | H49: Silver
A50: CUST1048 | B50: April Mullins | C50: 54 | D50: Male | E50: Dawsonbury | F50: North Carolina | G50: USA | H50: Platinum
A51: CUST1049 | B51: Timothy Weaver | C51: 45 | D51: Female | E51: New Amy | F51: Ohio | G51: USA | H51: Gold
... A501: CUST1499 | B501: Philip Pennington | C501: 27 | D501: Female | E501: East Valerieview | F501: Oregon | G501: USA | H501: Platinum

Sheet Product_Raw
A1: Product_ID | B1: Product_Name | C1: Category | D1: Sub_Category | E1: Brand | F1: COST ORI | G1: Stock ORI | H1: Stock
A2: PROD0 | B2: Brother Laser Printer | C2: Electronics | D2: Computer | E2: Hunt Inc | F2: 112 | G2: 416 | H2: 416
A3: PROD1 | B3: Men's Graphic T-Shirt | C3: Clothing | D3: Tops | E3: Terry-Moore | F3: 342 | G3: 181 | H3: 181
A4: PROD2 | B4: Women's Casual Hoodie | C4: Clothing | D4: Outerwear | E4: Sims Inc | F4: 254 | G4: 352 | H4: 352
A5: PROD3 | B5: Men's Running Jacket | C5: Clothing | D5: Outerwear | E5: Pineda Ltd | F5: 364 | G5: 452 | H5: 452
A6: PROD4 | B6: Women's Yoga Pants | C6: Clothing | D6: Bottoms | E6: Gonzales-Davis | F6: 306 | G6: 487 | H6: 487
A7: PROD5 | B7: Men's Leather Belt | C7: Clothing | D7: Accessories | E7: Baldwin, Garza and Gonzalez | F7: 261 | G7: 59 | H7: 59
A8: PROD6 | B8: Herbal Face Moisturizer | C8: Beauty | D8: Skincare | E8: Davidson PLC | F8: 312 | G8: 343 | H8: 350
A9: PROD7 | B9: LED Table Lamp | C9: Home | D9: Lighting | E9: Harrell LLC | F9: 218 | G9: 360 | H9: 170
A10: PROD8 | B10: Wireless Bluetooth Earbuds | C10: Electronics | D10: Audio | E10: Perez-Johnston | F10: 439 | G10: 268 | H10: 142
A11: PROD9 | B11: Adjustable Dumbbell Set | C11: Sports | D11: Fitness | E11: Hill PLC | F11: 495 | G11: 154 | H11: 323
A12: PROD10 | B12: Ceramic Kitchen Bowl Set | C12: Home | D12: Kitchen | E12: Hamilton Group | F12: 298 | G12: 214 | H12: 308
A13: PROD11 | B13: HD Smart TV Stick | C13: Electronics | D13: Accessories | E13: Gibson, Hobbs and Weaver | F13: 449 | G13: 296 | H13: 296
A14: PROD12 | B14: Hair Strengthening Shampoo | C14: Beauty | D14: Haircare | E14: Rice LLC | F14: 115 | G14: 125 | H14: 460
A15: PROD13 | B15: USB-C Fast Charger | C15: Electronics | D15: Accessories | E15: Dawson-Perkins | F15: 242 | G15: 485 | H15: 453
A16: PROD14 | B16: Decorative Wall Mirror | C16: Home | D16: Decor | E16: Luna, Anderson and Bowman | F16: 48 | G16: 224 | H16: 439
A17: PROD15 | B17: 4K Home Projector | C17: Electronics | D17: Appliances | E17: Thomas LLC | F17: 465 | G17: 82 | H17: 301
A18: PROD16 | B18: Beard Grooming Kit | C18: Beauty | D18: Grooming | E18: Erickson-Green | F18: 337 | G18: 210 | H18: 256
A19: PROD17 | B19: Soccer Training Cone Set | C19: Sports | D19: Accessories | E19: Ford, Murphy and Wilson | F19: 144 | G19: 496 | H19: 367
A20: PROD18 | B20: Women's Denim Jeans | C20: Clothing | D20: Bottoms | E20: Guerra-Hendrix | F20: 254 | G20: 343 | H20: 343
A21: PROD19 | B21: Knee Support Brace | C21: Sports | D21: Equipment | E21: May-Reese | F21: 21 | G21: 65 | H21: 65
A22: PROD20 | B22: Outdoor Sports Water Bottle | C22: Sports | D22: Accessories | E22: Soto-Ellis | F22: 131 | G22: 268 | H22: =INT(IF(ISBLANK(I22),AVERAGE($H22:$H$99),I22)) -> 268
A23: PROD21 | B23: Multi-Purpose Storage Box | C23: Home | D23: Storage | E23: Gardner-Montes | F23: 123 | G23: 76 | H23: 76
A24: PROD22 | B24: Carbon Fiber Tennis Racket | C24: Sports | D24: Equipment | E24: Flores, Pineda and Rodriguez | F24: 484 | G24: 432 | H24: 432
A25: PROD23 | B25: Men's Formal Shirt | C25: Clothing | D25: Tops | E25: Moon, Mora and Santos | F25: 254 | G25: 360 | H25: 360
A26: PROD24 | B26: Foldable Camping Chair | C26: Sports | D26: Outdoor | E26: Cook Ltd | F26: 166 | G26: 340 | H26: 340
A27: PROD25 | B27: Women's Scarf Set | C27: Clothing | D27: Accessories | E27: Brown and Sons | F27: 174 | G27: 268 | H27: 268
A28: PROD26 | B28: Wireless Bluetooth Speaker | C28: Electronics | D28: Audio | E28: Reed-Schmidt | F28: 322 | G28: 213 | H28: 213
A29: PROD27 | B29: Decorative Floor Vase | C29: Home | D29: Decor | E29: Khan, Jones and Paul | F29: 254 | G29: 378 | H29: 378
A30: PROD28 | B30: Sports Stopwatch Timer | C30: Sports | D30: Accessories | E30: Burns-Hansen | F30: 38 | G30: 137 | H30: 137
A31: PROD29 | B31: Fabric Sofa Throw Blanket | C31: Home | D31: Decor | E31: Hoffman Group | F31: 218 | G31: 276 | H31: 276
A32: PROD30 | B32: Stainless Steel Cutlery Set | C32: Home | D32: Kitchen | E32: Stevens, Fernandez and Martin | F32: 19 | G32: 57 | H32: 57
A33: PROD31 | B33: Basketball | C33: Sports | D33: Team Sports | E33: Nolan-Snow | F33: 204 | G33: 281 | H33: 281
A34: PROD32 | B34: Vitamin C Face Serum | C34: Beauty | D34: Skincare | E34: Griffin Ltd | F34: 283 | G34: 244 | H34: 244
A35: PROD33 | B35: Modern Wall Clock | C35: Home | D35: Decor | E35: Weiss-Watson | F35: 179 | G35: 305 | H35: 305
A36: PROD34 | B36: Gaming Mechanical Keyboard | C36: Electronics | D36: Computer | E36: Lucero LLC | F36: 419 | G36: 86 | H36: 86
A37: PROD35 | B37: Bedroom Table Lamp | C37: Home | D37: Lighting | E37: Jones LLC | F37: 382 | G37: 329 | H37: 329
A38: PROD36 | B38: Women's Summer Dress | C38: Clothing | D38: Tops | E38: Smith-Mills | F38: 223 | G38: 154 | H38: 154
A39: PROD37 | B39: Men's Casual Sneakers | C39: Clothing | D39: Footwear | E39: Hogan-Lee | F39: 353 | G39: 214 | H39: 214
A40: PROD38 | B40: Sports Water Hydration Pack | C40: Sports | D40: Outdoor | E40: Sims-Smith | F40: 135 | G40: 394 | H40: 394
A41: PROD39 | B41: Portable Power Bank | C41: Electronics | D41: Mobile | E41: Cummings and Sons | F41: 326 | G41: 301 | H41: 301
A42: PROD40 | B42: Noise-Canceling Headphones | C42: Electronics | D42: Audio | E42: Taylor-Hart | F42: 38 | G42: 378 | H42: 378
A43: PROD41 | B43: Yoga Exercise Mat | C43: Sports | D43: Fitness | E43: Carroll, Long and Mendoza | F43: 313 | G43: 369 | H43: 369
A44: PROD42 | B44: Smart Home WiFi Camera | C44: Electronics | D44: Accessories | E44: Holmes LLC | F44: 450 | G44: 389 | H44: 389
A45: PROD43 | B45: USB External Hard Drive | C45: Electronics | D45: Computer | E45: Robinson Inc | F45: 253 | G45: 266 | H45: 266
A46: PROD44 | B46: Adjustable Jump Rope | C46: Sports | D46: Fitness | E46: Cox Inc | F46: 167 | G46: 316 | H46: 316
A47: PROD45 | B47: High-Grip Football | C47: Sports | D47: Team Sports | E47: Bridges, Banks and Cummings | F47: 318 | G47: 114 | H47: 114
A48: PROD46 | B48: Men's Winter Jacket | C48: Clothing | D48: Outerwear | E48: Kelly, Smith and Perez | F48: 167 | G48: 296 | H48: 296
A49: PROD47 | B49: Makeup Brush Set | C49: Beauty | D49: Makeup | E49: Cook Inc | F49: 254 | G49: 431 | H49: 431
A50: PROD48 | B50: Car Dashboard Phone Holder | C50: Electronics | D50: Accessories | E50: Byrd, Stewart and Valdez | F50: 177 | G50: 103 | H50: 103
A51: PROD49 | B51: Men's Roll-On Perfume | C51: Beauty | D51: Fragrance | E51: Sullivan and Sons | F51: 43 | G51: 267 | H51: 267
A52: PROD50 | B52: Boxing Hand Wraps | C52: Sports | D52: Fitness | E52: Smith-King | F52: 190 | G52: 260 | H52: 260
A53: PROD51 | B53: HDMI Cable – 2m | C53: Electronics | D53: Accessories | E53: Bautista, Green and Hale | F53: 88 | G53: 246 | H53: 246
A54: PROD52 | B54: Rugby Ball | C54: Sports | D54: Team Sports | E54: Harris Inc | F54: 212 | G54: 82 | H54: 82
A55: PROD53 | B55: Men's Track Pants | C55: Clothing | D55: Bottoms | E55: Hamilton, Woods and Walker | F55: 386 | G55: 125 | H55: 125
A56: PROD54 | B56: Sports Stopwatch Pro | C56: Sports | D56: Accessories | E56: Thompson-French | F56: 434 | G56: 185 | H56: 185
A57: PROD55 | B57: Ceramic Plant Pot | C57: Home | D57: Decor | E57: Hatfield, Baird and Torres | F57: 81 | G57: 269 | H57: =INT(IF(ISBLANK(I57),AVERAGE($H$9:$H$101),I57)) -> 269
A58: PROD56 | B58: Premium Blanket Throw | C58: Home | D58: Decor | E58: Hernandez, Kennedy and Porter | F58: 461 | G58: 190 | H58: 190
A59: PROD57 | B59: Foam Roller | C59: Sports | D59: Fitness | E59: Atkinson, Camacho and Oliver | F59: 30 | G59: 138 | H59: 138
A60: PROD58 | B60: Womens Cotton Scarf | C60: Clothing | D60: Accessories | E60: Shepherd-Gould | F60: 113 | G60: 485 | H60: 485
A61: PROD59 | B61: Men's Hair Styling Gel | C61: Beauty | D61: Haircare | E61: Cline-Mccarthy | F61: 17 | G61: 399 | H61: 399
A62: PROD60 | B62: Luxury Perfume Spray | C62: Beauty | D62: Fragrance | E62: Gibson, Green and Lopez | F62: 482 | G62: 444 | H62: 444
A63: PROD61 | B63: Tennis Ball 3-Pack | C63: Sports | D63: Equipment | E63: Lopez LLC | F63: 103 | G63: 465 | H63: 465
A64: PROD62 | B64: Laptop Cooling Pad | C64: Electronics | D64: Computer | E64: Murray, Gould and Ware | F64: 86 | G64: 222 | H64: 222
A65: PROD63 | B65: Organic Sunscreen Lotion | C65: Beauty | D65: Skincare | E65: Anderson-Riley | F65: 266 | G65: 458 | H65: 458
A66: PROD64 | B66: Matte Lipstick Set | C66: Beauty | D66: Makeup | E66: Zhang Inc | F66: 299 | G66: 118 | H66: 118
A67: PROD65 | B67: Adjustable Dumbbells 20kg | C67: Sports | D67: Fitness | E67: Montgomery, Benton and Miller | F67: 240 | G67: 423 | H67: 423
A68: PROD66 | B68: Women's Hair Dryer Brush | C68: Beauty | D68: Haircare | E68: Torres, Spencer and Potter | F68: 340 | G68: 177 | H68: 177
A69: PROD67 | B69: Smart LED Light Strip | C69: Electronics | D69: Accessories | E69: Flores-Davis | F69: 349 | G69: 476 | H69: 476
A70: PROD68 | B70: Wooden Nightstand | C70: Home | D70: Furniture | E70: Wolfe, Ross and Hester | F70: 243 | G70: 130 | H70: 130
A71: PROD69 | B71: Men's Sports Shorts | C71: Clothing | D71: Bottoms | E71: Fitzpatrick Ltd | F71: 218 | G71: 224 | H71: 224
A72: PROD70 | B72: Kitchen Storage Rack | C72: Home | D72: Storage | E72: Duran Group | F72: 138 | G72: 89 | H72: 89
A73: PROD71 | B73: Hair Repair Oil Treatment | C73: Beauty | D73: Haircare | E73: Hopkins Ltd | F73: 214 | G73: 383 | H73: 383
A74: PROD72 | B74: Professional Jump Rope | C74: Sports | D74: Fitness | E74: Davis PLC | F74: 477 | G74: 300 | H74: 300
A75: PROD73 | B75: Shin Guards – Adult | C75: Sports | D75: Team Sports | E75: French Ltd | F75: 107 | G75: 359 | H75: 359
A76: PROD74 | B76: Bluetooth Car Audio System | C76: Electronics | D76: Audio | E76: Bruce-Bowen | F76: 403 | G76: 159 | H76: 159
A77: PROD75 | B77: Women's Ankle Boots | C77: Clothing | D77: Footwear | E77: Poole PLC | F77: 158 | G77: 82 | H77: 82
A78: PROD76 | B78: Wireless Mouse | C78: Electronics | D78: Computer | E78: Larson Ltd | F78: 392 | G78: 320 | H78: 320
A79: PROD77 | B79: WiFi Mesh Router | C79: Electronics | D79: Appliances | E79: White, Reeves and Woods | F79: 480 | G79: 104 | H79: 104
A80: PROD78 | B80: Essential Oil Diffuser | C80: Home | D80: Decor | E80: Hernandez Inc | F80: 325 | G80: 400 | H80: 400
A81: PROD79 | B81: Decorative Lamp Shade | C81: Home | D81: Lighting | E81: Ramirez-Hanson | F81: 228 | G81: 469 | H81: 469
A82: PROD80 | B82: Wall-Mounted Spice Rack | C82: Home | D82: Kitchen | E82: Allison Ltd | F82: 143 | G82: 58 | H82: 58
A83: PROD81 | B83: Badminton Racket Set | C83: Sports | D83: Equipment | E83: Robinson-Brown | F83: 285 | G83: 358 | H83: 358
A84: PROD82 | B84: Fitness Resistance Bands | C84: Sports | D84: Fitness | E84: Reese-Watson | F84: 152 | G84: 281 | H84: 281
A85: PROD83 | B85: Hydrating Face Cleanser | C85: Beauty | D85: Skincare | E85: Butler Group | F85: 254 | G85: 159 | H85: 159
A86: PROD84 | B86: Wooden Bookshelf | C86: Home | D86: Furniture | E86: Collins-Stephenson | F86: 388 | G86: 208 | H86: 208
A87: PROD85 | B87: Women's Beanie Hat | C87: Clothing | D87: Accessories | E87: Richardson-Carrillo | F87: 119 | G87: 210 | H87: 210
A88: PROD86 | B88: Kitchen Cutting Board | C88: Home | D88: Kitchen | E88: Taylor, Dodson and Johnston | F88: 176 | G88: 82 | H88: 82
A89: PROD87 | B89: LED Bedside Lamp | C89: Home | D89: Lighting | E89: Aguilar, Horton and Lewis | F89: 371 | G89: 220 | H89: 220
A90: PROD88 | B90: Sports Wrist Sweatbands | C90: Sports | D90: Accessories | E90: Olsen-Daniels | F90: 131 | G90: 232 | H90: 232
A91: PROD89 | B91: Face Foundation Kit | C91: Beauty | D91: Makeup | E91: Taylor-Elliott | F91: 183 | G91: 457 | H91: 457
A92: PROD90 | B92: Gaming Mouse Pad XL | C92: Electronics | D92: Accessories | E92: Sharp, Taylor and Rodriguez | F92: 340 | G92: 361 | H92: 361
A93: PROD91 | B93: Women's High Heels | C93: Clothing | D93: Footwear | E93: Smith-Charles | F93: 438 | G93: 496 | H93: 496
A94: PROD92 | B94: Microwave Oven | C94: Home | D94: Appliances | E94: Green, Powell and Palmer | F94: 447 | G94: 191 | H94: 191
A95: PROD93 | B95: USB-C Laptop Charger | C95: Electronics | D95: Computer | E95: Martin LLC | F95: 377 | G95: 485 | H95: 485
A96: PROD94 | B96: Vitamin E Body Lotion | C96: Beauty | D96: Skincare | E96: Hoffman-Williams | F96: 358 | G96: 213 | H96: 213
A97: PROD95 | B97: Sports Stopwatch Basic | C97: Sports | D97: Accessories | E97: Wilson Group | F97: 60 | G97: 75 | H97: 75
A98: PROD96 | B98: Women's Formal Blazer | C98: Clothing | D98: Outerwear | E98: Phillips and Sons | F98: 358 | G98: 143 | H98: 143
A99: PROD97 | B99: Cricket Bat | C99: Sports | D99: Team Sports | E99: Khan LLC | F99: 245 | G99: 471 | H99: 471
A100: PROD98 | B100: Portable Bluetooth Speaker | C100: Electronics | D100: Audio | E100: Flores-King | F100: 431 | G100: 73 | H100: 73
...

Sheet Store_Raw
A1: Store_ID | B1: Store_Name | C1: Region | D1: City | E1: Store_Type
A2: STORE0 | B2: Rivera-Warner | C2: East | D2: Washingtonfurt | E2: Flagship
A3: STORE1 | B3: Martinez, Adkins and Johnson | C3: North | D3: Danielmouth | E3: Flagship
A4: STORE2 | B4: Black-Horn | C4: South | D4: North Nancyview | E4: Outlet
A5: STORE3 | B5: Johnson-Wright | C5: North | D5: Hoodberg | E5: Outlet
A6: STORE4 | B6: Alexander Group | C6: South | D6: Port Sharon | E6: Online
A7: STORE5 | B7: Gray Ltd | C7: North | D7: New Michaelchester | E7: Outlet
A8: STORE6 | B8: Benson-Elliott | C8: East | D8: Port Josephberg | E8: Online
A9: STORE7 | B9: Martinez-Mullins | C9: South | D9: Williamsfurt | E9: Online
A10: STORE8 | B10: Bean, Jones and Park | C10: West | D10: Thompsonborough | E10: Online
A11: STORE9 | B11: Moore, Padilla and Butler | C11: South | D11: East Johnstad | E11: Flagship
A12: STORE10 | B12: Hill, Wagner and Ballard | C12: East | D12: East Davidville | E12: Online
... A21: STORE19 | B21: Mann-Austin | C21: East | D21: Vasquezborough | E21: Online

Sheet Sales_Fact Raw
A1: Sales_ID | B1: Order_Date | C1: Customer_ID | D1: Product_ID | E1: Store_ID | F1: Quantity | G1: Unit_Price | H1: Discount | I1: Payment_Type | J1: Total_Amount
A2: SALE66 | B2: 45213 | C2: CUST1269 | D2: PROD77 | E2: STORE2 | F2: 4 | G2: 814.25 | H2: 0.18 | I2: Credit Card | J2: 2670.74
A3: SALE799 | B3: 45213 | C3: CUST1235 | D3: PROD92 | E3: STORE11 | F3: 4 | G3: 23.57 | H3: 0.1 | I3: Credit Card | J3: 84.852
A4: SALE1173 | B4: 45213 | C4: CUST1283 | D4: PROD56 | E4: STORE16 | F4: 2 | G4: 805.08 | H4: 0.27 | I4: PayPal | J4: 1175.4168
A5: SALE105 | B5: 45214 | C5: CUST1002 | D5: PROD79 | E5: STORE17 | F5: 2 | G5: 418.23 | H5: 0.28 | I5: Credit Card | J5: 602.2512
A6: SALE1727 | B6: 45214 | C6: CUST1023 | D6: PROD12 | E6: STORE0 | F6: 1 | G6: 145.48 | H6: 0.1 | I6: COD | J6: 130.932
A7: SALE34 | B7: 45215 | C7: CUST1344 | D7: PROD79 | E7: STORE1 | F7: =TEXT(F7,0) -> 0 | G7: 873.22 | H7: 0.18 | I7: Credit Card | J7: 2148.1212
A8: SALE1071 | B8: 45215 | C8: CUST1225 | D8: PROD89 | E8: STORE2 | F8: 4 | G8: 753.83 | H8: 0.24 | I8: Credit Card | J8: 2291.6432
A9: SALE1221 | B9: 45216 | C9: CUST1010 | D9: PROD52 | E9: STORE19 | F9: 2 | G9: 441.03 | H9: 0.23 | I9: COD | J9: 679.1862
A10: SALE1958 | B10: 45216 | C10: CUST1072 | D10: PROD64 | E10: STORE19 | F10: 3 | G10: 449.99 | H10: 0.17 | I10: COD | J10: 1120.4751
A11: SALE30 | B11: 45217 | C11: CUST1028 | D11: PROD5 | E11: STORE19 | F11: 1 | G11: 429.38 | H11: 0.13 | I11: PayPal | J11: 373.5606
A12: SALE369 | B12: 45217 | C12: CUST1448 | D12: PROD65 | E12: STORE3 | F12: 4 | G12: 269.49 | H12: 0.07 | I12: PayPal | J12: 1002.5028
A13: SALE732 | B13: 45217 | C13: CUST1224 | D13: PROD50 | E13: STORE17 | F13: 1 | G13: 498.61 | H13: 0.04 | I13: PayPal | J13: 478.6656
A14: SALE1007 | B14: 45217 | C14: CUST1198 | D14: PROD75 | E14: STORE2 | F14: 2 | G14: 541.52 | H14: 0.26 | I14: PayPal | J14: 801.4496
A15: SALE1274 | B15: 45217 | C15: CUST1198 | D15: PROD60 | E15: STORE11 | F15: 3 | G15: 257.11 | H15: 0.26 | I15: COD | J15: 570.7842
A16: SALE48 | B16: 45218 | C16: CUST1203 | D16: PROD44 | E16: STORE17 | F16: 1 | G16: 517.13 | H16: 0.28 | I16: Credit Card | J16: 372.3336
A17: SALE340 | B17: 45218 | C17: CUST1047 | D17: PROD17 | E17: STORE19 | F17: 3 | G17: 997.95 | H17: 0.09 | I17: COD | J17: 2724.4035
A18: SALE217 | B18: 45219 | C18: CUST1266 | D18: PROD15 | E18: STORE19 | F18: 1 | G18: 332.82 | H18: 0.14 | I18: PayPal | J18: 286.2252
A19: SALE1116 | B19: 45219 | C19: CUST1140 | D19: PROD13 | E19: STORE8 | F19: 3 | G19: 278.38 | H19: 0.03 | I19: Credit Card | J19: 810.0858
... A153: SALE79 | B153: 45268 | C153: CUST1115 | D153: PROD21 | E153: STORE2 | F153: 1 | G153: 341.17 | H153: 0.15 | I153: Credit Card | J153: 289.9945
A154: SALE84 | B154: 45268 | C154: CUST1423 | D154: PROD46 | E154: STORE17 | F154: 1 | G154: 773.57 | H154: 0.05 | I154: COD | J154: =F154*G154*(1-H154) -> 734.8915
A155: SALE300 | B155: 45268 | C155: CUST1198 | D155: PROD12 | E155: STORE15 | F155: 4 | G155: 889.47 | H155: 0.24 | I155: Credit Card | J155: 2703.9888
A156: SALE1328 | B156: 45268 | C156: CUST1334 | D156: PROD5 | E156: STORE8 | F156: 3 | G156: 120.77 | H156: 0.29 | I156: PayPal | J156: 257.2401
A157: SALE1581 | B157: 45268 | C157: CUST1307 | D157: PROD46 | E157: STORE10 | F157: 1 | G157: 209.7 | H157: 0.2 | I157: PayPal | J157: 167.76
A158: SALE1681 | B158: 45268 | C158: CUST1136 | D158: PROD37 | E158: STORE15 | F158: 3 | G158: 281.96 | H158: 0.01 | I158: COD | J158: 837.4212
A159: SALE1702 | B159: 45268 | C159: CUST1217 | D159: PROD37 | E159: STORE7 | F159: 2 | G159: 985.79 | H159: 0.04 | I159: PayPal | J159: 1892.7168
A160: SALE166 | B160: 45269 | C160: CUST1295 | D160: PROD69 | E160: STORE8 | F160: 4 | G160: 714.47 | H160: 0.18 | I160: COD | J160: 2343.4616
A161: SALE1892 | B161: 45269 | C161: CUST1059 | D161: PROD70 | E161: STORE14 | F161: 2 | G161: 47.3 | H161: 0.01 | I161: PayPal | J161: 93.654
A162: SALE68 | B162: 45270 | C162: CUST1372 | D162: PROD72 | E162: STORE10 | F162: 4 | G162: 62.48 | H162: 0.18 | I162: Credit Card | J162: 204.9344
A163: SALE461 | B163: 45270 | C163: CUST1129 | D163: PROD91 | E163: STORE11 | F163: 4 | G163: 202.46 | H163: 0.24 | I163: Credit Card | J163: 615.4784
A164: SALE685 | B164: 45270 | C164: CUST1456 | D164: PROD88 | E164: STORE13 | F164: 4 | G164: 451.41 | H164: 0.06 | I164: PayPal | J164: 1697.3016
A165: SALE1119 | B165: 45271 | C165: CUST1455 | D165: PROD21 | E165: STORE4 | F165: 2 | G165: 961.84 | H165: 0.25 | I165: PayPal | J165: 1442.76
A166: SALE980 | B166: 45272 | C166: CUST1232 | D166: PROD66 | E166: STORE8 | F166: 4 | G166: 649.52 | H166: 0.11 | I166: Credit Card | J166: 2312.2912
... A224: SALE1948 | B224: 45293 | C224: CUST1425 | D224: PROD94 | E224: STORE10 | F224: 4 | G224: 101.25 | H224: 0.16 | I224: PayPal | J224: 340.2
A225: SALE26 | B225: 45294 | C225: CUST1213 | D225: PROD98 | E225: STORE8 | F225: 4 | G225: 156.16 | H225: =TEXT(H225,0) -> 0 | I225: Credit Card | J225: 599.6544
A226: SALE896 | B226: 45294 | C226: CUST1431 | D226: PROD96 | E226: STORE16 | F226: 1 | G226: 835.17 | H226: 0.02 | I226: COD | J226: 818.4666
A227: SALE1645 | B227: 45294 | C227: CUST1343 | D227: PROD39 | E227: STORE5 | F227: 1 | G227: 702.27 | H227: 0.17 | I227: COD | J227: 582.8841
A228: SALE548 | B228: 45295 | C228: CUST1123 | D228: PROD12 | E228: STORE15 | F228: 2 | G228: 562.97 | H228: 0.2 | I228: Credit Card | J228: 900.752
A229: SALE1409 | B229: 45296 | C229: CUST1067 | D229: PROD25 | E229: STORE15 | F229: 2 | G229: 795.37 | H229: 0.2 | I229: COD | J229: 1272.592
A230: SALE1525 | B230: 45296 | C230: CUST1296 | D230: PROD23 | E230: STORE18 | F230: 1 | G230: 616.82 | H230: 0.24 | I230: Credit Card | J230: 468.7832
A231: SALE1666 | B231: 45296 | C231: CUST1365 | D231: PROD27 | E231: STORE9 | F231: 4 | G231: 208.34 | H231: 0.01 | I231: PayPal | J231: 825.0264
A232: SALE1729 | B232: 45296 | C232: CUST1292 | D232: PROD1 | E232: STORE14 | F232: 4 | G232: 146.12 | H232: 0.12 | I232: COD | J232: 514.3424
A233: SALE1751 | B233: 45296 | C233: CUST1257 | D233: PROD97 | E233: STORE19 | F233: 4 | G233: 715.42 | H233: 0.29 | I233: PayPal | J233: 2031.7928
A234: SALE4 | B234: 45297 | C234: CUST1493 | D234: PROD59 | E234: STORE5 | F234: 3 | G234: 745.3 | H234: 0.18 | I234: Credit Card | J234: 1833.438
A235: SALE970 | B235: 45297 | C235: CUST1061 | D235: PROD96 | E235: STORE19 | F235: 4 | G235: 492.71 | H235: 0.08 | I235: Credit Card | J235: 1813.1728
A236: SALE356 | B236: 45299 | C236: CUST1065 | D236: PROD18 | E236: STORE1 | F236: 1 | G236: 691.38 | H236: 0.11 | I236: COD | J236: 615.3282
A237: SALE796 | B237: 45299 | C237: CUST1052 | D237: PROD51 | E237: STORE16 | F237: 1 | G237: 408.66 | H237: 0.13 | I237: COD | J237: 355.5342
... A245: SALE1949 | B245: 45301 | C245: CUST1226 | D245: PROD7 | E245: STORE17 | F245: 4 | G245: 716.39 | H245: 0.03 | I245: PayPal | J245: 2779.5932
A246: SALE29 | B246: 45302 | C246: CUST1348 | D246: PROD99 | E246: STORE3 | F246: =TEXT(F246,0) -> 0 | G246: 451.67 | H246: 0.15 | I246: Credit Card | J246: 1535.678
A247: SALE384 | B247: 45302 | C247: CUST1483 | D247: PROD9 | E247: STORE15 | F247: 4 | G247: 355.14 | H247: 0.16 | I247: COD | J247: 1193.2704
A248: SALE871 | B248: 45302 | C248: CUST1066 | D248: PROD40 | E248: STORE15 | F248: 1 | G248: 517.82 | H248: 0.29 | I248: Credit Card | J248: 367.6522
A249: SALE339 | B249: 45303 | C249: CUST1222 | D249: PROD46 | E249: STORE6 | F249: 4 | G249: 344.12 | H249: 0.25 | I249: PayPal | J249: 1032.36
A250: SALE355 | B250: 45304 | C250: CUST1241 | D250: PROD15 | E250: STORE15 | F250: 2 | G250: 899.27 | H250: 0.17 | I250: Credit Card | J250: 1492.7882
A251: SALE999 | B251: 45304 | C251: CUST1421 | D251: PROD81 | E251: STORE8 | F251: 4 | G251: 22.51 | H251: 0.27 | I251: PayPal | J251: 65.7292
A252: SALE1323 | B252: 45304 | C252: CUST1251 | D252: PROD30 | E252: STORE1 | F252: 4 | G252: 629.05 | H252: 0.26 | I252: Credit Card | J252: 1861.988
A253: SALE1417 | B253: 45304 | C253: CUST1059 | D253: PROD23 | E253: STORE1 | F253: 2 | G253: 54.51 | H253: 0.07 | I253: Credit Card | J253: 101.3886
A254: SALE1450 | B254: 45305 | C254: CUST1452 | D254: PROD9 | E254: STORE7 | F254: 1 | G254: 484.23 | H254: 0.12 | I254: COD | J254: 426.1224
A255: SALE505 | B255: 45306 | C255: CUST1163 | D255: PROD95 | E255: STORE1 | F255: 1 | G255: 301.6 | H255: 0.27 | I255: Credit Card | J255: 220.168
A256: SALE821 | B256: 45307 | C256: CUST1053 | D256: PROD49 | E256: STORE5 | F256: 1 | G256: 678.9 | H256: 0.17 | I256: Credit Card | J256: 563.487
A257: SALE1125 | B257: 45307 | C257: CUST1233 | D257: PROD95 | E257: STORE15 | F257: 2 | G257: 463.52 | H257: 0.27 | I257: PayPal | J257: 676.7392
A258: SALE286 | B258: 45308 | C258: CUST1466 | D258: PROD48 | E258: STORE19 | F258: 3 | G258: 807.95 | H258: 0.1 | I258: PayPal | J258: 2181.465
... A427: SALE1392 | B427: 45368 | C427: CUST1115 | D427: PROD49 | E427: STORE7 | F427: 3 | G427: 847.44 | H427: 0.17 | I427: Credit Card | J427: 2110.1256
A428: SALE19 | B428: 45369 | C428: CUST1239 | D428: PROD60 | E428: STORE13 | F428: 4 | G428: =INT(J428/(F428*(1-H428))) -> 464 | H428: 0.04 | I428: COD | J428: 1782.4512
A429: SALE670 | B429: 45369 | C429: CUST1221 | D429: PROD67 | E429: STORE4 | F429: 2 | G429: 132.77 | H429: 0.13 | I429: COD | J429: 231.0198
A430: SALE926 | B430: 45369 | C430: CUST1215 | D430: PROD67 | E430: STORE19 | F430: 3 | G430: 968.88 | H430: 0.15 | I430: Credit Card | J430: 2470.644
A431: SALE1799 | B431: 45369 | C431: CUST1227 | D431: PROD99 | E431: STORE8 | F431: 3 | G431: 561.44 | H431: 0.2 | I431: COD | J431: 1347.456
A432: SALE1076 | B432: 45370 | C432: CUST1045 | D432: PROD33 | E432: STORE17 | F432: 3 | G432: 623.82 | H432: 0.13 | I432: COD | J432: 1628.1702
A433: SALE176 | B433: 45371 | C433: CUST1128 | D433: PROD25 | E433: STORE15 | F433: 1 | G433: 857.35 | H433: 0.28 | I433: PayPal | J433: 617.292
A434: SALE490 | B434: 45371 | C434: CUST1418 | D434: PROD89 | E434: STORE18 | F434: 1 | G434: 170.43 | H434: 0.03 | I434: Credit Card | J434: 165.3171
A435: SALE734 | B435: 45371 | C435: CUST1198 | D435: PROD3 | E435: STORE2 | F435: 2 | G435: 371.03 | H435: 0.23 | I435: PayPal | J435: 571.3862
A436: SALE761 | B436: 45371 | C436: CUST1165 | D436: PROD78 | E436: STORE1 | F436: 3 | G436: 468.25 | H436: 0.07 | I436: PayPal | J436: 1306.4175
A437: SALE1202 | B437: 45371 | C437: CUST1264 | D437: PROD66 | E437: STORE9 | F437: 2 | G437: 972.4 | H437: 0.06 | I437: COD | J437: 1828.112
A438: SALE516 | B438: 45372 | C438: CUST1175 | D438: PROD62 | E438: STORE14 | F438: 1 | G438: 145.43 | H438: 0.08 | I438: Credit Card | J438: 133.7956
A439: SALE741 | B439: 45372 | C439: CUST1002 | D439: PROD86 | E439: STORE9 | F439: 1 | G439: 431.69 | H439: 0.09 | I439: Credit Card | J439: 392.8379
A440: SALE1563 | B440: 45372 | C440: CUST1047 | D440: PROD76 | E440: STORE16 | F440: 2 | G440: 675.61 | H440: 0.08 | I440: COD | J440: 1243.1224
... A855: SALE1350 | B855: 45529 | C855: CUST1390 | D855: PROD23 | E855: STORE2 | F855: 3 | G855: 152.41 | H855: 0.25 | I855: Credit Card | J855: 342.9225
A856: SALE94 | B856: 45530 | C856: CUST1298 | D856: PROD97 | E856: STORE19 | F856: 2 | G856: 569.36 | H856: 0.01 | I856: PayPal | J856: =F856*G856*(1-H856) -> 1127.3328
A857: SALE698 | B857: 45530 | C857: CUST1039 | D857: PROD37 | E857: STORE7 | F857: 3 | G857: 346.77 | H857: 0.18 | I857: PayPal | J857: 853.0542
A858: SALE971 | B858: 45530 | C858: CUST1280 | D858: PROD91 | E858: STORE13 | F858: 4 | G858: 853.26 | H858: 0.24 | I858: COD | J858: 2593.9104
A859: SALE1188 | B859: 45530 | C859: CUST1209 | D859: PROD34 | E859: STORE9 | F859: 2 | G859: 166.26 | H859: 0.14 | I859: PayPal | J859: 285.9672
A860: SALE1210 | B860: 45530 | C860: CUST1081 | D860: PROD36 | E860: STORE8 | F860: 4 | G860: 271.04 | H860: 0.12 | I860: COD | J860: 954.0608
A861: SALE1263 | B861: 45530 | C861: CUST1427 | D861: PROD32 | E861: STORE4 | F861: 3 | G861: 918.76 | H861: 0.2 | I861: PayPal | J861: 2205.024
A862: SALE652 | B862: 45531 | C862: CUST1006 | D862: PROD39 | E862: STORE18 | F862: 2 | G862: 673.02 | H862: 0.11 | I862: PayPal | J862: 1197.9756
A863: SALE1083 | B863: 45531 | C863: CUST1385 | D863: PROD29 | E863: STORE16 | F863: 1 | G863: 850.06 | H863: 0.29 | I863: PayPal | J863: 603.5426
A864: SALE1220 | B864: 45531 | C864: CUST1313 | D864: PROD84 | E864: STORE7 | F864: 4 | G864: 450.83 | H864: 0.24 | I864: Credit Card | J864: 1370.5232
A865: SALE1622 | B865: 45531 | C865: CUST1468 | D865: PROD55 | E865: STORE16 | F865: 4 | G865: 570.38 | H865: 0.26 | I865: PayPal | J865: 1688.3248
A866: SALE826 | B866: 45532 | C866: CUST1287 | D866: PROD65 | E866: STORE4 | F866: 4 | G866: 277.58 | H866: 0.22 | I866: PayPal | J866: 866.0496
A867: SALE1361 | B867: 45532 | C867: CUST1188 | D867: PROD33 | E867: STORE19 | F867: 4 | G867: 885.57 | H867: 0.27 | I867: Credit Card | J867: 2585.8644
A868: SALE1652 | B868: 45532 | C868: CUST1426 | D868: PROD93 | E868: STORE15 | F868: 3 | G868: 199.13 | H868: 0.24 | I868: Credit Card | J868: 454.0164
... A934: SALE1821 | B934: 45554 | C934: CUST1147 | D934: PROD37 | E934: STORE8 | F934: 3 | G934: 204.17 | H934: 0.1 | I934: PayPal | J934: 551.259
A935: SALE268 | B935: 45555 | C935: CUST1406 | D935: PROD90 | E935: STORE18 | F935: 3 | G935: =INT(J935/(F935*(1-H935))) -> 111 | H935: 0.06 | I935: Credit Card | J935: 315.2478
A936: SALE436 | B936: 45555 | C936: CUST1053 | D936: PROD37 | E936: STORE12 | F936: 4 | G936: 747.56 | H936: 0.09 | I936: COD | J936: 2721.1184
A937: SALE606 | B937: 45555 | C937: CUST1029 | D937: PROD27 | E937: STORE8 | F937: 3 | G937: 827.88 | H937: 0.19 | I937: PayPal | J937: 2011.7484
A938: SALE1495 | B938: 45555 | C938: CUST1007 | D938: PROD13 | E938: STORE3 | F938: 3 | G938: 162.17 | H938: 0.15 | I938: PayPal | J938: 413.5335
A939: SALE1560 | B939: 45555 | C939: CUST1209 | D939: PROD48 | E939: STORE15 | F939: 1 | G939: 135.13 | H939: 0.04 | I939: Credit Card | J939: 129.7248
A940: SALE95 | B940: 45556 | C940: CUST1321 | D940: PROD99 | E940: STORE6 | F940: 2 | G940: 68.29 | H940: 0.14 | I940: COD | J940: 117.4588
A941: SALE295 | B941: 45556 | C941: CUST1211 | D941: PROD85 | E941: STORE17 | F941: 4 | G941: 626.35 | H941: 0.25 | I941: COD | J941: 1879.05
A942: SALE1155 | B942: 45556 | C942: CUST1340 | D942: PROD41 | E942: STORE5 | F942: 2 | G942: 20.47 | H942: 0.12 | I942: COD | J942: 36.0272
A943: SALE1742 | B943: 45556 | C943: CUST1293 | D943: PROD73 | E943: STORE3 | F943: 1 | G943: 24.13 | H943: 0 | I943: Credit Card | J943: 24.13
A944: SALE1849 | B944: 45556 | C944: CUST1299 | D944: PROD82 | E944: STORE1 | F944: 4 | G944: 740.5 | H944: 0.17 | I944: PayPal | J944: 2458.46
...

Sheet Customer_Cleaned
A1: Customer_ID | B1: Name | C1: Age | D1: Gender | E1: City | F1: State | G1: Country | H1: Loyalty_Level
A2: CUST1000 | B2: Sheena Bonilla | C2: 55 | D2: Male | E2: Donaldton | F2: North Carolina | G2: USA | H2: =IF(C2>=50,"Platinum",IF(C2>=35,"Silver","Bronze")) -> Platinum
A3: CUST1001 | B3: Eugene Nelson | C3: 26 | D3: Female | E3: Phillipsmouth | F3: North Dakota | G3: USA | H3: =IF(C3>=50,"Platinum",IF(C3>=35,"Silver","Bronze")) -> Bronze
A4: CUST1002 | B4: Dr. Benjamin Price | C4: 29 | D4: Female | E4: Kylebury | F4: Alabama | G4: USA | H4: =IF(C4>=50,"Platinum",IF(C4>=35,"Silver","Bronze")) -> Bronze
A5: CUST1003 | B5: Jeremy Harris | C5: 59 | D5: Female | E5: Thomastown | F5: Ohio | G5: USA | H5: =IF(C5>=50,"Platinum",IF(C5>=35,"Silver","Bronze")) -> Platinum
A6: CUST1004 | B6: Caroline Collins | C6: 64 | D6: Female | E6: Nicholasshire | F6: California | G6: USA | H6: =IF(C6>=50,"Platinum",IF(C6>=35,"Silver","Bronze")) -> Platinum
A7: CUST1005 | B7: Christine Vaughn | C7: 24 | D7: Male | E7: East Amandamouth | F7: Oregon | G7: USA | H7: =IF(C7>=50,"Platinum",IF(C7>=35,"Silver","Bronze")) -> Bronze
A8: CUST1006 | B8: Amber Jackson | C8: 29 | D8: Female | E8: Deborahborough | F8: South Dakota | G8: USA | H8: =IF(C8>=50,"Platinum",IF(C8>=35,"Silver","Bronze")) -> Bronze
A9: CUST1007 | B9: Daniel Boyd | C9: 29 | D9: Female | E9: West Pamelafurt | F9: West Virginia | G9: USA | H9: =IF(C9>=50,"Platinum",IF(C9>=35,"Silver","Bronze")) -> Bronze
A10: CUST1008 | B10: Melissa Howard | C10: 53 | D10: Female | E10: Maynardton | F10: New Hampshire | G10: USA | H10: =IF(C10>=50,"Platinum",IF(C10>=35,"Silver","Bronze")) -> Platinum
A11: CUST1009 | B11: Ms. Maria Leach | C11: 64 | D11: Male | E11: Melissashire | F11: Pennsylvania | G11: USA | H11: =IF(C11>=50,"Platinum",IF(C11>=35,"Silver","Bronze")) -> Platinum
A12: CUST1010 | B12: Dominic Page | C12: 53 | D12: Male | E12: Port Michaelburgh | F12: Pennsylvania | G12: USA | H12: =IF(C12>=50,"Platinum",IF(C12>=35,"Silver","Bronze")) -> Platinum
A13: CUST1011 | B13: Brian Lopez | C13: 28 | D13: Female | E13: East Krista | F13: New York | G13: USA | H13: =IF(C13>=50,"Platinum",IF(C13>=35,"Silver","Bronze")) -> Bronze
... A501: CUST1499 | B501: Philip Pennington | C501: 27 | D501: Female | E501: East Valerieview | F501: Oregon | G501: USA | H501: =IF(C501>=50,"Platinum",IF(C501>=35,"Silver","Bronze")) -> Bronze

Sheet Product_Cleaned
A1: Product_ID | B1: Product_Name | C1: Category | D1: Sub_Category | E1: Brand | F1: Cost | G1: Stock
A2: PROD0 | B2: Brother Laser Printer | C2: Electronics | D2: Computer | E2: Hunt Inc | F2: 112 | G2: 416
A3: PROD26 | B3: Wireless Bluetooth Speaker | C3: Electronics | D3: Audio | E3: Reed-Schmidt | F3: 322 | G3: 213
A4: PROD34 | B4: Gaming Mechanical Keyboard | C4: Electronics | D4: Computer | E4: Lucero LLC | F4: 419 | G4: 86
A5: PROD39 | B5: Portable Power Bank | C5: Electronics | D5: Mobile | E5: Cummings and Sons | F5: 326 | G5: 301
A6: PROD40 | B6: Noise-Canceling Headphones | C6: Electronics | D6: Audio | E6: Taylor-Hart | F6: 38 | G6: 378
A7: PROD42 | B7: Smart Home WiFi Camera | C7: Electronics | D7: Accessories | E7: Holmes LLC | F7: 450 | G7: 389
A8: PROD43 | B8: USB External Hard Drive | C8: Electronics | D8: Computer | E8: Robinson Inc | F8: 253 | G8: 266
A9: PROD48 | B9: Car Dashboard Phone Holder | C9: Electronics | D9: Accessories | E9: Byrd, Stewart and Valdez | F9: 177 | G9: 103
A10: PROD51 | B10: HDMI Cable – 2m | C10: Electronics | D10: Accessories | E10: Bautista, Green and Hale | F10: 88 | G10: 246
A11: PROD62 | B11: Laptop Cooling Pad | C11: Electronics | D11: Computer | E11: Murray, Gould and Ware | F11: 86 | G11: 222
A12: PROD67 | B12: Smart LED Light Strip | C12: Electronics | D12: Accessories | E12: Flores-Davis | F12: 349 | G12: 476
A13: PROD74 | B13: Bluetooth Car Audio System | C13: Electronics | D13: Audio | E13: Bruce-Bowen | F13: 403 | G13: 159
... A18: PROD98 | B18: Portable Bluetooth Speaker | C18: Electronics | D18: Audio | E18: Flores-King | F18: 431 | G18: 73
A19: PROD1 | B19: Men's Graphic T-Shirt | C19: Clothing | D19: Tops | E19: Terry-Moore | F19: 342 | G19: 181
A20: PROD2 | B20: Women's Casual Hoodie | C20: Clothing | D20: Outerwear | E20: Sims Inc | F20: 254 | G20: 352
A21: PROD3 | B21: Men's Running Jacket | C21: Clothing | D21: Outerwear | E21: Pineda Ltd | F21: 364 | G21: 452
A22: PROD4 | B22: Women's Yoga Pants | C22: Clothing | D22: Bottoms | E22: Gonzales-Davis | F22: 306 | G22: 487
A23: PROD5 | B23: Men's Leather Belt | C23: Clothing | D23: Accessories | E23: Baldwin, Garza and Gonzalez | F23: 261 | G23: 59
A24: PROD6 | B24: Herbal Face Moisturizer | C24: Beauty | D24: Skincare | E24: Davidson PLC | F24: 312 | G24: 343
A25: PROD7 | B25: LED Table Lamp | C25: Home | D25: Lighting | E25: Harrell LLC | F25: 218 | G25: 360
A26: PROD8 | B26: Wireless Bluetooth Earbuds | C26: Electronics | D26: Audio | E26: Perez-Johnston | F26: 439 | G26: 268
A27: PROD9 | B27: Adjustable Dumbbell Set | C27: Sports | D27: Fitness | E27: Hill PLC | F27: 495 | G27: 154
A28: PROD10 | B28: Ceramic Kitchen Bowl Set | C28: Home | D28: Kitchen | E28: Hamilton Group | F28: 298 | G28: 214
A29: PROD11 | B29: HD Smart TV Stick | C29: Electronics | D29: Accessories | E29: Gibson, Hobbs and Weaver | F29: 449 | G29: 296
A30: PROD12 | B30: Hair Strengthening Shampoo | C30: Beauty | D30: Haircare | E30: Rice LLC | F30: 115 | G30: 125
A31: PROD13 | B31: USB-C Fast Charger | C31: Electronics | D31: Accessories | E31: Dawson-Perkins | F31: 242 | G31: 485
A32: PROD14 | B32: Decorative Wall Mirror | C32: Home | D32: Decor | E32: Luna, Anderson and Bowman | F32: 48 | G32: 224
A33: PROD15 | B33: 4K Home Projector | C33: Electronics | D33: Appliances | E33: Thomas LLC | F33: 465 | G33: 82
A34: PROD16 | B34: Beard Grooming Kit | C34: Beauty | D34: Grooming | E34: Erickson-Green | F34: 337 | G34: 210
A35: PROD17 | B35: Soccer Training Cone Set | C35: Sports | D35: Accessories | E35: Ford, Murphy and Wilson | F35: 144 | G35: 496
A36: PROD18 | B36: Women's Denim Jeans | C36: Clothing | D36: Bottoms | E36: Guerra-Hendrix | F36: 254 | G36: 343
A37: PROD19 | B37: Knee Support Brace | C37: Sports | D37: Equipment | E37: May-Reese | F37: 21 | G37: 65
A38: PROD20 | B38: Outdoor Sports Water Bottle | C38: Sports | D38: Accessories | E38: Soto-Ellis | F38: 131 | G38: 268
A39: PROD21 | B39: Multi-Purpose Storage Box | C39: Home | D39: Storage | E39: Gardner-Montes | F39: 123 | G39: 76
A40: PROD22 | B40: Carbon Fiber Tennis Racket | C40: Sports | D40: Equipment | E40: Flores, Pineda and Rodriguez | F40: 484 | G40: 432
A41: PROD23 | B41: Men's Formal Shirt | C41: Clothing | D41: Tops | E41: Moon, Mora and Santos | F41: 254 | G41: 360
A42: PROD24 | B42: Foldable Camping Chair | C42: Sports | D42: Outdoor | E42: Cook Ltd | F42: 166 | G42: 340
A43: PROD25 | B43: Women's Scarf Set | C43: Clothing | D43: Accessories | E43: Brown and Sons | F43: 174 | G43: 268
A44: PROD27 | B44: Decorative Floor Vase | C44: Home | D44: Decor | E44: Khan, Jones and Paul | F44: 254 | G44: 378
A45: PROD28 | B45: Sports Stopwatch Timer | C45: Sports | D45: Accessories | E45: Burns-Hansen | F45: 38 | G45: 137
A46: PROD29 | B46: Fabric Sofa Throw Blanket | C46: Home | D46: Decor | E46: Hoffman Group | F46: 218 | G46: 276
A47: PROD30 | B47: Stainless Steel Cutlery Set | C47: Home | D47: Kitchen | E47: Stevens, Fernandez and Martin | F47: 19 | G47: 57
A48: PROD31 | B48: Basketball | C48: Sports | D48: Team Sports | E48: Nolan-Snow | F48: 204 | G48: 281
A49: PROD32 | B49: Vitamin C Face Serum | C49: Beauty | D49: Skincare | E49: Griffin Ltd | F49: 283 | G49: 244
A50: PROD33 | B50: Modern Wall Clock | C50: Home | D50: Decor | E50: Weiss-Watson | F50: 179 | G50: 305
A51: PROD35 | B51: Bedroom Table Lamp | C51: Home | D51: Lighting | E51: Jones LLC | F51: 382 | G51: 329
A52: PROD36 | B52: Women's Summer Dress | C52: Clothing | D52: Tops | E52: Smith-Mills | F52: 223 | G52: 154
A53: PROD37 | B53: Men's Casual Sneakers | C53: Clothing | D53: Footwear | E53: Hogan-Lee | F53: 353 | G53: 214
A54: PROD38 | B54: Sports Water Hydration Pack | C54: Sports | D54: Outdoor | E54: Sims-Smith | F54: 135 | G54: 394
A55: PROD41 | B55: Yoga Exercise Mat | C55: Sports | D55: Fitness | E55: Carroll, Long and Mendoza | F55: 313 | G55: 369
A56: PROD44 | B56: Adjustable Jump Rope | C56: Sports | D56: Fitness | E56: Cox Inc | F56: 167 | G56: 316
A57: PROD45 | B57: High-Grip Football | C57: Sports | D57: Team Sports | E57: Bridges, Banks and Cummings | F57: 318 | G57: 114
A58: PROD46 | B58: Men's Winter Jacket | C58: Clothing | D58: Outerwear | E58: Kelly, Smith and Perez | F58: 167 | G58: 296
A59: PROD47 | B59: Makeup Brush Set | C59: Beauty | D59: Makeup | E59: Cook Inc | F59: 254 | G59: 431
A60: PROD49 | B60: Men's Roll-On Perfume | C60: Beauty | D60: Fragrance | E60: Sullivan and Sons | F60: 43 | G60: 267
A61: PROD50 | B61: Boxing Hand Wraps | C61: Sports | D61: Fitness | E61: Smith-King | F61: 190 | G61: 260
A62: PROD52 | B62: Rugby Ball | C62: Sports | D62: Team Sports | E62: Harris Inc | F62: 212 | G62: 82
A63: PROD53 | B63: Men's Track Pants | C63: Clothing | D63: Bottoms | E63: Hamilton, Woods and Walker | F63: 386 | G63: 125
A64: PROD54 | B64: Sports Stopwatch Pro | C64: Sports | D64: Accessories | E64: Thompson-French | F64: 434 | G64: 185
A65: PROD55 | B65: Ceramic Plant Pot | C65: Home | D65: Decor | E65: Hatfield, Baird and Torres | F65: 81 | G65: 269
A66: PROD56 | B66: Premium Blanket Throw | C66: Home | D66: Decor | E66: Hernandez, Kennedy and Porter | F66: 461 | G66: 190
A67: PROD57 | B67: Foam Roller | C67: Sports | D67: Fitness | E67: Atkinson, Camacho and Oliver | F67: 30 | G67: 138
A68: PROD58 | B68: Womens Cotton Scarf | C68: Clothing | D68: Accessories | E68: Shepherd-Gould | F68: 113 | G68: 485
A69: PROD59 | B69: Men's Hair Styling Gel | C69: Beauty | D69: Haircare | E69: Cline-Mccarthy | F69: 17 | G69: 399
A70: PROD60 | B70: Luxury Perfume Spray | C70: Beauty | D70: Fragrance | E70: Gibson, Green and Lopez | F70: 482 | G70: 444
A71: PROD61 | B71: Tennis Ball 3-Pack | C71: Sports | D71: Equipment | E71: Lopez LLC | F71: 103 | G71: 465
A72: PROD63 | B72: Organic Sunscreen Lotion | C72: Beauty | D72: Skincare | E72: Anderson-Riley | F72: 266 | G72: 458
A73: PROD64 | B73: Matte Lipstick Set | C73: Beauty | D73: Makeup | E73: Zhang Inc | F73: 299 | G73: 118
A74: PROD65 | B74: Adjustable Dumbbells 20kg | C74: Sports | D74: Fitness | E74: Montgomery, Benton and Miller | F74: 240 | G74: 423
A75: PROD66 | B75: Women's Hair Dryer Brush | C75: Beauty | D75: Haircare | E75: Torres, Spencer and Potter | F75: 340 | G75: 177
A76: PROD68 | B76: Wooden Nightstand | C76: Home | D76: Furniture | E76: Wolfe, Ross and Hester | F76: 243 | G76: 130
A77: PROD69 | B77: Men's Sports Shorts | C77: Clothing | D77: Bottoms | E77: Fitzpatrick Ltd | F77: 218 | G77: 224
A78: PROD70 | B78: Kitchen Storage Rack | C78: Home | D78: Storage | E78: Duran Group | F78: 138 | G78: 89
A79: PROD71 | B79: Hair Repair Oil Treatment | C79: Beauty | D79: Haircare | E79: Hopkins Ltd | F79: 214 | G79: 383
A80: PROD72 | B80: Professional Jump Rope | C80: Sports | D80: Fitness | E80: Davis PLC | F80: 477 | G80: 300
A81: PROD73 | B81: Shin Guards – Adult | C81: Sports | D81: Team Sports | E81: French Ltd | F81: 107 | G81: 359
A82: PROD75 | B82: Women's Ankle Boots | C82: Clothing | D82: Footwear | E82: Poole PLC | F82: 158 | G82: 82
A83: PROD78 | B83: Essential Oil Diffuser | C83: Home | D83: Decor | E83: Hernandez Inc | F83: 325 | G83: 400
A84: PROD79 | B84: Decorative Lamp Shade | C84: Home | D84: Lighting | E84: Ramirez-Hanson | F84: 228 | G84: 469
A85: PROD80 | B85: Wall-Mounted Spice Rack | C85: Home | D85: Kitchen | E85: Allison Ltd | F85: 143 | G85: 58
A86: PROD81 | B86: Badminton Racket Set | C86: Sports | D86: Equipment | E86: Robinson-Brown | F86: 285 | G86: 358
A87: PROD82 | B87: Fitness Resistance Bands | C87: Sports | D87: Fitness | E87: Reese-Watson | F87: 152 | G87: 281
A88: PROD83 | B88: Hydrating Face Cleanser | C88: Beauty | D88: Skincare | E88: Butler Group | F88: 254 | G88: 159
A89: PROD84 | B89: Wooden Bookshelf | C89: Home | D89: Furniture | E89: Collins-Stephenson | F89: 388 | G89: 208
A90: PROD85 | B90: Women's Beanie Hat | C90: Clothing | D90: Accessories | E90: Richardson-Carrillo | F90: 119 | G90: 210
A91: PROD86 | B91: Kitchen Cutting Board | C91: Home | D91: Kitchen | E91: Taylor, Dodson and Johnston | F91: 176 | G91: 82
A92: PROD87 | B92: LED Bedside Lamp | C92: Home | D92: Lighting | E92: Aguilar, Horton and Lewis | F92: 371 | G92: 220
A93: PROD88 | B93: Sports Wrist Sweatbands | C93: Sports | D93: Accessories | E93: Olsen-Daniels | F93: 131 | G93: 232
A94: PROD89 | B94: Face Foundation Kit | C94: Beauty | D94: Makeup | E94: Taylor-Elliott | F94: 183 | G94: 457
A95: PROD91 | B95: Women's High Heels | C95: Clothing | D95: Footwear | E95: Smith-Charles | F95: 438 | G95: 496
A96: PROD92 | B96: Microwave Oven | C96: Home | D96: Appliances | E96: Green, Powell and Palmer | F96: 447 | G96: 191
A97: PROD94 | B97: Vitamin E Body Lotion | C97: Beauty | D97: Skincare | E97: Hoffman-Williams | F97: 358 | G97: 213
A98: PROD95 | B98: Sports Stopwatch Basic | C98: Sports | D98: Accessories | E98: Wilson Group | F98: 60 | G98: 75
A99: PROD96 | B99: Women's Formal Blazer | C99: Clothing | D99: Outerwear | E99: Phillips and Sons | F99: 358 | G99: 143
A100: PROD97 | B100: Cricket Bat | C100: Sports | D100: Team Sports | E100: Khan LLC | F100: 245 | G100: 471
A101: PROD99 | B101: Stainless Steel Cookware Set | C101: Home | D101: Kitchen | E101: Campbell Ltd | F101: 201 | G101: 146

Sheet Sales_Fact cleaned
A1: Order_Date | B1: Customer_ID | C1: Product_ID | D1: Product_Name | E1: Category | F1: Sub_Category | G1: Brand | H1: Store_ID | I1: Store_Name | J1: Region | K1: City | L1: Store_Type | M1: Name | N1: Age | O1: Gender | P1: Loyalty_Level | Q1: State | R1: Country | S1: Quantity | T1: Unit_Price | U1: Discount | V1: Total_Amount | W1: Payment_Type
A2: 45213 | B2: CUST1181 | C2: PROD81 | D2: =VLOOKUP(C2,Product_Cleaned!$A$2:$B$101,2,FALSE) -> Badminton Racket Set | E2: =VLOOKUP(C2,Product_Cleaned!$A$2:$C$101,3,FALSE) -> Sports | F2: =VLOOKUP(C2,Product_Cleaned!$A$2:$E$101,4,FALSE) -> Equipment | G2: =VLOOKUP('Sales_Fact cleaned'!C698,Product_Cleaned!$A$2:$E$101,5, FALSE) -> Green, Powell and Palmer | H2: STORE7 | I2: =_xlfn.XLOOKUP(H2,Store_Raw!$A$2:$A$21,Store_Raw!$B$2:$B$21) -> Martinez-Mullins | J2: =_xlfn.XLOOKUP(H2,Store_Raw!$A$2:$A$21,Store_Raw!$C$2:$C$21) -> South | K2: =_xlfn.XLOOKUP(H2,Store_Raw!$A$2:$A$21,Store_Raw!$D$2:$D$21) -> Williamsfurt | L2: =_xlfn.XLOOKUP(H2,Store_Raw!$A$2:$A$21,Store_Raw!$E$2:$E$21) -> Online | M2: =VLOOKUP(B2,Customer_Cleaned!$A$2:$H$501,2,FALSE) -> Erin Ward | N2: =VLOOKUP(B2,Customer_Cleaned!$A$2:$H$501,3,FALSE) -> 60 | O2: =VLOOKUP(B2,Customer_Cleaned!$A$2:$H$501,4,FALSE) -> Male | P2: =VLOOKUP(B2,Customer_Cleaned!$A$2:$H$501,8,FALSE) -> Platinum | Q2: =_xlfn.XLOOKUP('Sales_Fact cleaned'!B698,Customer_Cleaned!$A$2:$A$501,Customer_Cleaned!$F$2:$F$501) -> Missouri | R2: =_xlfn.XLOOKUP(B2,Customer_Cleaned!$A$2:$A$501,Customer_Cleaned!$G$2:$G$501) -> USA | S2: 1 | T2: 26.37 | U2: 0.3 | V2: 18.459 | W2: Credit Card
A3: 45213 | B3: CUST1089 | C3: PROD20 | D3: =VLOOKUP(C3,Product_Cleaned!$A$2:$B$101,2,FALSE) -> Outdoor Sports Water Bottle | E3: =VLOOKUP(C3,Product_Cleaned!$A$2:$C$101,3,FALSE) -> Sports | F3: =VLOOKUP(C3,Product_Cleaned!$A$2:$E$101,4,FALSE) -> Accessories | G3: =VLOOKUP('Sales_Fact cleaned'!C1502,Product_Cleaned!$A$2:$E$101,5, FALSE) -> Harris Inc | H3: STORE18 | I3: =_xlfn.XLOOKUP(H3,Store_Raw!$A$2:$A$21,Store_Raw!$B$2:$B$21) -> Guerrero-Schmitt | J3: =_xlfn.XLOOKUP(H3,Store_Raw!$A$2:$A$21,Store_Raw!$C$2:$C$21) -> East | K3: =_xlfn.XLOOKUP(H3,Store_Raw!$A$2:$A$21,Store_Raw!$D$2:$D$21) -> East Stevechester | L3: =_xlfn.XLOOKUP(H3,Store_Raw!$A$2:$A$21,Store_Raw!$E$2:$E$21) -> Flagship | M3: =VLOOKUP(B3,Customer_Cleaned!$A$2:$H$501,2,FALSE) -> Jamie Yoder | N3: =VLOOKUP(B3,Customer_Cleaned!$A$2:$H$501,3,FALSE) -> 43 | O3: =VLOOKUP(B3,Customer_Cleaned!$A$2:$H$501,4,FALSE) -> Male | P3: =VLOOKUP(B3,Customer_Cleaned!$A$2:$H$501,8,FALSE) -> Silver | Q3: =_xlfn.XLOOKUP('Sales_Fact cleaned'!B1502,Customer_Cleaned!$A$2:$A$501,Customer_Cleaned!$F$2:$F$501) -> Pennsylvania | R3: =_xlfn.XLOOKUP(B3,Customer_Cleaned!$A$2:$A$501,Customer_Cleaned!$G$2:$G$501) -> USA | S3: 1 | T3: 27.83 | U3: 0.3 | V3: 19.481 | W3: Credit Card
A4: 45213 | B4: CUST1343 | C4: PROD38 | D4: =VLOOKUP(C4,Product_Cleaned!$A$2:$B$101,2,FALSE) -> Sports Water Hydration Pack | E4: =VLOOKUP(C4,Product_Cleaned!$A$2:$C$101,3,FALSE) -> Sports | F4: =VLOOKUP(C4,Product_Cleaned!$A$2:$E$101,4,FALSE) -> Outdoor | G4: =VLOOKUP('Sales_Fact cleaned'!C1500,Product_Cleaned!$A$2:$E$101,5, FALSE) -> Larson Ltd | H4: STORE12 | I4: =_xlfn.XLOOKUP(H4,Store_Raw!$A$2:$A$21,Store_Raw!$B$2:$B$21) -> Thomas, Bridges and Harris | J4: =_xlfn.XLOOKUP(H4,Store_Raw!$A$2:$A$21,Store_Raw!$C$2:$C$21) -> North | K4: =_xlfn.XLOOKUP(H4,Store_Raw!$A$2:$A$21,Store_Raw!$D$2:$D$21) -> Sabrinatown | L4: =_xlfn.XLOOKUP(H4,Store_Raw!$A$2:$A$21,Store_Raw!$E$2:$E$21) -> Online | M4: =VLOOKUP(B4,Customer_Cleaned!$A$2:$H$501,2,FALSE) -> Ryan Moore | N4: =VLOOKUP(B4,Customer_Cleaned!$A$2:$H$501,3,FALSE) -> 38 | O4: =VLOOKUP(B4,Customer_Cleaned!$A$2:$H$501,4,FALSE) -> Male | P4: =VLOOKUP(B4,Customer_Cleaned!$A$2:$H$501,8,FALSE) -> Silver | Q4: =_xlfn.XLOOKUP('Sales_Fact cleaned'!B1500,Customer_Cleaned!$A$2:$A$501,Customer_Cleaned!$F$2:$F$501) -> North Dakota | R4: =_xlfn.XLOOKUP(B4,Customer_Cleaned!$A$2:$A$501,Customer_Cleaned!$G$2:$G$501) -> USA | S4: 1 | T4: 21.14 | U4: 0.06 | V4: 19.8716 | W4: PayPal
A5: 45214 | B5: CUST1293 | C5: PROD73 | D5: =VLOOKUP(C5,Product_Cleaned!$A$2:$B$101,2,FALSE) -> Shin Guards – Adult | E5: =VLOOKUP(C5,Product_Cleaned!$A$2:$C$101,3,FALSE) -> Sports | F5: =VLOOKUP(C5,Product_Cleaned!$A$2:$E$101,4,FALSE) -> Team Sports | G5: =VLOOKUP('Sales_Fact cleaned'!C943,Product_Cleaned!$A$2:$E$101,5, FALSE) -> Montgomery, Benton and Miller | H5: STORE3 | I5: =_xlfn.XLOOKUP(H5,Store_Raw!$A$2:$A$21,Store_Raw!$B$2:$B$21) -> Johnson-Wright | J5: =_xlfn.XLOOKUP(H5,Store_Raw!$A$2:$A$21,Store_Raw!$C$2:$C$21) -> North | K5: =_xlfn.XLOOKUP(H5,Store_Raw!$A$2:$A$21,Store_Raw!$D$2:$D$21) -> Hoodberg | L5: =_xlfn.XLOOKUP(H5,Store_Raw!$A$2:$A$21,Store_Raw!$E$2:$E$21) -> Outlet | M5: =VLOOKUP(B5,Customer_Cleaned!$A$2:$H$501,2,FALSE) -> Gloria Taylor | N5: =VLOOKUP(B5,Customer_Cleaned!$A$2:$H$501,3,FALSE) -> 56 | O5: =VLOOKUP(B5,Customer_Cleaned!$A$2:$H$501,4,FALSE) -> Female | P5: =VLOOKUP(B5,Customer_Cleaned!$A$2:$H$501,8,FALSE) -> Platinum | Q5: =_xlfn.XLOOKUP('Sales_Fact cleaned'!B943,Customer_Cleaned!$A$2:$A$501,Customer_Cleaned!$F$2:$F$501) -> Kansas | R5: =_xlfn.XLOOKUP(B5,Customer_Cleaned!$A$2:$A$501,Customer_Cleaned!$G$2:$G$501) -> USA | S5: 1 | T5: 24.13 | U5: 0 | V5: 24.13 | W5: Credit Card
A6: 45214 | B6: CUST1384 | C6: PROD74 | D6: =VLOOKUP(C6,Product_Cleaned!$A$2:$B$101,2,FALSE) -> Bluetooth Car Audio System | E6: =VLOOKUP(C6,Product_Cleaned!$A$2:$C$101,3,FALSE) -> Electronics | F6: =VLOOKUP(C6,Product_Cleaned!$A$2:$E$101,4,FALSE) -> Audio | G6: =VLOOKUP('Sales_Fact cleaned'!C1792,Product_Cleaned!$A$2:$E$101,5, FALSE) -> Anderson-Riley | H6: STORE10 | I6: =_xlfn.XLOOKUP(H6,Store_Raw!$A$2:$A$21,Store_Raw!$B$2:$B$21) -> Hill, Wagner and Ballard | J6: =_xlfn.XLOOKUP(H6,Store_Raw!$A$2:$A$21,Store_Raw!$C$2:$C$21) -> East | K6: =_xlfn.XLOOKUP(H6,Store_Raw!$A$2:$A$21,Store_Raw!$D$2:$D$21) -> East Davidville | L6: =_xlfn.XLOOKUP(H6,Store_Raw!$A$2:$A$21,Store_Raw!$E$2:$E$21) -> Online | M6: =VLOOKUP(B6,Customer_Cleaned!$A$2:$H$501,2,FALSE) -> Andrew Mason | N6: =VLOOKUP(B6,Customer_Cleaned!$A$2:$H$501,3,FALSE) -> 52 | O6: =VLOOKUP(B6,Customer_Cleaned!$A$2:$H$501,4,FALSE) -> Female | P6: =VLOOKUP(B6,Customer_Cleaned!$A$2:$H$501,8,FALSE) -> Platinum | Q6: =_xlfn.XLOOKUP('Sales_Fact cleaned'!B1792,Customer_Cleaned!$A$2:$A$501,Customer_Cleaned!$F$2:$F$501) -> Nebraska | R6: =_xlfn.XLOOKUP(B6,Customer_Cleaned!$A$2:$A$501,Customer_Cleaned!$G$2:$G$501) -> USA | S6: 1 | T6: 30.94 | U6: 0.21 | V6: 24.4426 | W6: COD
A7: 45215 | B7: CUST1241 | C7: PROD15 | D7: =VLOOKUP(C7,Product_Cleaned!$A$2:$B$101,2,FALSE) -> 4K Home Projector | E7: =VLOOKUP(C7,Product_Cleaned!$A$2:$C$101,3,FALSE) -> Electronics | F7: =VLOOKUP(C7,Product_Cleaned!$A$2:$E$101,4,FALSE) -> Appliances | G7: =VLOOKUP('Sales_Fact cleaned'!C463,Product_Cleaned!$A$2:$E$101,5, FALSE) -> Hernandez Inc | H7: STORE14 | I7: =_xlfn.XLOOKUP(H7,Store_Raw!$A$2:$A$21,Store_Raw!$B$2:$B$21) -> Mcdonald Inc | J7: =_xlfn.XLOOKUP(H7,Store_Raw!$A$2:$A$21,Store_Raw!$C$2:$C$21) -> South | K7: =_xlfn.XLOOKUP(H7,Store_Raw!$A$2:$A$21,Store_Raw!$D$2:$D$21) -> Christopherland | L7: =_xlfn.XLOOKUP(H7,Store_Raw!$A$2:$A$21,Store_Raw!$E$2:$E$21) -> Outlet | M7: =VLOOKUP(B7,Customer_Cleaned!$A$2:$H$501,2,FALSE) -> Mr. William Horton | N7: =VLOOKUP(B7,Customer_Cleaned!$A$2:$H$501,3,FALSE) -> 31 | O7: =VLOOKUP(B7,Customer_Cleaned!$A$2:$H$501,4,FALSE) -> Male | P7: =VLOOKUP(B7,Customer_Cleaned!$A$2:$H$501,8,FALSE) -> Bronze | Q7: =_xlfn.XLOOKUP('Sales_Fact cleaned'!B463,Customer_Cleaned!$A$2:$A$501,Customer_Cleaned!$F$2:$F$501) -> New Mexico | R7: =_xlfn.XLOOKUP(B7,Customer_Cleaned!$A$2:$A$501,Customer_Cleaned!$G$2:$G$501) -> USA | S7: 1 | T7: 31.36 | U7: 0.21 | V7: 24.7744 | W7: Credit Card
A8: 45215 | B8: CUST1105 | C8: PROD57 | D8: =VLOOKUP(C8,Product_Cleaned!$A$2:$B$101,2,FALSE) -> Foam Roller | E8: =VLOOKUP(C8,Product_Cleaned!$A$2:$C$101,3,FALSE) -> Sports | F8: =VLOOKUP(C8,Product_Cleaned!$A$2:$E$101,4,FALSE) -> Fitness | G8: =VLOOKUP('Sales_Fact cleaned'!C1317,Product_Cleaned!$A$2:$E$101,5, FALSE) -> Robinson-Brown | H8: STORE3 | I8: =_xlfn.XLOOKUP(H8,Store_Raw!$A$2:$A$21,Store_Raw!$B$2:$B$21) -> Johnson-Wright | J8: =_xlfn.XLOOKUP(H8,Store_Raw!$A$2:$A$21,Store_Raw!$C$2:$C$21) -> North | K8: =_xlfn.XLOOKUP(H8,Store_Raw!$A$2:$A$21,Store_Raw!$D$2:$D$21) -> Hoodberg | L8: =_xlfn.XLOOKUP(H8,Store_Raw!$A$2:$A$21,Store_Raw!$E$2:$E$21) -> Outlet | M8: =VLOOKUP(B8,Customer_Cleaned!$A$2:$H$501,2,FALSE) -> Lance Baker | N8: =VLOOKUP(B8,Customer_Cleaned!$A$2:$H$501,3,FALSE) -> 50 | O8: =VLOOKUP(B8,Customer_Cleaned!$A$2:$H$501,4,FALSE) -> Female | P8: =VLOOKUP(B8,Customer_Cleaned!$A$2:$H$501,8,FALSE) -> Platinum | Q8: =_xlfn.XLOOKUP('Sales_Fact cleaned'!B1317,Customer_Cleaned!$A$2:$A$501,Customer_Cleaned!$F$2:$F$501) -> New Hampshire | R8: =_xlfn.XLOOKUP(B8,Customer_Cleaned!$A$2:$A$501,Customer_Cleaned!$G$2:$G$501) -> USA | S8: 1 | T8: 38.95 | U8: 0.28 | V8: 28.044 | W8: Credit Card
A9: 45216 | B9: CUST1104 | C9: PROD31 | D9: =VLOOKUP(C9,Product_Cleaned!$A$2:$B$101,2,FALSE) -> Basketball | E9: =VLOOKUP(C9,Product_Cleaned!$A$2:$C$101,3,FALSE) -> Sports | F9: =VLOOKUP(C9,Product_Cleaned!$A$2:$E$101,4,FALSE) -> Team Sports | G9: =VLOOKUP('Sales_Fact cleaned'!C1421,Product_Cleaned!$A$2:$E$101,5, FALSE) -> Allison Ltd | H9: STORE3 | I9: =_xlfn.XLOOKUP(H9,Store_Raw!$A$2:$A$21,Store_Raw!$B$2:$B$21) -> Johnson-Wright | J9: =_xlfn.XLOOKUP(H9,Store_Raw!$A$2:$A$21,Store_Raw!$C$2:$C$21) -> North | K9: =_xlfn.XLOOKUP(H9,Store_Raw!$A$2:$A$21,Store_Raw!$D$2:$D$21) -> Hoodberg | L9: =_xlfn.XLOOKUP(H9,Store_Raw!$A$2:$A$21,Store_Raw!$E$2:$E$21) -> Outlet | M9: =VLOOKUP(B9,Customer_Cleaned!$A$2:$H$501,2,FALSE) -> Christopher Lester | N9: =VLOOKUP(B9,Customer_Cleaned!$A$2:$H$501,3,FALSE) -> 64 | O9: =VLOOKUP(B9,Customer_Cleaned!$A$2:$H$501,4,FALSE) -> Male | P9: =VLOOKUP(B9,Customer_Cleaned!$A$2:$H$501,8,FALSE) -> Platinum | Q9: =_xlfn.XLOOKUP('Sales_Fact cleaned'!B1421,Customer_Cleaned!$A$2:$A$501,Customer_Cleaned!$F$2:$F$501) -> Pennsylvania | R9: =_xlfn.XLOOKUP(B9,Customer_Cleaned!$A$2:$A$501,Customer_Cleaned!$G$2:$G$501) -> USA | S9: 1 | T9: 36.8 | U9: 0.18 | V9: 30.176 | W9: COD
A10: 45216 | B10: CUST1377 | C10: PROD78 | D10: =VLOOKUP(C10,Product_Cleaned!$A$2:$B$101,2,FALSE) -> Essential Oil Diffuser | E10: =VLOOKUP(C10,Product_Cleaned!$A$2:$C$101,3,FALSE) -> Home | F10: =VLOOKUP(C10,Product_Cleaned!$A$2:$E$101,4,FALSE) -> Decor | G10: =VLOOKUP('Sales_Fact cleaned'!C387,Product_Cleaned!$A$2:$E$101,5, FALSE) -> Moon, Mora and Santos | H10: STORE4 | I10: =_xlfn.XLOOKUP(H10,Store_Raw!$A$2:$A$21,Store_Raw!$B$2:$B$21) -> Alexander Group | J10: =_xlfn.XLOOKUP(H10,Store_Raw!$A$2:$A$21,Store_Raw!$C$2:$C$21) -> South | K10: =_xlfn.XLOOKUP(H10,Store_Raw!$A$2:$A$21,Store_Raw!$D$2:$D$21) -> Port Sharon | L10: =_xlfn.XLOOKUP(H10,Store_Raw!$A$2:$A$21,Store_Raw!$E$2:$E$21) -> Online | M10: =VLOOKUP(B10,Customer_Cleaned!$A$2:$H$501,2,FALSE) -> Charles Conley | N10: =VLOOKUP(B10,Customer_Cleaned!$A$2:$H$501,3,FALSE) -> 39 | O10: =VLOOKUP(B10,Customer_Cleaned!$A$2:$H$501,4,FALSE) -> Female | P10: =VLOOKUP(B10,Customer_Cleaned!$A$2:$H$501,8,FALSE) -> Silver | Q10: =_xlfn.XLOOKUP('Sales_Fact cleaned'!B387,Customer_Cleaned!$A$2:$A$501,Customer_Cleaned!$F$2:$F$501) -> Arkansas | R10: =_xlfn.XLOOKUP(B10,Customer_Cleaned!$A$2:$A$501,Customer_Cleaned!$G$2:$G$501) -> USA | S10: 1 | T10: 34.71 | U10: 0.1 | V10: 31.239 | W10: COD
A11: 45217 | B11: CUST1007 | C11: PROD5 | D11: =VLOOKUP(C11,Product_Cleaned!$A$2:$B$101,2,FALSE) -> Men's Leather Belt | E11: =VLOOKUP(C11,Product_Cleaned!$A$2:$C$101,3,FALSE) -> Clothing | F11: =VLOOKUP(C11,Product_Cleaned!$A$2:$E$101,4,FALSE) -> Accessories | G11: =VLOOKUP('Sales_Fact cleaned'!C1570,Product_Cleaned!$A$2:$E$101,5, FALSE) -> Dawson-Perkins | H11: STORE14 | I11: =_xlfn.XLOOKUP(H11,Store_Raw!$A$2:$A$21,Store_Raw!$B$2:$B$21) -> Mcdonald Inc | J11: =_xlfn.XLOOKUP(H11,Store_Raw!$A$2:$A$21,Store_Raw!$C$2:$C$21) -> South | K11: =_xlfn.XLOOKUP(H11,Store_Raw!$A$2:$A$21,Store_Raw!$D$2:$D$21) -> Christopherland | L11: =_xlfn.XLOOKUP(H11,Store_Raw!$A$2:$A$21,Store_Raw!$E$2:$E$21) -> Outlet | M11: =VLOOKUP(B11,Customer_Cleaned!$A$2:$H$501,2,FALSE) -> Daniel Boyd | N11: =VLOOKUP(B11,Customer_Cleaned!$A$2:$H$501,3,FALSE) -> 29 | O11: =VLOOKUP(B11,Customer_Cleaned!$A$2:$H$501,4,FALSE) -> Female | P11: =VLOOKUP(B11,Customer_Cleaned!$A$2:$H$501,8,FALSE) -> Bronze | Q11: =_xlfn.XLOOKUP('Sales_Fact cleaned'!B1570,Customer_Cleaned!$A$2:$A$501,Customer_Cleaned!$F$2:$F$501) -> Kansas | R11: =_xlfn.XLOOKUP(B11,Customer_Cleaned!$A$2:$A$501,Customer_Cleaned!$G$2:$G$501) -> USA | S11: 1 | T11: 38.88 | U11: 0.16 | V11: 32.6592 | W11: PayPal
A12: 45217 | B12: CUST1274 | C12: PROD44 | D12: =VLOOKUP(C12,Product_Cleaned!$A$2:$B$101,2,FALSE) -> Adjustable Jump Rope | E12: =VLOOKUP(C12,Product_Cleaned!$A$2:$C$101,3,FALSE) -> Sports | F12: =VLOOKUP(C12,Product_Cleaned!$A$2:$E$101,4,FALSE) -> Fitness | G12: =VLOOKUP('Sales_Fact cleaned'!C1379,Product_Cleaned!$A$2:$E$101,5, FALSE) -> Zhang Inc | H12: STORE4 | I12: =_xlfn.XLOOKUP(H12,Store_Raw!$A$2:$A$21,Store_Raw!$B$2:$B$21) -> Alexander Group | J12: =_xlfn.XLOOKUP(H12,Store_Raw!$A$2:$A$21,Store_Raw!$C$2:$C$21) -> South | K12: =_xlfn.XLOOKUP(H12,Store_Raw!$A$2:$A$21,Store_Raw!$D$2:$D$21) -> Port Sharon | L12: =_xlfn.XLOOKUP(H12,Store_Raw!$A$2:$A$21,Store_Raw!$E$2:$E$21) -> Online | M12: =VLOOKUP(B12,Customer_Cleaned!$A$2:$H$501,2,FALSE) -> Sarah Lane | N12: =VLOOKUP(B12,Customer_Cleaned!$A$2:$H$501,3,FALSE) -> 38 | O12: =VLOOKUP(B12,Customer_Cleaned!$A$2:$H$501,4,FALSE) -> Male | P12: =VLOOKUP(B12,Customer_Cleaned!$A$2:$H$501,8,FALSE) -> Silver | Q12: =_xlfn.XLOOKUP('Sales_Fact cleaned'!B1379,Customer_Cleaned!$A$2:$A$501,Customer_Cleaned!$F$2:$F$501) -> Georgia | R12: =_xlfn.XLOOKUP(B12,Customer_Cleaned!$A$2:$A$501,Customer_Cleaned!$G$2:$G$501) -> USA | S12: 1 | T12: 34.51 | U12: 0.04 | V12: 33.1296 | W12: PayPal
A13: 45217 | B13: CUST1305 | C13: PROD5 | D13: =VLOOKUP(C13,Product_Cleaned!$A$2:$B$101,2,FALSE) -> Men's Leather Belt | E13: =VLOOKUP(C13,Product_Cleaned!$A$2:$C$101,3,FALSE) -> Clothing | F13: =VLOOKUP(C13,Product_Cleaned!$A$2:$E$101,4,FALSE) -> Accessories | G13: =VLOOKUP('Sales_Fact cleaned'!C1442,Product_Cleaned!$A$2:$E$101,5, FALSE) -> Khan, Jones and Paul | H13: STORE4 | I13: =_xlfn.XLOOKUP(H13,Store_Raw!$A$2:$A$21,Store_Raw!$B$2:$B$21) -> Alexander Group | J13: =_xlfn.XLOOKUP(H13,Store_Raw!$A$2:$A$21,Store_Raw!$C$2:$C$21) -> South | K13: =_xlfn.XLOOKUP(H13,Store_Raw!$A$2:$A$21,Store_Raw!$D$2:$D$21) -> Port Sharon | L13: =_xlfn.XLOOKUP(H13,Store_Raw!$A$2:$A$21,Store_Raw!$E$2:$E$21) -> Online | M13: =VLOOKUP(B13,Customer_Cleaned!$A$2:$H$501,2,FALSE) -> Roberta Green | N13: =VLOOKUP(B13,Customer_Cleaned!$A$2:$H$501,3,FALSE) -> 64 | O13: =VLOOKUP(B13,Customer_Cleaned!$A$2:$H$501,4,FALSE) -> Male | P13: =VLOOKUP(B13,Customer_Cleaned!$A$2:$H$501,8,FALSE) -> Platinum | Q13: =_xlfn.XLOOKUP('Sales_Fact cleaned'!B1442,Customer_Cleaned!$A$2:$A$501,Customer_Cleaned!$F$2:$F$501) -> Kansas | R13: =_xlfn.XLOOKUP(B13,Customer_Cleaned!$A$2:$A$501,Customer_Cleaned!$G$2:$G$501) -> USA | S13: 1 | T13: 47.47 | U13: 0.28 | V13: 34.1784 | W13: PayPal
A14: 45217 | B14: CUST1095 | C14: PROD19 | D14: =VLOOKUP(C14,Product_Cleaned!$A$2:$B$101,2,FALSE) -> Knee Support Brace | E14: =VLOOKUP(C14,Product_Cleaned!$A$2:$C$101,3,FALSE) -> Sports | F14: =VLOOKUP(C14,Product_Cleaned!$A$2:$E$101,4,FALSE) -> Equipment | G14: =VLOOKUP('Sales_Fact cleaned'!C36,Product_Cleaned!$A$2:$E$101,5, FALSE) -> Campbell Ltd | H14: STORE16 | I14: =_xlfn.XLOOKUP(H14,Store_Raw!$A$2:$A$21,Store_Raw!$B$2:$B$21) -> Frederick-Wright | J14: =_xlfn.XLOOKUP(H14,Store_Raw!$A$2:$A$21,Store_Raw!$C$2:$C$21) -> West | K14: =_xlfn.XLOOKUP(H14,Store_Raw!$A$2:$A$21,Store_Raw!$D$2:$D$21) -> New Jimmymouth | L14: =_xlfn.XLOOKUP(H14,Store_Raw!$A$2:$A$21,Store_Raw!$E$2:$E$21) -> Flagship | M14: =VLOOKUP(B14,Customer_Cleaned!$A$2:$H$501,2,FALSE) -> Amy Fowler | N14: =VLOOKUP(B14,Customer_Cleaned!$A$2:$H$501,3,FALSE) -> 62 | O14: =VLOOKUP(B14,Customer_Cleaned!$A$2:$H$501,4,FALSE) -> Female | P14: =VLOOKUP(B14,Customer_Cleaned!$A$2:$H$501,8,FALSE) -> Platinum | Q14: =_xlfn.XLOOKUP('Sales_Fact cleaned'!B36,Customer_Cleaned!$A$2:$A$501,Customer_Cleaned!$F$2:$F$501) -> Tennessee | R14: =_xlfn.XLOOKUP(B14,Customer_Cleaned!$A$2:$A$501,Customer_Cleaned!$G$2:$G$501) -> USA | S14: 2 | T14: 22.47 | U14: 0.22 | V14: 35.0532 | W14: PayPal
A15: 45217 | B15: CUST1340 | C15: PROD41 | D15: =VLOOKUP(C15,Product_Cleaned!$A$2:$B$101,2,FALSE) -> Yoga Exercise Mat | E15: =VLOOKUP(C15,Product_Cleaned!$A$2:$C$101,3,FALSE) -> Sports | F15: =VLOOKUP(C15,Product_Cleaned!$A$2:$E$101,4,FALSE) -> Fitness | G15: =VLOOKUP('Sales_Fact cleaned'!C942,Product_Cleaned!$A$2:$E$101,5, FALSE) -> Stevens, Fernandez and Martin | H15: STORE5 | I15: =_xlfn.XLOOKUP(H15,Store_Raw!$A$2:$A$21,Store_Raw!$B$2:$B$21) -> Gray Ltd | J15: =_xlfn.XLOOKUP(H15,Store_Raw!$A$2:$A$21,Store_Raw!$C$2:$C$21) -> North | K15: =_xlfn.XLOOKUP(H15,Store_Raw!$A$2:$A$21,Store_Raw!$D$2:$D$21) -> New Michaelchester | L15: =_xlfn.XLOOKUP(H15,Store_Raw!$A$2:$A$21,Store_Raw!$E$2:$E$21) -> Outlet | M15: =VLOOKUP(B15,Customer_Cleaned!$A$2:$H$501,2,FALSE) -> Eric Davis | N15: =VLOOKUP(B15,Customer_Cleaned!$A$2:$H$501,3,FALSE) -> 27 | O15: =VLOOKUP(B15,Customer_Cleaned!$A$2:$H$501,4,FALSE) -> Male | P15: =VLOOKUP(B15,Customer_Cleaned!$A$2:$H$501,8,FALSE) -> Bronze | Q15: =_xlfn.XLOOKUP('Sales_Fact cleaned'!B942,Customer_Cleaned!$A$2:$A$501,Customer_Cleaned!$F$2:$F$501) -> Oregon | R15: =_xlfn.XLOOKUP(B15,Customer_Cleaned!$A$2:$A$501,Customer_Cleaned!$G$2:$G$501) -> USA | S15: 2 | T15: 20.47 | U15: 0.12 | V15: 36.0272 | W15: COD
A16: 45218 | B16: CUST1275 | C16: PROD38 | D16: =VLOOKUP(C16,Product_Cleaned!$A$2:$B$101,2,FALSE) -> Sports Water Hydration Pack | E16: =VLOOKUP(C16,Product_Cleaned!$A$2:$C$101,3,FALSE) -> Sports | F16: =VLOOKUP(C16,Product_Cleaned!$A$2:$E$101,4,FALSE) -> Outdoor | G16: =VLOOKUP('Sales_Fact cleaned'!C325,Product_Cleaned!$A$2:$E$101,5, FALSE) -> Sharp, Taylor and Rodriguez | H16: STORE9 | I16: =_xlfn.XLOOKUP(H16,Store_Raw!$A$2:$A$21,Store_Raw!$B$2:$B$21) -> Moore, Padilla and Butler | J16: =_xlfn.XLOOKUP(H16,Store_Raw!$A$2:$A$21,Store_Raw!$C$2:$C$21) -> South | K16: =_xlfn.XLOOKUP(H16,Store_Raw!$A$2:$A$21,Store_Raw!$D$2:$D$21) -> East Johnstad | L16: =_xlfn.XLOOKUP(H16,Store_Raw!$A$2:$A$21,Store_Raw!$E$2:$E$21) -> Flagship | M16: =VLOOKUP(B16,Customer_Cleaned!$A$2:$H$501,2,FALSE) -> Shannon Miller | N16: =VLOOKUP(B16,Customer_Cleaned!$A$2:$H$501,3,FALSE) -> 22 | O16: =VLOOKUP(B16,Customer_Cleaned!$A$2:$H$501,4,FALSE) -> Male | P16: =VLOOKUP(B16,Customer_Cleaned!$A$2:$H$501,8,FALSE) -> Bronze | Q16: =_xlfn.XLOOKUP('Sales_Fact cleaned'!B325,Customer_Cleaned!$A$2:$A$501,Customer_Cleaned!$F$2:$F$501) -> Iowa | R16: =_xlfn.XLOOKUP(B16,Customer_Cleaned!$A$2:$A$501,Customer_Cleaned!$G$2:$G$501) -> USA | S16: 1 | T16: 40.25 | U16: 0.1 | V16: 36.225 | W16: Credit Card
A17: 45218 | B17: CUST1490 | C17: PROD84 | D17: =VLOOKUP(C17,Product_Cleaned!$A$2:$B$101,2,FALSE) -> Wooden Bookshelf | E17: =VLOOKUP(C17,Product_Cleaned!$A$2:$C$101,3,FALSE) -> Home | F17: =VLOOKUP(C17,Product_Cleaned!$A$2:$E$101,4,FALSE) -> Furniture | G17: =VLOOKUP('Sales_Fact cleaned'!C608,Product_Cleaned!$A$2:$E$101,5, FALSE) -> Fitzpatrick Ltd | H17: STORE14 | I17: =_xlfn.XLOOKUP(H17,Store_Raw!$A$2:$A$21,Store_Raw!$B$2:$B$21) -> Mcdonald Inc | J17: =_xlfn.XLOOKUP(H17,Store_Raw!$A$2:$A$21,Store_Raw!$C$2:$C$21) -> South | K17: =_xlfn.XLOOKUP(H17,Store_Raw!$A$2:$A$21,Store_Raw!$D$2:$D$21) -> Christopherland | L17: =_xlfn.XLOOKUP(H17,Store_Raw!$A$2:$A$21,Store_Raw!$E$2:$E$21) -> Outlet | M17: =VLOOKUP(B17,Customer_Cleaned!$A$2:$H$501,2,FALSE) -> Scott Harris | N17: =VLOOKUP(B17,Customer_Cleaned!$A$2:$H$501,3,FALSE) -> 23 | O17: =VLOOKUP(B17,Customer_Cleaned!$A$2:$H$501,4,FALSE) -> Male | P17: =VLOOKUP(B17,Customer_Cleaned!$A$2:$H$501,8,FALSE) -> Bronze | Q17: =_xlfn.XLOOKUP('Sales_Fact cleaned'!B608,Customer_Cleaned!$A$2:$A$501,Customer_Cleaned!$F$2:$F$501) -> Minnesota | R17: =_xlfn.XLOOKUP(B17,Customer_Cleaned!$A$2:$A$501,Customer_Cleaned!$G$2:$G$501) -> USA | S17: 1 | T17: 46.66 | U17: 0.2 | V17: 37.328 | W17: COD
A18: 45219 | B18: CUST1431 | C18: PROD25 | D18: =VLOOKUP(C18,Product_Cleaned!$A$2:$B$101,2,FALSE) -> Women's Scarf Set | E18: =VLOOKUP(C18,Product_Cleaned!$A$2:$C$101,3,FALSE) -> Clothing | F18: =VLOOKUP(C18,Product_Cleaned!$A$2:$E$101,4,FALSE) -> Accessories | G18: =VLOOKUP('Sales_Fact cleaned'!C97,Product_Cleaned!$A$2:$E$101,5, FALSE) -> Lopez LLC | H18: STORE8 | I18: =_xlfn.XLOOKUP(H18,Store_Raw!$A$2:$A$21,Store_Raw!$B$2:$B$21) -> Bean, Jones and Park | J18: =_xlfn.XLOOKUP(H18,Store_Raw!$A$2:$A$21,Store_Raw!$C$2:$C$21) -> West | K18: =_xlfn.XLOOKUP(H18,Store_Raw!$A$2:$A$21,Store_Raw!$D$2:$D$21) -> Thompsonborough | L18: =_xlfn.XLOOKUP(H18,Store_Raw!$A$2:$A$21,Store_Raw!$E$2:$E$21) -> Online | M18: =VLOOKUP(B18,Customer_Cleaned!$A$2:$H$501,2,FALSE) -> John Smith | N18: =VLOOKUP(B18,Customer_Cleaned!$A$2:$H$501,3,FALSE) -> 27 | O18: =VLOOKUP(B18,Customer_Cleaned!$A$2:$H$501,4,FALSE) -> Male | P18: =VLOOKUP(B18,Customer_Cleaned!$A$2:$H$501,8,FALSE) -> Bronze | Q18: =_xlfn.XLOOKUP('Sales_Fact cleaned'!B97,Customer_Cleaned!$A$2:$A$501,Customer_Cleaned!$F$2:$F$501) -> New Jersey | R18: =_xlfn.XLOOKUP(B18,Customer_Cleaned!$A$2:$A$501,Customer_Cleaned!$G$2:$G$501) -> USA | S18: 1 | T18: 52.06 | U18: 0.27 | V18: 38.0038 | W18: PayPal
A19: 45219 | B19: CUST1003 | C19: PROD74 | D19: =VLOOKUP(C19,Product_Cleaned!$A$2:$B$101,2,FALSE) -> Bluetooth Car Audio System | E19: =VLOOKUP(C19,Product_Cleaned!$A$2:$C$101,3,FALSE) -> Electronics | F19: =VLOOKUP(C19,Product_Cleaned!$A$2:$E$101,4,FALSE) -> Audio | G19: =VLOOKUP('Sales_Fact cleaned'!C1335,Product_Cleaned!$A$2:$E$101,5, FALSE) -> Bridges, Banks and Cummings | H19: STORE15 | I19: =_xlfn.XLOOKUP(H19,Store_Raw!$A$2:$A$21,Store_Raw!$B$2:$B$21) -> Shelton PLC | J19: =_xlfn.XLOOKUP(H19,Store_Raw!$A$2:$A$21,Store_Raw!$C$2:$C$21) -> North | K19: =_xlfn.XLOOKUP(H19,Store_Raw!$A$2:$A$21,Store_Raw!$D$2:$D$21) -> East Jenniferstad | L19: =_xlfn.XLOOKUP(H19,Store_Raw!$A$2:$A$21,Store_Raw!$E$2:$E$21) -> Flagship | M19: =VLOOKUP(B19,Customer_Cleaned!$A$2:$H$501,2,FALSE) -> Jeremy Harris | N19: =VLOOKUP(B19,Customer_Cleaned!$A$2:$H$501,3,FALSE) -> 59 | O19: =VLOOKUP(B19,Customer_Cleaned!$A$2:$H$501,4,FALSE) -> Female | P19: =VLOOKUP(B19,Customer_Cleaned!$A$2:$H$501,8,FALSE) -> Platinum | Q19: =_xlfn.XLOOKUP('Sales_Fact cleaned'!B1335,Customer_Cleaned!$A$2:$A$501,Customer_Cleaned!$F$2:$F$501) -> Oregon | R19: =_xlfn.XLOOKUP(B19,Customer_Cleaned!$A$2:$A$501,Customer_Cleaned!$G$2:$G$501) -> USA | S19: 2 | T19: 25.3 | U19: 0.21 | V19: 39.974 | W19: Credit Card
A20: 45220 | B20: CUST1249 | C20: PROD72 | D20: =VLOOKUP(C20,Product_Cleaned!$A$2:$B$101,2,FALSE) -> Professional Jump Rope | E20: =VLOOKUP(C20,Product_Cleaned!$A$2:$C$101,3,FALSE) -> Sports | F20: =VLOOKUP(C20,Product_Cleaned!$A$2:$E$101,4,FALSE) -> Fitness | G20: =VLOOKUP('Sales_Fact cleaned'!C1645,Product_Cleaned!$A$2:$E$101,5, FALSE) -> Weiss-Watson | H20: STORE4 | I20: =_xlfn.XLOOKUP(H20,Store_Raw!$A$2:$A$21,Store_Raw!$B$2:$B$21) -> Alexander Group | J20: =_xlfn.XLOOKUP(H20,Store_Raw!$A$2:$A$21,Store_Raw!$C$2:$C$21) -> South | K20: =_xlfn.XLOOKUP(H20,Store_Raw!$A$2:$A$21,Store_Raw!$D$2:$D$21) -> Port Sharon | L20: =_xlfn.XLOOKUP(H20,Store_Raw!$A$2:$A$21,Store_Raw!$E$2:$E$21) -> Online | M20: =VLOOKUP(B20,Customer_Cleaned!$A$2:$H$501,2,FALSE) -> Lauren George | N20: =VLOOKUP(B20,Customer_Cleaned!$A$2:$H$501,3,FALSE) -> 41 | O20: =VLOOKUP(B20,Customer_Cleaned!$A$2:$H$501,4,FALSE) -> Female | P20: =VLOOKUP(B20,Customer_Cleaned!$A$2:$H$501,8,FALSE) -> Silver | Q20: =_xlfn.XLOOKUP('Sales_Fact cleaned'!B1645,Customer_Cleaned!$A$2:$A$501,Customer_Cleaned!$F$2:$F$501) -> Indiana | R20: =_xlfn.XLOOKUP(B20,Customer_Cleaned!$A$2:$A$501,Customer_Cleaned!$G$2:$G$501) -> USA | S20: 1 | T20: 41.39 | U20: 0.01 | V20: 40.9761 | W20: COD
A21: 45220 | B21: CUST1425 | C21: PROD72 | D21: =VLOOKUP(C21,Product_Cleaned!$A$2:$B$101,2,FALSE) -> Professional Jump Rope | E21: =VLOOKUP(C21,Product_Cleaned!$A$2:$C$101,3,FALSE) -> Sports | F21: =VLOOKUP(C21,Product_Cleaned!$A$2:$E$101,4,FALSE) -> Fitness | G21: =VLOOKUP('Sales_Fact cleaned'!C514,Product_Cleaned!$A$2:$E$101,5, FALSE) -> Bruce-Bowen | H21: STORE19 | I21: =_xlfn.XLOOKUP(H21,Store_Raw!$A$2:$A$21,Store_Raw!$B$2:$B$21) -> Mann-Austin | J21: =_xlfn.XLOOKUP(H21,Store_Raw!$A$2:$A$21,Store_Raw!$C$2:$C$21) -> East | K21: =_xlfn.XLOOKUP(H21,Store_Raw!$A$2:$A$21,Store_Raw!$D$2:$D$21) -> Vasquezborough | L21: =_xlfn.XLOOKUP(H21,Store_Raw!$A$2:$A$21,Store_Raw!$E$2:$E$21) -> Online | M21: =VLOOKUP(B21,Customer_Cleaned!$A$2:$H$501,2,FALSE) -> Bryce Hawkins | N21: =VLOOKUP(B21,Customer_Cleaned!$A$2:$H$501,3,FALSE) -> 40 | O21: =VLOOKUP(B21,Customer_Cleaned!$A$2:$H$501,4,FALSE) -> Male | P21: =VLOOKUP(B21,Customer_Cleaned!$A$2:$H$501,8,FALSE) -> Silver | Q21: =_xlfn.XLOOKUP('Sales_Fact cleaned'!B514,Customer_Cleaned!$A$2:$A$501,Customer_Cleaned!$F$2:$F$501) -> Vermont | R21: =_xlfn.XLOOKUP(B21,Customer_Cleaned!$A$2:$A$501,Customer_Cleaned!$G$2:$G$501) -> USA | S21: 1 | T21: 44.08 | U21: 0.05 | V21: 41.876 | W21: Credit Card
A22: 45221 | B22: CUST1137 | C22: PROD8 | D22: =VLOOKUP(C22,Product_Cleaned!$A$2:$B$101,2,FALSE) -> Wireless Bluetooth Earbuds | E22: =VLOOKUP(C22,Product_Cleaned!$A$2:$C$101,3,FALSE) -> Electronics | F22: =VLOOKUP(C22,Product_Cleaned!$A$2:$E$101,4,FALSE) -> Audio | G22: =VLOOKUP('Sales_Fact cleaned'!C269,Product_Cleaned!$A$2:$E$101,5, FALSE) -> Brown and Sons | H22: STORE15 | I22: =_xlfn.XLOOKUP(H22,Store_Raw!$A$2:$A$21,Store_Raw!$B$2:$B$21) -> Shelton PLC | J22: =_xlfn.XLOOKUP(H22,Store_Raw!$A$2:$A$21,Store_Raw!$C$2:$C$21) -> North | K22: =_xlfn.XLOOKUP(H22,Store_Raw!$A$2:$A$21,Store_Raw!$D$2:$D$21) -> East Jenniferstad | L22: =_xlfn.XLOOKUP(H22,Store_Raw!$A$2:$A$21,Store_Raw!$E$2:$E$21) -> Flagship | M22: =VLOOKUP(B22,Customer_Cleaned!$A$2:$H$501,2,FALSE) -> Rick Dominguez | N22: =VLOOKUP(B22,Customer_Cleaned!$A$2:$H$501,3,FALSE) -> 55 | O22: =VLOOKUP(B22,Customer_Cleaned!$A$2:$H$501,4,FALSE) -> Female | P22: =VLOOKUP(B22,Customer_Cleaned!$A$2:$H$501,8,FALSE) -> Platinum | Q22: =_xlfn.XLOOKUP('Sales_Fact cleaned'!B269,Customer_Cleaned!$A$2:$A$501,Customer_Cleaned!$F$2:$F$501) -> Kansas | R22: =_xlfn.XLOOKUP(B22,Customer_Cleaned!$A$2:$A$501,Customer_Cleaned!$G$2:$G$501) -> USA | S22: 1 | T22: 43.58 | U22: 0.01 | V22: 43.1442 | W22: COD
A23: 45222 | B23: CUST1036 | C23: PROD59 | D23: =VLOOKUP(C23,Product_Cleaned!$A$2:$B$101,2,FALSE) -> Men's Hair Styling Gel | E23: =VLOOKUP(C23,Product_Cleaned!$A$2:$C$101,3,FALSE) -> Beauty | F23: =VLOOKUP(C23,Product_Cleaned!$A$2:$E$101,4,FALSE) -> Haircare | G23: =VLOOKUP('Sales_Fact cleaned'!C594,Product_Cleaned!$A$2:$E$101,5, FALSE) -> Wilson Group | H23: STORE11 | I23: =_xlfn.XLOOKUP(H23,Store_Raw!$A$2:$A$21,Store_Raw!$B$2:$B$21) -> Aguirre-Keller | J23: =_xlfn.XLOOKUP(H23,Store_Raw!$A$2:$A$21,Store_Raw!$C$2:$C$21) -> South | K23: =_xlfn.XLOOKUP(H23,Store_Raw!$A$2:$A$21,Store_Raw!$D$2:$D$21) -> Lake Michael | L23: =_xlfn.XLOOKUP(H23,Store_Raw!$A$2:$A$21,Store_Raw!$E$2:$E$21) -> Online | M23: =VLOOKUP(B23,Customer_Cleaned!$A$2:$H$501,2,FALSE) -> Thomas Phillips | N23: =VLOOKUP(B23,Customer_Cleaned!$A$2:$H$501,3,FALSE) -> 20 | O23: =VLOOKUP(B23,Customer_Cleaned!$A$2:$H$501,4,FALSE) -> Female | P23: =VLOOKUP(B23,Customer_Cleaned!$A$2:$H$501,8,FALSE) -> Bronze | Q23: =_xlfn.XLOOKUP('Sales_Fact cleaned'!B594,Customer_Cleaned!$A$2:$A$501,Customer_Cleaned!$F$2:$F$501) -> South Carolina | R23: =_xlfn.XLOOKUP(B23,Customer_Cleaned!$A$2:$A$501,Customer_Cleaned!$G$2:$G$501) -> USA | S23: 2 | T23: 23.58 | U23: 0.02 | V23: 46.2168 | W23: PayPal
A24: 45222 | B24: CUST1207 | C24: PROD84 | D24: =VLOOKUP(C24,Product_Cleaned!$A$2:$B$101,2,FALSE) -> Wooden Bookshelf | E24: =VLOOKUP(C24,Product_Cleaned!$A$2:$C$101,3,FALSE) -> Home | F24: =VLOOKUP(C24,Product_Cleaned!$A$2:$E$101,4,FALSE) -> Furniture | G24: =VLOOKUP('Sales_Fact cleaned'!C1947,Product_Cleaned!$A$2:$E$101,5, FALSE) -> Hatfield, Baird and Torres | H24: STORE8 | I24: =_xlfn.XLOOKUP(H24,Store_Raw!$A$2:$A$21,Store_Raw!$B$2:$B$21) -> Bean, Jones and Park | J24: =_xlfn.XLOOKUP(H24,Store_Raw!$A$2:$A$21,Store_Raw!$C$2:$C$21) -> West | K24: =_xlfn.XLOOKUP(H24,Store_Raw!$A$2:$A$21,Store_Raw!$D$2:$D$21) -> Thompsonborough | L24: =_xlfn.XLOOKUP(H24,Store_Raw!$A$2:$A$21,Store_Raw!$E$2:$E$21) -> Online | M24: =VLOOKUP(B24,Customer_Cleaned!$A$2:$H$501,2,FALSE) -> Jacqueline Pacheco | N24: =VLOOKUP(B24,Customer_Cleaned!$A$2:$H$501,3,FALSE) -> 28 | O24: =VLOOKUP(B24,Customer_Cleaned!$A$2:$H$501,4,FALSE) -> Female | P24: =VLOOKUP(B24,Customer_Cleaned!$A$2:$H$501,8,FALSE) -> Bronze | Q24: =_xlfn.XLOOKUP('Sales_Fact cleaned'!B1947,Customer_Cleaned!$A$2:$A$501,Customer_Cleaned!$F$2:$F$501) -> Washington | R24: =_xlfn.XLOOKUP(B24,Customer_Cleaned!$A$2:$A$501,Customer_Cleaned!$G$2:$G$501) -> USA | S24: 2 | T24: 30.14 | U24: 0.21 | V24: 47.6212 | W24: PayPal
A25: 45222 | B25: CUST1172 | C25: PROD11 | D25: =VLOOKUP(C25,Product_Cleaned!$A$2:$B$101,2,FALSE) -> HD Smart TV Stick | E25: =VLOOKUP(C25,Product_Cleaned!$A$2:$C$101,3,FALSE) -> Electronics | F25: =VLOOKUP(C25,Product_Cleaned!$A$2:$E$101,4,FALSE) -> Accessories | G25: =VLOOKUP('Sales_Fact cleaned'!C1623,Product_Cleaned!$A$2:$E$101,5, FALSE) -> Hoffman-Williams | H25: STORE6 | I25: =_xlfn.XLOOKUP(H25,Store_Raw!$A$2:$A$21,Store_Raw!$B$2:$B$21) -> Benson-Elliott | J25: =_xlfn.XLOOKUP(H25,Store_Raw!$A$2:$A$21,Store_Raw!$C$2:$C$21) -> East | K25: =_xlfn.XLOOKUP(H25,Store_Raw!$A$2:$A$21,Store_Raw!$D$2:$D$21) -> Port Josephberg | L25: =_xlfn.XLOOKUP(H25,Store_Raw!$A$2:$A$21,Store_Raw!$E$2:$E$21) -> Online | M25: =VLOOKUP(B25,Customer_Cleaned!$A$2:$H$501,2,FALSE) -> Thomas Rhodes | N25: =VLOOKUP(B25,Customer_Cleaned!$A$2:$H$501,3,FALSE) -> 41 | O25: =VLOOKUP(B25,Customer_Cleaned!$A$2:$H$501,4,FALSE) -> Female | P25: =VLOOKUP(B25,Customer_Cleaned!$A$2:$H$501,8,FALSE) -> Silver | Q25: =_xlfn.XLOOKUP('Sales_Fact cleaned'!B1623,Customer_Cleaned!$A$2:$A$501,Customer_Cleaned!$F$2:$F$501) -> Iowa | R25: =_xlfn.XLOOKUP(B25,Customer_Cleaned!$A$2:$A$501,Customer_Cleaned!$G$2:$G$501) -> USA | S25: 1 | T25: 56.59 | U25: 0.15 | V25: 48.1015 | W25: Credit Card
A26: 45222 | B26: CUST1463 | C26: PROD31 | D26: =VLOOKUP(C26,Product_Cleaned!$A$2:$B$101,2,FALSE) -> Basketball | E26: =VLOOKUP(C26,Product_Cleaned!$A$2:$C$101,3,FALSE) -> Sports | F26: =VLOOKUP(C26,Product_Cleaned!$A$2:$E$101,4,FALSE) -> Team Sports | G26: =VLOOKUP('Sales_Fact cleaned'!C1455,Product_Cleaned!$A$2:$E$101,5, FALSE) -> Guerra-Hendrix | H26: STORE15 | I26: =_xlfn.XLOOKUP(H26,Store_Raw!$A$2:$A$21,Store_Raw!$B$2:$B$21) -> Shelton PLC | J26: =_xlfn.XLOOKUP(H26,Store_Raw!$A$2:$A$21,Store_Raw!$C$2:$C$21) -> North | K26: =_xlfn.XLOOKUP(H26,Store_Raw!$A$2:$A$21,Store_Raw!$D$2:$D$21) -> East Jenniferstad | L26: =_xlfn.XLOOKUP(H26,Store_Raw!$A$2:$A$21,Store_Raw!$E$2:$E$21) -> Flagship | M26: =VLOOKUP(B26,Customer_Cleaned!$A$2:$H$501,2,FALSE) -> Samantha Lee | N26: =VLOOKUP(B26,Customer_Cleaned!$A$2:$H$501,3,FALSE) -> 36 | O26: =VLOOKUP(B26,Customer_Cleaned!$A$2:$H$501,4,FALSE) -> Female | P26: =VLOOKUP(B26,Customer_Cleaned!$A$2:$H$501,8,FALSE) -> Silver | Q26: =_xlfn.XLOOKUP('Sales_Fact cleaned'!B1455,Customer_Cleaned!$A$2:$A$501,Customer_Cleaned!$F$2:$F$501) -> Pennsylvania | R26: =_xlfn.XLOOKUP(B26,Customer_Cleaned!$A$2:$A$501,Customer_Cleaned!$G$2:$G$501) -> USA | S26: 2 | T26: 31.28 | U26: 0.2 | V26: 50.048 | W26: COD
A27: 45223 | B27: CUST1092 | C27: PROD10 | D27: =VLOOKUP(C27,Product_Cleaned!$A$2:$B$101,2,FALSE) -> Ceramic Kitchen Bowl Set | E27: =VLOOKUP(C27,Product_Cleaned!$A$2:$C$101,3,FALSE) -> Home | F27: =VLOOKUP(C27,Product_Cleaned!$A$2:$E$101,4,FALSE) -> Kitchen | G27: =VLOOKUP('Sales_Fact cleaned'!C663,Product_Cleaned!$A$2:$E$101,5, FALSE) -> Torres, Spencer and Potter | H27: STORE11 | I27: =_xlfn.XLOOKUP(H27,Store_Raw!$A$2:$A$21,Store_Raw!$B$2:$B$21) -> Aguirre-Keller | J27: =_xlfn.XLOOKUP(H27,Store_Raw!$A$2:$A$21,Store_Raw!$C$2:$C$21) -> South | K27: =_xlfn.XLOOKUP(H27,Store_Raw!$A$2:$A$21,Store_Raw!$D$2:$D$21) -> Lake Michael | L27: =_xlfn.XLOOKUP(H27,Store_Raw!$A$2:$A$21,Store_Raw!$E$2:$E$21) -> Online | M27: =VLOOKUP(B27,Customer_Cleaned!$A$2:$H$501,2,FALSE) -> Robert Jackson | N27: =VLOOKUP(B27,Customer_Cleaned!$A$2:$H$501,3,FALSE) -> 44 | O27: =VLOOKUP(B27,Customer_Cleaned!$A$2:$H$501,4,FALSE) -> Female | P27: =VLOOKUP(B27,Customer_Cleaned!$A$2:$H$501,8,FALSE) -> Silver | Q27: =_xlfn.XLOOKUP('Sales_Fact cleaned'!B663,Customer_Cleaned!$A$2:$A$501,Customer_Cleaned!$F$2:$F$501) -> Vermont | R27: =_xlfn.XLOOKUP(B27,Customer_Cleaned!$A$2:$A$501,Customer_Cleaned!$G$2:$G$501) -> USA | S27: 1 | T27: 57.94 | U27: 0.13 | V27: 50.4078 | W27: Credit Card
A28: 45223 | B28: CUST1030 | C28: PROD40 | D28: =VLOOKUP(C28,Product_Cleaned!$A$2:$B$101,2,FALSE) -> Noise-Canceling Headphones | E28: =VLOOKUP(C28,Product_Cleaned!$A$2:$C$101,3,FALSE) -> Electronics | F28: =VLOOKUP(C28,Product_Cleaned!$A$2:$E$101,4,FALSE) -> Audio | G28: =VLOOKUP('Sales_Fact cleaned'!C576,Product_Cleaned!$A$2:$E$101,5, FALSE) -> Atkinson, Camacho and Oliver | H28: STORE9 | I28: =_xlfn.XLOOKUP(H28,Store_Raw!$A$2:$A$21,Store_Raw!$B$2:$B$21) -> Moore, Padilla and Butler | J28: =_xlfn.XLOOKUP(H28,Store_Raw!$A$2:$A$21,Store_Raw!$C$2:$C$21) -> South | K28: =_xlfn.XLOOKUP(H28,Store_Raw!$A$2:$A$21,Store_Raw!$D$2:$D$21) -> East Johnstad | L28: =_xlfn.XLOOKUP(H28,Store_Raw!$A$2:$A$21,Store_Raw!$E$2:$E$21) -> Flagship | M28: =VLOOKUP(B28,Customer_Cleaned!$A$2:$H$501,2,FALSE) -> Jessica Acevedo | N28: =VLOOKUP(B28,Customer_Cleaned!$A$2:$H$501,3,FALSE) -> 64 | O28: =VLOOKUP(B28,Customer_Cleaned!$A$2:$H$501,4,FALSE) -> Female | P28: =VLOOKUP(B28,Customer_Cleaned!$A$2:$H$501,8,FALSE) -> Platinum | Q28: =_xlfn.XLOOKUP('Sales_Fact cleaned'!B576,Customer_Cleaned!$A$2:$A$501,Customer_Cleaned!$F$2:$F$501) -> Minnesota | R28: =_xlfn.XLOOKUP(B28,Customer_Cleaned!$A$2:$A$501,Customer_Cleaned!$G$2:$G$501) -> USA | S28: 2 | T28: 26.36 | U28: 0.03 | V28: 51.1384 | W28: COD
A29: 45223 | B29: CUST1223 | C29: PROD81 | D29: =VLOOKUP(C29,Product_Cleaned!$A$2:$B$101,2,FALSE) -> Badminton Racket Set | E29: =VLOOKUP(C29,Product_Cleaned!$A$2:$C$101,3,FALSE) -> Sports | F29: =VLOOKUP(C29,Product_Cleaned!$A$2:$E$101,4,FALSE) -> Equipment | G29: =VLOOKUP('Sales_Fact cleaned'!C1193,Product_Cleaned!$A$2:$E$101,5, FALSE) -> Hoffman Group | H29: STORE12 | I29: =_xlfn.XLOOKUP(H29,Store_Raw!$A$2:$A$21,Store_Raw!$B$2:$B$21) -> Thomas, Bridges and Harris | J29: =_xlfn.XLOOKUP(H29,Store_Raw!$A$2:$A$21,Store_Raw!$C$2:$C$21) -> North | K29: =_xlfn.XLOOKUP(H29,Store_Raw!$A$2:$A$21,Store_Raw!$D$2:$D$21) -> Sabrinatown | L29: =_xlfn.XLOOKUP(H29,Store_Raw!$A$2:$A$21,Store_Raw!$E$2:$E$21) -> Online | M29: =VLOOKUP(B29,Customer_Cleaned!$A$2:$H$501,2,FALSE) -> Robert Harris | N29: =VLOOKUP(B29,Customer_Cleaned!$A$2:$H$501,3,FALSE) -> 50 | O29: =VLOOKUP(B29,Customer_Cleaned!$A$2:$H$501,4,FALSE) -> Male | P29: =VLOOKUP(B29,Customer_Cleaned!$A$2:$H$501,8,FALSE) -> Platinum | Q29: =_xlfn.XLOOKUP('Sales_Fact cleaned'!B1193,Customer_Cleaned!$A$2:$A$501,Customer_Cleaned!$F$2:$F$501) -> Massachusetts | R29: =_xlfn.XLOOKUP(B29,Customer_Cleaned!$A$2:$A$501,Customer_Cleaned!$G$2:$G$501) -> USA | S29: 1 | T29: 64.94 | U29: 0.21 | V29: 51.3026 | W29: Credit Card
A30: 45224 | B30: CUST1471 | C30: PROD3 | D30: =VLOOKUP(C30,Product_Cleaned!$A$2:$B$101,2,FALSE) -> Men's Running Jacket | E30: =VLOOKUP(C30,Product_Cleaned!$A$2:$C$101,3,FALSE) -> Clothing | F30: =VLOOKUP(C30,Product_Cleaned!$A$2:$E$101,4,FALSE) -> Outerwear | G30: =VLOOKUP('Sales_Fact cleaned'!C797,Product_Cleaned!$A$2:$E$101,5, FALSE) -> Sims-Smith | H30: STORE15 | I30: =_xlfn.XLOOKUP(H30,Store_Raw!$A$2:$A$21,Store_Raw!$B$2:$B$21) -> Shelton PLC | J30: =_xlfn.XLOOKUP(H30,Store_Raw!$A$2:$A$21,Store_Raw!$C$2:$C$21) -> North | K30: =_xlfn.XLOOKUP(H30,Store_Raw!$A$2:$A$21,Store_Raw!$D$2:$D$21) -> East Jenniferstad | L30: =_xlfn.XLOOKUP(H30,Store_Raw!$A$2:$A$21,Store_Raw!$E$2:$E$21) -> Flagship | M30: =VLOOKUP(B30,Customer_Cleaned!$A$2:$H$501,2,FALSE) -> Debra Mccullough | N30: =VLOOKUP(B30,Customer_Cleaned!$A$2:$H$501,3,FALSE) -> 42 | O30: =VLOOKUP(B30,Customer_Cleaned!$A$2:$H$501,4,FALSE) -> Male | P30: =VLOOKUP(B30,Customer_Cleaned!$A$2:$H$501,8,FALSE) -> Silver | Q30: =_xlfn.XLOOKUP('Sales_Fact cleaned'!B797,Customer_Cleaned!$A$2:$A$501,Customer_Cleaned!$F$2:$F$501) -> Wisconsin | R30: =_xlfn.XLOOKUP(B30,Customer_Cleaned!$A$2:$A$501,Customer_Cleaned!$G$2:$G$501) -> USA | S30: 1 | T30: 74.29 | U30: 0.3 | V30: 52.003 | W30: PayPal
A31: 45224 | B31: CUST1083 | C31: PROD10 | D31: =VLOOKUP(C31,Product_Cleaned!$A$2:$B$101,2,FALSE) -> Ceramic Kitchen Bowl Set | E31: =VLOOKUP(C31,Product_Cleaned!$A$2:$C$101,3,FALSE) -> Home | F31: =VLOOKUP(C31,Product_Cleaned!$A$2:$E$101,4,FALSE) -> Kitchen | G31: =VLOOKUP('Sales_Fact cleaned'!C1748,Product_Cleaned!$A$2:$E$101,5, FALSE) -> Taylor-Elliott | H31: STORE7 | I31: =_xlfn.XLOOKUP(H31,Store_Raw!$A$2:$A$21,Store_Raw!$B$2:$B$21) -> Martinez-Mullins | J31: =_xlfn.XLOOKUP(H31,Store_Raw!$A$2:$A$21,Store_Raw!$C$2:$C$21) -> South | K31: =_xlfn.XLOOKUP(H31,Store_Raw!$A$2:$A$21,Store_Raw!$D$2:$D$21) -> Williamsfurt | L31: =_xlfn.XLOOKUP(H31,Store_Raw!$A$2:$A$21,Store_Raw!$E$2:$E$21) -> Online | M31: =VLOOKUP(B31,Customer_Cleaned!$A$2:$H$501,2,FALSE) -> Thomas Robinson | N31: =VLOOKUP(B31,Customer_Cleaned!$A$2:$H$501,3,FALSE) -> 48 | O31: =VLOOKUP(B31,Customer_Cleaned!$A$2:$H$501,4,FALSE) -> Female | P31: =VLOOKUP(B31,Customer_Cleaned!$A$2:$H$501,8,FALSE) -> Silver | Q31: =_xlfn.XLOOKUP('Sales_Fact cleaned'!B1748,Customer_Cleaned!$A$2:$A$501,Customer_Cleaned!$F$2:$F$501) -> Utah | R31: =_xlfn.XLOOKUP(B31,Customer_Cleaned!$A$2:$A$501,Customer_Cleaned!$G$2:$G$501) -> USA | S31: 1 | T31: 66.86 | U31: 0.22 | V31: 52.1508 | W31: PayPal
A32: 45224 | B32: CUST1206 | C32: PROD56 | D32: =VLOOKUP(C32,Product_Cleaned!$A$2:$B$101,2,FALSE) -> Premium Blanket Throw | E32: =VLOOKUP(C32,Product_Cleaned!$A$2:$C$101,3,FALSE) -> Home | F32: =VLOOKUP(C32,Product_Cleaned!$A$2:$E$101,4,FALSE) -> Decor | G32: =VLOOKUP('Sales_Fact cleaned'!C571,Product_Cleaned!$A$2:$E$101,5, FALSE) -> Ford, Murphy and Wilson | H32: STORE18 | I32: =_xlfn.XLOOKUP(H32,Store_Raw!$A$2:$A$21,Store_Raw!$B$2:$B$21) -> Guerrero-Schmitt | J32: =_xlfn.XLOOKUP(H32,Store_Raw!$A$2:$A$21,Store_Raw!$C$2:$C$21) -> East | K32: =_xlfn.XLOOKUP(H32,Store_Raw!$A$2:$A$21,Store_Raw!$D$2:$D$21) -> East Stevechester | L32: =_xlfn.XLOOKUP(H32,Store_Raw!$A$2:$A$21,Store_Raw!$E$2:$E$21) -> Flagship | M32: =VLOOKUP(B32,Customer_Cleaned!$A$2:$H$501,2,FALSE) -> Ronald Jones | N32: =VLOOKUP(B32,Customer_Cleaned!$A$2:$H$501,3,FALSE) -> 26 | O32: =VLOOKUP(B32,Customer_Cleaned!$A$2:$H$501,4,FALSE) -> Female | P32: =VLOOKUP(B32,Customer_Cleaned!$A$2:$H$501,8,FALSE) -> Bronze | Q32: =_xlfn.XLOOKUP('Sales_Fact cleaned'!B571,Customer_Cleaned!$A$2:$A$501,Customer_Cleaned!$F$2:$F$501) -> Wyoming | R32: =_xlfn.XLOOKUP(B32,Customer_Cleaned!$A$2:$A$501,Customer_Cleaned!$G$2:$G$501) -> USA | S32: 1 | T32: 75.8 | U32: 0.29 | V32: 53.818 | W32: COD
A33: 45225 | B33: CUST1042 | C33: PROD89 | D33: =VLOOKUP(C33,Product_Cleaned!$A$2:$B$101,2,FALSE) -> Face Foundation Kit | E33: =VLOOKUP(C33,Product_Cleaned!$A$2:$C$101,3,FALSE) -> Beauty | F33: =VLOOKUP(C33,Product_Cleaned!$A$2:$E$101,4,FALSE) -> Makeup | G33: =VLOOKUP('Sales_Fact cleaned'!C1531,Product_Cleaned!$A$2:$E$101,5, FALSE) -> Burns-Hansen | H33: STORE2 | I33: =_xlfn.XLOOKUP(H33,Store_Raw!$A$2:$A$21,Store_Raw!$B$2:$B$21) -> Black-Horn | J33: =_xlfn.XLOOKUP(H33,Store_Raw!$A$2:$A$21,Store_Raw!$C$2:$C$21) -> South | K33: =_xlfn.XLOOKUP(H33,Store_Raw!$A$2:$A$21,Store_Raw!$D$2:$D$21) -> North Nancyview | L33: =_xlfn.XLOOKUP(H33,Store_Raw!$A$2:$A$21,Store_Raw!$E$2:$E$21) -> Outlet | M33: =VLOOKUP(B33,Customer_Cleaned!$A$2:$H$501,2,FALSE) -> William Martin | N33: =VLOOKUP(B33,Customer_Cleaned!$A$2:$H$501,3,FALSE) -> 19 | O33: =VLOOKUP(B33,Customer_Cleaned!$A$2:$H$501,4,FALSE) -> Male | P33: =VLOOKUP(B33,Customer_Cleaned!$A$2:$H$501,8,FALSE) -> Bronze | Q33: =_xlfn.XLOOKUP('Sales_Fact cleaned'!B1531,Customer_Cleaned!$A$2:$A$501,Customer_Cleaned!$F$2:$F$501) -> Ohio | R33: =_xlfn.XLOOKUP(B33,Customer_Cleaned!$A$2:$A$501,Customer_Cleaned!$G$2:$G$501) -> USA | S33: 3 | T33: 21.59 | U33: 0.16 | V33: 54.4068 | W33: COD
A34: 45225 | B34: CUST1444 | C34: PROD17 | D34: =VLOOKUP(C34,Product_Cleaned!$A$2:$B$101,2,FALSE) -> Soccer Training Cone Set | E34: =VLOOKUP(C34,Product_Cleaned!$A$2:$C$101,3,FALSE) -> Sports | F34: =VLOOKUP(C34,Product_Cleaned!$A$2:$E$101,4,FALSE) -> Accessories | G34: =VLOOKUP('Sales_Fact cleaned'!C966,Product_Cleaned!$A$2:$E$101,5, FALSE) -> Khan, Jones and Paul | H34: STORE6 | I34: =_xlfn.XLOOKUP(H34,Store_Raw!$A$2:$A$21,Store_Raw!$B$2:$B$21) -> Benson-Elliott | J34: =_xlfn.XLOOKUP(H34,Store_Raw!$A$2:$A$21,Store_Raw!$C$2:$C$21) -> East | K34: =_xlfn.XLOOKUP(H34,Store_Raw!$A$2:$A$21,Store_Raw!$D$2:$D$21) -> Port Josephberg | L34: =_xlfn.XLOOKUP(H34,Store_Raw!$A$2:$A$21,Store_Raw!$E$2:$E$21) -> Online | M34: =VLOOKUP(B34,Customer_Cleaned!$A$2:$H$501,2,FALSE) -> Cheryl Carr | N34: =VLOOKUP(B34,Customer_Cleaned!$A$2:$H$501,3,FALSE) -> 19 | O34: =VLOOKUP(B34,Customer_Cleaned!$A$2:$H$501,4,FALSE) -> Male | P34: =VLOOKUP(B34,Customer_Cleaned!$A$2:$H$501,8,FALSE) -> Bronze | Q34: =_xlfn.XLOOKUP('Sales_Fact cleaned'!B966,Customer_Cleaned!$A$2:$A$501,Customer_Cleaned!$F$2:$F$501) -> Alaska | R34: =_xlfn.XLOOKUP(B34,Customer_Cleaned!$A$2:$A$501,Customer_Cleaned!$G$2:$G$501) -> USA | S34: 1 | T34: 55.04 | U34: 0.01 | V34: 54.4896 | W34: PayPal
A35: 45227 | B35: CUST1216 | C35: PROD72 | D35: =VLOOKUP(C35,Product_Cleaned!$A$2:$B$101,2,FALSE) -> Professional Jump Rope | E35: =VLOOKUP(C35,Product_Cleaned!$A$2:$C$101,3,FALSE) -> Sports | F35: =VLOOKUP(C35,Product_Cleaned!$A$2:$E$101,4,FALSE) -> Fitness | G35: =VLOOKUP('Sales_Fact cleaned'!C24,Product_Cleaned!$A$2:$E$101,5, FALSE) -> Collins-Stephenson | H35: STORE0 | I35: =_xlfn.XLOOKUP(H35,Store_Raw!$A$2:$A$21,Store_Raw!$B$2:$B$21) -> Rivera-Warner | J35: =_xlfn.XLOOKUP(H35,Store_Raw!$A$2:$A$21,Store_Raw!$C$2:$C$21) -> East | K35: =_xlfn.XLOOKUP(H35,Store_Raw!$A$2:$A$21,Store_Raw!$D$2:$D$21) -> Washingtonfurt | L35: =_xlfn.XLOOKUP(H35,Store_Raw!$A$2:$A$21,Store_Raw!$E$2:$E$21) -> Flagship | M35: =VLOOKUP(B35,Customer_Cleaned!$A$2:$H$501,2,FALSE) -> Kathryn Garcia | N35: =VLOOKUP(B35,Customer_Cleaned!$A$2:$H$501,3,FALSE) -> 44 | O35: =VLOOKUP(B35,Customer_Cleaned!$A$2:$H$501,4,FALSE) -> Male | P35: =VLOOKUP(B35,Customer_Cleaned!$A$2:$H$501,8,FALSE) -> Silver | Q35: =_xlfn.XLOOKUP('Sales_Fact cleaned'!B24,Customer_Cleaned!$A$2:$A$501,Customer_Cleaned!$F$2:$F$501) -> New Jersey | R35: =_xlfn.XLOOKUP(B35,Customer_Cleaned!$A$2:$A$501,Customer_Cleaned!$G$2:$G$501) -> USA | S35: 1 | T35: 61.11 | U35: 0.1 | V35: 54.999 | W35: PayPal
A36: 45227 | B36: CUST1199 | C36: PROD99 | D36: =VLOOKUP(C36,Product_Cleaned!$A$2:$B$101,2,FALSE) -> Stainless Steel Cookware Set | E36: =VLOOKUP(C36,Product_Cleaned!$A$2:$C$101,3,FALSE) -> Home | F36: =VLOOKUP(C36,Product_Cleaned!$A$2:$E$101,4,FALSE) -> Kitchen | G36: =VLOOKUP('Sales_Fact cleaned'!C1517,Product_Cleaned!$A$2:$E$101,5, FALSE) -> Phillips and Sons | H36: STORE2 | I36: =_xlfn.XLOOKUP(H36,Store_Raw!$A$2:$A$21,Store_Raw!$B$2:$B$21) -> Black-Horn | J36: =_xlfn.XLOOKUP(H36,Store_Raw!$A$2:$A$21,Store_Raw!$C$2:$C$21) -> South | K36: =_xlfn.XLOOKUP(H36,Store_Raw!$A$2:$A$21,Store_Raw!$D$2:$D$21) -> North Nancyview | L36: =_xlfn.XLOOKUP(H36,Store_Raw!$A$2:$A$21,Store_Raw!$E$2:$E$21) -> Outlet | M36: =VLOOKUP(B36,Customer_Cleaned!$A$2:$H$501,2,FALSE) -> Carmen Price | N36: =VLOOKUP(B36,Customer_Cleaned!$A$2:$H$501,3,FALSE) -> 46 | O36: =VLOOKUP(B36,Customer_Cleaned!$A$2:$H$501,4,FALSE) -> Male | P36: =VLOOKUP(B36,Customer_Cleaned!$A$2:$H$501,8,FALSE) -> Silver | Q36: =_xlfn.XLOOKUP('Sales_Fact cleaned'!B1517,Customer_Cleaned!$A$2:$A$501,Customer_Cleaned!$F$2:$F$501) -> Pennsylvania | R36: =_xlfn.XLOOKUP(B36,Customer_Cleaned!$A$2:$A$501,Customer_Cleaned!$G$2:$G$501) -> USA | S36: 1 | T36: 71.71 | U36: 0.23 | V36: 55.2167 | W36: PayPal
A37: 45227 | B37: CUST1029 | C37: PROD79 | D37: =VLOOKUP(C37,Product_Cleaned!$A$2:$B$101,2,FALSE) -> Decorative Lamp Shade | E37: =VLOOKUP(C37,Product_Cleaned!$A$2:$C$101,3,FALSE) -> Home | F37: =VLOOKUP(C37,Product_Cleaned!$A$2:$E$101,4,FALSE) -> Lighting | G37: =VLOOKUP('Sales_Fact cleaned'!C110,Product_Cleaned!$A$2:$E$101,5, FALSE) -> Cummings and Sons | H37: STORE4 | I37: =_xlfn.XLOOKUP(H37,Store_Raw!$A$2:$A$21,Store_Raw!$B$2:$B$21) -> Alexander Group | J37: =_xlfn.XLOOKUP(H37,Store_Raw!$A$2:$A$21,Store_Raw!$C$2:$C$21) -> South | K37: =_xlfn.XLOOKUP(H37,Store_Raw!$A$2:$A$21,Store_Raw!$D$2:$D$21) -> Port Sharon | L37: =_xlfn.XLOOKUP(H37,Store_Raw!$A$2:$A$21,Store_Raw!$E$2:$E$21) -> Online | M37: =VLOOKUP(B37,Customer_Cleaned!$A$2:$H$501,2,FALSE) -> David Arnold | N37: =VLOOKUP(B37,Customer_Cleaned!$A$2:$H$501,3,FALSE) -> 54 | O37: =VLOOKUP(B37,Customer_Cleaned!$A$2:$H$501,4,FALSE) -> Female | P37: =VLOOKUP(B37,Customer_Cleaned!$A$2:$H$501,8,FALSE) -> Platinum | Q37: =_xlfn.XLOOKUP('Sales_Fact cleaned'!B110,Customer_Cleaned!$A$2:$A$501,Customer_Cleaned!$F$2:$F$501) -> Florida | R37: =_xlfn.XLOOKUP(B37,Customer_Cleaned!$A$2:$A$501,Customer_Cleaned!$G$2:$G$501) -> USA | S37: 2 | T37: 32.19 | U37: 0.13 | V37: 56.0106 | W37: Credit Card
A38: 45228 | B38: CUST1443 | C38: PROD88 | D38: =VLOOKUP(C38,Product_Cleaned!$A$2:$B$101,2,FALSE) -> Sports Wrist Sweatbands | E38: =VLOOKUP(C38,Product_Cleaned!$A$2:$C$101,3,FALSE) -> Sports | F38: =VLOOKUP(C38,Product_Cleaned!$A$2:$E$101,4,FALSE) -> Accessories | G38: =VLOOKUP('Sales_Fact cleaned'!C1310,Product_Cleaned!$A$2:$E$101,5, FALSE) -> Hoffman Group | H38: STORE10 | I38: =_xlfn.XLOOKUP(H38,Store_Raw!$A$2:$A$21,Store_Raw!$B$2:$B$21) -> Hill, Wagner and Ballard | J38: =_xlfn.XLOOKUP(H38,Store_Raw!$A$2:$A$21,Store_Raw!$C$2:$C$21) -> East | K38: =_xlfn.XLOOKUP(H38,Store_Raw!$A$2:$A$21,Store_Raw!$D$2:$D$21) -> East Davidville | L38: =_xlfn.XLOOKUP(H38,Store_Raw!$A$2:$A$21,Store_Raw!$E$2:$E$21) -> Online | M38: =VLOOKUP(B38,Customer_Cleaned!$A$2:$H$501,2,FALSE) -> Adam Castro | N38: =VLOOKUP(B38,Customer_Cleaned!$A$2:$H$501,3,FALSE) -> 51 | O38: =VLOOKUP(B38,Customer_Cleaned!$A$2:$H$501,4,FALSE) -> Male | P38: =VLOOKUP(B38,Customer_Cleaned!$A$2:$H$501,8,FALSE) -> Platinum | Q38: =_xlfn.XLOOKUP('Sales_Fact cleaned'!B1310,Customer_Cleaned!$A$2:$A$501,Customer_Cleaned!$F$2:$F$501) -> Mississippi | R38: =_xlfn.XLOOKUP(B38,Customer_Cleaned!$A$2:$A$501,Customer_Cleaned!$G$2:$G$501) -> USA | S38: 1 | T38: 66.14 | U38: 0.14 | V38: 56.8804 | W38: Credit Card
A39: 45228 | B39: CUST1190 | C39: PROD44 | D39: =VLOOKUP(C39,Product_Cleaned!$A$2:$B$101,2,FALSE) -> Adjustable Jump Rope | E39: =VLOOKUP(C39,Product_Cleaned!$A$2:$C$101,3,FALSE) -> Sports | F39: =VLOOKUP(C39,Product_Cleaned!$A$2:$E$101,4,FALSE) -> Fitness | G39: =VLOOKUP('Sales_Fact cleaned'!C875,Product_Cleaned!$A$2:$E$101,5, FALSE) -> Ramirez-Hanson | H39: STORE6 | I39: =_xlfn.XLOOKUP(H39,Store_Raw!$A$2:$A$21,Store_Raw!$B$2:$B$21) -> Benson-Elliott | J39: =_xlfn.XLOOKUP(H39,Store_Raw!$A$2:$A$21,Store_Raw!$C$2:$C$21) -> East | K39: =_xlfn.XLOOKUP(H39,Store_Raw!$A$2:$A$21,Store_Raw!$D$2:$D$21) -> Port Josephberg | L39: =_xlfn.XLOOKUP(H39,Store_Raw!$A$2:$A$21,Store_Raw!$E$2:$E$21) -> Online | M39: =VLOOKUP(B39,Customer_Cleaned!$A$2:$H$501,2,FALSE) -> Christopher Stewart | N39: =VLOOKUP(B39,Customer_Cleaned!$A$2:$H$501,3,FALSE) -> 21 | O39: =VLOOKUP(B39,Customer_Cleaned!$A$2:$H$501,4,FALSE) -> Male | P39: =VLOOKUP(B39,Customer_Cleaned!$A$2:$H$501,8,FALSE) -> Bronze | Q39: =_xlfn.XLOOKUP('Sales_Fact cleaned'!B875,Customer_Cleaned!$A$2:$A$501,Customer_Cleaned!$F$2:$F$501) -> West Virginia | R39: =_xlfn.XLOOKUP(B39,Customer_Cleaned!$A$2:$A$501,Customer_Cleaned!$G$2:$G$501) -> USA | S39: 1 | T39: 62.38 | U39: 0.08 | V39: 57.3896 | W39: Credit Card
A40: 45228 | B40: CUST1357 | C40: PROD88 | D40: =VLOOKUP(C40,Product_Cleaned!$A$2:$B$101,2,FALSE) -> Sports Wrist Sweatbands | E40: =VLOOKUP(C40,Product_Cleaned!$A$2:$C$101,3,FALSE) -> Sports | F40: =VLOOKUP(C40,Product_Cleaned!$A$2:$E$101,4,FALSE) -> Accessories | G40: =VLOOKUP('Sales_Fact cleaned'!C747,Product_Cleaned!$A$2:$E$101,5, FALSE) -> Thompson-French | H40: STORE6 | I40: =_xlfn.XLOOKUP(H40,Store_Raw!$A$2:$A$21,Store_Raw!$B$2:$B$21) -> Benson-Elliott | J40: =_xlfn.XLOOKUP(H40,Store_Raw!$A$2:$A$21,Store_Raw!$C$2:$C$21) -> East | K40: =_xlfn.XLOOKUP(H40,Store_Raw!$A$2:$A$21,Store_Raw!$D$2:$D$21) -> Port Josephberg | L40: =_xlfn.XLOOKUP(H40,Store_Raw!$A$2:$A$21,Store_Raw!$E$2:$E$21) -> Online | M40: =VLOOKUP(B40,Customer_Cleaned!$A$2:$H$501,2,FALSE) -> Manuel Castillo | N40: =VLOOKUP(B40,Customer_Cleaned!$A$2:$H$501,3,FALSE) -> 41 | O40: =VLOOKUP(B40,Customer_Cleaned!$A$2:$H$501,4,FALSE) -> Male | P40: =VLOOKUP(B40,Customer_Cleaned!$A$2:$H$501,8,FALSE) -> Silver | Q40: =_xlfn.XLOOKUP('Sales_Fact cleaned'!B747,Customer_Cleaned!$A$2:$A$501,Customer_Cleaned!$F$2:$F$501) -> West Virginia | R40: =_xlfn.XLOOKUP(B40,Customer_Cleaned!$A$2:$A$501,Customer_Cleaned!$G$2:$G$501) -> USA | S40: 3 | T40: 23.37 | U40: 0.15 | V40: 59.5935 | W40: COD
A41: 45229 | B41: CUST1177 | C41: PROD59 | D41: =VLOOKUP(C41,Product_Cleaned!$A$2:$B$101,2,FALSE) -> Men's Hair Styling Gel | E41: =VLOOKUP(C41,Product_Cleaned!$A$2:$C$101,3,FALSE) -> Beauty | F41: =VLOOKUP(C41,Product_Cleaned!$A$2:$E$101,4,FALSE) -> Haircare | G41: =VLOOKUP('Sales_Fact cleaned'!C1721,Product_Cleaned!$A$2:$E$101,5, FALSE) -> Hopkins Ltd | H41: STORE14 | I41: =_xlfn.XLOOKUP(H41,Store_Raw!$A$2:$A$21,Store_Raw!$B$2:$B$21) -> Mcdonald Inc | J41: =_xlfn.XLOOKUP(H41,Store_Raw!$A$2:$A$21,Store_Raw!$C$2:$C$21) -> South | K41: =_xlfn.XLOOKUP(H41,Store_Raw!$A$2:$A$21,Store_Raw!$D$2:$D$21) -> Christopherland | L41: =_xlfn.XLOOKUP(H41,Store_Raw!$A$2:$A$21,Store_Raw!$E$2:$E$21) -> Outlet | M41: =VLOOKUP(B41,Customer_Cleaned!$A$2:$H$501,2,FALSE) -> Curtis Lam | N41: =VLOOKUP(B41,Customer_Cleaned!$A$2:$H$501,3,FALSE) -> 55 | O41: =VLOOKUP(B41,Customer_Cleaned!$A$2:$H$501,4,FALSE) -> Male | P41: =VLOOKUP(B41,Customer_Cleaned!$A$2:$H$501,8,FALSE) -> Platinum | Q41: =_xlfn.XLOOKUP('Sales_Fact cleaned'!B1721,Customer_Cleaned!$A$2:$A$501,Customer_Cleaned!$F$2:$F$501) -> Michigan | R41: =_xlfn.XLOOKUP(B41,Customer_Cleaned!$A$2:$A$501,Customer_Cleaned!$G$2:$G$501) -> USA | S41: 2 | T41: 37.21 | U41: 0.19 | V41: 60.2802 | W41: PayPal
A42: 45229 | B42: CUST1021 | C42: PROD54 | D42: =VLOOKUP(C42,Product_Cleaned!$A$2:$B$101,2,FALSE) -> Sports Stopwatch Pro | E42: =VLOOKUP(C42,Product_Cleaned!$A$2:$C$101,3,FALSE) -> Sports | F42: =VLOOKUP(C42,Product_Cleaned!$A$2:$E$101,4,FALSE) -> Accessories | G42: =VLOOKUP('Sales_Fact cleaned'!C614,Product_Cleaned!$A$2:$E$101,5, FALSE) -> Kelly, Smith and Perez | H42: STORE4 | I42: =_xlfn.XLOOKUP(H42,Store_Raw!$A$2:$A$21,Store_Raw!$B$2:$B$21) -> Alexander Group | J42: =_xlfn.XLOOKUP(H42,Store_Raw!$A$2:$A$21,Store_Raw!$C$2:$C$21) -> South | K42: =_xlfn.XLOOKUP(H42,Store_Raw!$A$2:$A$21,Store_Raw!$D$2:$D$21) -> Port Sharon | L42: =_xlfn.XLOOKUP(H42,Store_Raw!$A$2:$A$21,Store_Raw!$E$2:$E$21) -> Online | M42: =VLOOKUP(B42,Customer_Cleaned!$A$2:$H$501,2,FALSE) -> Jeff Martinez | N42: =VLOOKUP(B42,Customer_Cleaned!$A$2:$H$501,3,FALSE) -> 36 | O42: =VLOOKUP(B42,Customer_Cleaned!$A$2:$H$501,4,FALSE) -> Female | P42: =VLOOKUP(B42,Customer_Cleaned!$A$2:$H$501,8,FALSE) -> Silver | Q42: =_xlfn.XLOOKUP('Sales_Fact cleaned'!B614,Customer_Cleaned!$A$2:$A$501,Customer_Cleaned!$F$2:$F$501) -> Kentucky | R42: =_xlfn.XLOOKUP(B42,Customer_Cleaned!$A$2:$A$501,Customer_Cleaned!$G$2:$G$501) -> USA | S42: 1 | T42: 62.26 | U42: 0.03 | V42: 60.3922 | W42: PayPal
A43: 45229 | B43: CUST1498 | C43: PROD2 | D43: =VLOOKUP(C43,Product_Cleaned!$A$2:$B$101,2,FALSE) -> Women's Casual Hoodie | E43: =VLOOKUP(C43,Product_Cleaned!$A$2:$C$101,3,FALSE) -> Clothing | F43: =VLOOKUP(C43,Product_Cleaned!$A$2:$E$101,4,FALSE) -> Outerwear | G43: =VLOOKUP('Sales_Fact cleaned'!C877,Product_Cleaned!$A$2:$E$101,5, FALSE) -> Cline-Mccarthy | H43: STORE12 | I43: =_xlfn.XLOOKUP(H43,Store_Raw!$A$2:$A$21,Store_Raw!$B$2:$B$21) -> Thomas, Bridges and Harris | J43: =_xlfn.XLOOKUP(H43,Store_Raw!$A$2:$A$21,Store_Raw!$C$2:$C$21) -> North | K43: =_xlfn.XLOOKUP(H43,Store_Raw!$A$2:$A$21,Store_Raw!$D$2:$D$21) -> Sabrinatown | L43: =_xlfn.XLOOKUP(H43,Store_Raw!$A$2:$A$21,Store_Raw!$E$2:$E$21) -> Online | M43: =VLOOKUP(B43,Customer_Cleaned!$A$2:$H$501,2,FALSE) -> Traci Gonzalez | N43: =VLOOKUP(B43,Customer_Cleaned!$A$2:$H$501,3,FALSE) -> 35 | O43: =VLOOKUP(B43,Customer_Cleaned!$A$2:$H$501,4,FALSE) -> Male | P43: =VLOOKUP(B43,Customer_Cleaned!$A$2:$H$501,8,FALSE) -> Silver | Q43: =_xlfn.XLOOKUP('Sales_Fact cleaned'!B877,Customer_Cleaned!$A$2:$A$501,Customer_Cleaned!$F$2:$F$501) -> Delaware | R43: =_xlfn.XLOOKUP(B43,Customer_Cleaned!$A$2:$A$501,Customer_Cleaned!$G$2:$G$501) -> USA | S43: 3 | T43: 24.29 | U43: 0.12 | V43: 64.1256 | W43: COD
A44: 45230 | B44: CUST1155 | C44: PROD14 | D44: =VLOOKUP(C44,Product_Cleaned!$A$2:$B$101,2,FALSE) -> Decorative Wall Mirror | E44: =VLOOKUP(C44,Product_Cleaned!$A$2:$C$101,3,FALSE) -> Home | F44: =VLOOKUP(C44,Product_Cleaned!$A$2:$E$101,4,FALSE) -> Decor | G44: =VLOOKUP('Sales_Fact cleaned'!C119,Product_Cleaned!$A$2:$E$101,5, FALSE) -> Byrd, Stewart and Valdez | H44: STORE12 | I44: =_xlfn.XLOOKUP(H44,Store_Raw!$A$2:$A$21,Store_Raw!$B$2:$B$21) -> Thomas, Bridges and Harris | J44: =_xlfn.XLOOKUP(H44,Store_Raw!$A$2:$A$21,Store_Raw!$C$2:$C$21) -> North | K44: =_xlfn.XLOOKUP(H44,Store_Raw!$A$2:$A$21,Store_Raw!$D$2:$D$21) -> Sabrinatown | L44: =_xlfn.XLOOKUP(H44,Store_Raw!$A$2:$A$21,Store_Raw!$E$2:$E$21) -> Online | M44: =VLOOKUP(B44,Customer_Cleaned!$A$2:$H$501,2,FALSE) -> Curtis Haynes | N44: =VLOOKUP(B44,Customer_Cleaned!$A$2:$H$501,3,FALSE) -> 60 | O44: =VLOOKUP(B44,Customer_Cleaned!$A$2:$H$501,4,FALSE) -> Female | P44: =VLOOKUP(B44,Customer_Cleaned!$A$2:$H$501,8,FALSE) -> Platinum | Q44: =_xlfn.XLOOKUP('Sales_Fact cleaned'!B119,Customer_Cleaned!$A$2:$A$501,Customer_Cleaned!$F$2:$F$501) -> South Carolina | R44: =_xlfn.XLOOKUP(B44,Customer_Cleaned!$A$2:$A$501,Customer_Cleaned!$G$2:$G$501) -> USA | S44: 1 | T44: 68.21 | U44: 0.05 | V44: 64.7995 | W44: Credit Card
A45: 45230 | B45: CUST1112 | C45: PROD40 | D45: =VLOOKUP(C45,Product_Cleaned!$A$2:$B$101,2,FALSE) -> Noise-Canceling Headphones | E45: =VLOOKUP(C45,Product_Cleaned!$A$2:$C$101,3,FALSE) -> Electronics | F45: =VLOOKUP(C45,Product_Cleaned!$A$2:$E$101,4,FALSE) -> Audio | G45: =VLOOKUP('Sales_Fact cleaned'!C628,Product_Cleaned!$A$2:$E$101,5, FALSE) -> Smith-Charles | H45: STORE0 | I45: =_xlfn.XLOOKUP(H45,Store_Raw!$A$2:$A$21,Store_Raw!$B$2:$B$21) -> Rivera-Warner | J45: =_xlfn.XLOOKUP(H45,Store_Raw!$A$2:$A$21,Store_Raw!$C$2:$C$21) -> East | K45: =_xlfn.XLOOKUP(H45,Store_Raw!$A$2:$A$21,Store_Raw!$D$2:$D$21) -> Washingtonfurt | L45: =_xlfn.XLOOKUP(H45,Store_Raw!$A$2:$A$21,Store_Raw!$E$2:$E$21) -> Flagship | M45: =VLOOKUP(B45,Customer_Cleaned!$A$2:$H$501,2,FALSE) -> David Cole | N45: =VLOOKUP(B45,Customer_Cleaned!$A$2:$H$501,3,FALSE) -> 27 | O45: =VLOOKUP(B45,Customer_Cleaned!$A$2:$H$501,4,FALSE) -> Female | P45: =VLOOKUP(B45,Customer_Cleaned!$A$2:$H$501,8,FALSE) -> Bronze | Q45: =_xlfn.XLOOKUP('Sales_Fact cleaned'!B628,Customer_Cleaned!$A$2:$A$501,Customer_Cleaned!$F$2:$F$501) -> Arizona | R45: =_xlfn.XLOOKUP(B45,Customer_Cleaned!$A$2:$A$501,Customer_Cleaned!$G$2:$G$501) -> USA | S45: 1 | T45: 70.52 | U45: 0.08 | V45: 64.8784 | W45: PayPal
A46: 45230 | B46: CUST1197 | C46: PROD21 | D46: =VLOOKUP(C46,Product_Cleaned!$A$2:$B$101,2,FALSE) -> Multi-Purpose Storage Box | E46: =VLOOKUP(C46,Product_Cleaned!$A$2:$C$101,3,FALSE) -> Home | F46: =VLOOKUP(C46,Product_Cleaned!$A$2:$E$101,4,FALSE) -> Storage | G46: =VLOOKUP('Sales_Fact cleaned'!C1204,Product_Cleaned!$A$2:$E$101,5, FALSE) -> Pineda Ltd | H46: STORE8 | I46: =_xlfn.XLOOKUP(H46,Store_Raw!$A$2:$A$21,Store_Raw!$B$2:$B$21) -> Bean, Jones and Park | J46: =_xlfn.XLOOKUP(H46,Store_Raw!$A$2:$A$21,Store_Raw!$C$2:$C$21) -> West | K46: =_xlfn.XLOOKUP(H46,Store_Raw!$A$2:$A$21,Store_Raw!$D$2:$D$21) -> Thompsonborough | L46: =_xlfn.XLOOKUP(H46,Store_Raw!$A$2:$A$21,Store_Raw!$E$2:$E$21) -> Online | M46: =VLOOKUP(B46,Customer_Cleaned!$A$2:$H$501,2,FALSE) -> Andrea Jacobs | N46: =VLOOKUP(B46,Customer_Cleaned!$A$2:$H$501,3,FALSE) -> 45 | O46: =VLOOKUP(B46,Customer_Cleaned!$A$2:$H$501,4,FALSE) -> Female | P46: =VLOOKUP(B46,Customer_Cleaned!$A$2:$H$501,8,FALSE) -> Silver | Q46: =_xlfn.XLOOKUP('Sales_Fact cleaned'!B1204,Customer_Cleaned!$A$2:$A$501,Customer_Cleaned!$F$2:$F$501) -> Idaho | R46: =_xlfn.XLOOKUP(B46,Customer_Cleaned!$A$2:$A$501,Customer_Cleaned!$G$2:$G$501) -> USA | S46: 1 | T46: 66.22 | U46: 0.02 | V46: 64.8956 | W46: Credit Card
A47: 45231 | B47: CUST1257 | C47: PROD68 | D47: =VLOOKUP(C47,Product_Cleaned!$A$2:$B$101,2,FALSE) -> Wooden Nightstand | E47: =VLOOKUP(C47,Product_Cleaned!$A$2:$C$101,3,FALSE) -> Home | F47: =VLOOKUP(C47,Product_Cleaned!$A$2:$E$101,4,FALSE) -> Furniture | G47: =VLOOKUP('Sales_Fact cleaned'!C1867,Product_Cleaned!$A$2:$E$101,5, FALSE) -> Collins-Stephenson | H47: STORE9 | I47: =_xlfn.XLOOKUP(H47,Store_Raw!$A$2:$A$21,Store_Raw!$B$2:$B$21) -> Moore, Padilla and Butler | J47: =_xlfn.XLOOKUP(H47,Store_Raw!$A$2:$A$21,Store_Raw!$C$2:$C$21) -> South | K47: =_xlfn.XLOOKUP(H47,Store_Raw!$A$2:$A$21,Store_Raw!$D$2:$D$21) -> East Johnstad | L47: =_xlfn.XLOOKUP(H47,Store_Raw!$A$2:$A$21,Store_Raw!$E$2:$E$21) -> Flagship | M47: =VLOOKUP(B47,Customer_Cleaned!$A$2:$H$501,2,FALSE) -> Christopher David | N47: =VLOOKUP(B47,Customer_Cleaned!$A$2:$H$501,3,FALSE) -> 42 | O47: =VLOOKUP(B47,Customer_Cleaned!$A$2:$H$501,4,FALSE) -> Male | P47: =VLOOKUP(B47,Customer_Cleaned!$A$2:$H$501,8,FALSE) -> Silver | Q47: =_xlfn.XLOOKUP('Sales_Fact cleaned'!B1867,Customer_Cleaned!$A$2:$A$501,Customer_Cleaned!$F$2:$F$501) -> California | R47: =_xlfn.XLOOKUP(B47,Customer_Cleaned!$A$2:$A$501,Customer_Cleaned!$G$2:$G$501) -> USA | S47: 1 | T47: 78.5 | U47: 0.17 | V47: 65.155 | W47: PayPal
A48: 45231 | B48: CUST1421 | C48: PROD81 | D48: =VLOOKUP(C48,Product_Cleaned!$A$2:$B$101,2,FALSE) -> Badminton Racket Set | E48: =VLOOKUP(C48,Product_Cleaned!$A$2:$C$101,3,FALSE) -> Sports | F48: =VLOOKUP(C48,Product_Cleaned!$A$2:$E$101,4,FALSE) -> Equipment | G48: =VLOOKUP('Sales_Fact cleaned'!C251,Product_Cleaned!$A$2:$E$101,5, FALSE) -> Bruce-Bowen | H48: STORE8 | I48: =_xlfn.XLOOKUP(H48,Store_Raw!$A$2:$A$21,Store_Raw!$B$2:$B$21) -> Bean, Jones and Park | J48: =_xlfn.XLOOKUP(H48,Store_Raw!$A$2:$A$21,Store_Raw!$C$2:$C$21) -> West | K48: =_xlfn.XLOOKUP(H48,Store_Raw!$A$2:$A$21,Store_Raw!$D$2:$D$21) -> Thompsonborough | L48: =_xlfn.XLOOKUP(H48,Store_Raw!$A$2:$A$21,Store_Raw!$E$2:$E$21) -> Online | M48: =VLOOKUP(B48,Customer_Cleaned!$A$2:$H$501,2,FALSE) -> Holly Robinson | N48: =VLOOKUP(B48,Customer_Cleaned!$A$2:$H$501,3,FALSE) -> 45 | O48: =VLOOKUP(B48,Customer_Cleaned!$A$2:$H$501,4,FALSE) -> Female | P48: =VLOOKUP(B48,Customer_Cleaned!$A$2:$H$501,8,FALSE) -> Silver | Q48: =_xlfn.XLOOKUP('Sales_Fact cleaned'!B251,Customer_Cleaned!$A$2:$A$501,Customer_Cleaned!$F$2:$F$501) -> Vermont | R48: =_xlfn.XLOOKUP(B48,Customer_Cleaned!$A$2:$A$501,Customer_Cleaned!$G$2:$G$501) -> USA | S48: 4 | T48: 22.51 | U48: 0.27 | V48: 65.7292 | W48: PayPal
A49: 45232 | B49: CUST1048 | C49: PROD95 | D49: =VLOOKUP(C49,Product_Cleaned!$A$2:$B$101,2,FALSE) -> Sports Stopwatch Basic | E49: =VLOOKUP(C49,Product_Cleaned!$A$2:$C$101,3,FALSE) -> Sports | F49: =VLOOKUP(C49,Product_Cleaned!$A$2:$E$101,4,FALSE) -> Accessories | G49: =VLOOKUP('Sales_Fact cleaned'!C1561,Product_Cleaned!$A$2:$E$101,5, FALSE) -> Cline-Mccarthy | H49: STORE14 | I49: =_xlfn.XLOOKUP(H49,Store_Raw!$A$2:$A$21,Store_Raw!$B$2:$B$21) -> Mcdonald Inc | J49: =_xlfn.XLOOKUP(H49,Store_Raw!$A$2:$A$21,Store_Raw!$C$2:$C$21) -> South | K49: =_xlfn.XLOOKUP(H49,Store_Raw!$A$2:$A$21,Store_Raw!$D$2:$D$21) -> Christopherland | L49: =_xlfn.XLOOKUP(H49,Store_Raw!$A$2:$A$21,Store_Raw!$E$2:$E$21) -> Outlet | M49: =VLOOKUP(B49,Customer_Cleaned!$A$2:$H$501,2,FALSE) -> April Mullins | N49: =VLOOKUP(B49,Customer_Cleaned!$A$2:$H$501,3,FALSE) -> 54 | O49: =VLOOKUP(B49,Customer_Cleaned!$A$2:$H$501,4,FALSE) -> Male | P49: =VLOOKUP(B49,Customer_Cleaned!$A$2:$H$501,8,FALSE) -> Platinum | Q49: =_xlfn.XLOOKUP('Sales_Fact cleaned'!B1561,Customer_Cleaned!$A$2:$A$501,Customer_Cleaned!$F$2:$F$501) -> Indiana | R49: =_xlfn.XLOOKUP(B49,Customer_Cleaned!$A$2:$A$501,Customer_Cleaned!$G$2:$G$501) -> USA | S49: 4 | T49: 20.09 | U49: 0.16 | V49: 67.5024 | W49: COD
A50: 45232 | B50: CUST1362 | C50: PROD83 | D50: =VLOOKUP(C50,Product_Cleaned!$A$2:$B$101,2,FALSE) -> Hydrating Face Cleanser | E50: =VLOOKUP(C50,Product_Cleaned!$A$2:$C$101,3,FALSE) -> Beauty | F50: =VLOOKUP(C50,Product_Cleaned!$A$2:$E$101,4,FALSE) -> Skincare | G50: =VLOOKUP('Sales_Fact cleaned'!C1583,Product_Cleaned!$A$2:$E$101,5, FALSE) -> Shepherd-Gould | H50: STORE0 | I50: =_xlfn.XLOOKUP(H50,Store_Raw!$A$2:$A$21,Store_Raw!$B$2:$B$21) -> Rivera-Warner | J50: =_xlfn.XLOOKUP(H50,Store_Raw!$A$2:$A$21,Store_Raw!$C$2:$C$21) -> East | K50: =_xlfn.XLOOKUP(H50,Store_Raw!$A$2:$A$21,Store_Raw!$D$2:$D$21) -> Washingtonfurt | L50: =_xlfn.XLOOKUP(H50,Store_Raw!$A$2:$A$21,Store_Raw!$E$2:$E$21) -> Flagship | M50: =VLOOKUP(B50,Customer_Cleaned!$A$2:$H$501,2,FALSE) -> Joshua Smith Dvm | N50: =VLOOKUP(B50,Customer_Cleaned!$A$2:$H$501,3,FALSE) -> 60 | O50: =VLOOKUP(B50,Customer_Cleaned!$A$2:$H$501,4,FALSE) -> Male | P50: =VLOOKUP(B50,Customer_Cleaned!$A$2:$H$501,8,FALSE) -> Platinum | Q50: =_xlfn.XLOOKUP('Sales_Fact cleaned'!B1583,Customer_Cleaned!$A$2:$A$501,Customer_Cleaned!$F$2:$F$501) -> Alabama | R50: =_xlfn.XLOOKUP(B50,Customer_Cleaned!$A$2:$A$501,Customer_Cleaned!$G$2:$G$501) -> USA | S50: 1 | T50: 92.83 | U50: 0.26 | V50: 68.6942 | W50: Credit Card
A51: 45233 | B51: CUST1020 | C51: PROD37 | D51: =VLOOKUP(C51,Product_Cleaned!$A$2:$B$101,2,FALSE) -> Men's Casual Sneakers | E51: =VLOOKUP(C51,Product_Cleaned!$A$2:$C$101,3,FALSE) -> Clothing | F51: =VLOOKUP(C51,Product_Cleaned!$A$2:$E$101,4,FALSE) -> Footwear | G51: =VLOOKUP('Sales_Fact cleaned'!C626,Product_Cleaned!$A$2:$E$101,5, FALSE) -> Zhang Inc | H51: STORE16 | I51: =_xlfn.XLOOKUP(H51,Store_Raw!$A$2:$A$21,Store_Raw!$B$2:$B$21) -> Frederick-Wright | J51: =_xlfn.XLOOKUP(H51,Store_Raw!$A$2:$A$21,Store_Raw!$C$2:$C$21) -> West | K51: =_xlfn.XLOOKUP(H51,Store_Raw!$A$2:$A$21,Store_Raw!$D$2:$D$21) -> New Jimmymouth | L51: =_xlfn.XLOOKUP(H51,Store_Raw!$A$2:$A$21,Store_Raw!$E$2:$E$21) -> Flagship | M51: =VLOOKUP(B51,Customer_Cleaned!$A$2:$H$501,2,FALSE) -> Bridget Allen | N51: =VLOOKUP(B51,Customer_Cleaned!$A$2:$H$501,3,FALSE) -> 59 | O51: =VLOOKUP(B51,Customer_Cleaned!$A$2:$H$501,4,FALSE) -> Male | P51: =VLOOKUP(B51,Customer_Cleaned!$A$2:$H$501,8,FALSE) -> Platinum | Q51: =_xlfn.XLOOKUP('Sales_Fact cleaned'!B626,Customer_Cleaned!$A$2:$A$501,Customer_Cleaned!$F$2:$F$501) -> Pennsylvania | R51: =_xlfn.XLOOKUP(B51,Customer_Cleaned!$A$2:$A$501,Customer_Cleaned!$G$2:$G$501) -> USA | S51: 4 | T51: 21.12 | U51: 0.18 | V51: 69.2736 | W51: PayPal
A52: 45233 | B52: CUST1261 | C52: PROD42 | D52: =VLOOKUP(C52,Product_Cleaned!$A$2:$B$101,2,FALSE) -> Smart Home WiFi Camera | E52: =VLOOKUP(C52,Product_Cleaned!$A$2:$C$101,3,FALSE) -> Electronics | F52: =VLOOKUP(C52,Product_Cleaned!$A$2:$E$101,4,FALSE) -> Accessories | G52: =VLOOKUP('Sales_Fact cleaned'!C1520,Product_Cleaned!$A$2:$E$101,5, FALSE) -> Ramirez-Hanson | H52: STORE2 | I52: =_xlfn.XLOOKUP(H52,Store_Raw!$A$2:$A$21,Store_Raw!$B$2:$B$21) -> Black-Horn | J52: =_xlfn.XLOOKUP(H52,Store_Raw!$A$2:$A$21,Store_Raw!$C$2:$C$21) -> South | K52: =_xlfn.XLOOKUP(H52,Store_Raw!$A$2:$A$21,Store_Raw!$D$2:$D$21) -> North Nancyview | L52: =_xlfn.XLOOKUP(H52,Store_Raw!$A$2:$A$21,Store_Raw!$E$2:$E$21) -> Outlet | M52: =VLOOKUP(B52,Customer_Cleaned!$A$2:$H$501,2,FALSE) -> Carol Bishop | N52: =VLOOKUP(B52,Customer_Cleaned!$A$2:$H$501,3,FALSE) -> 27 | O52: =VLOOKUP(B52,Customer_Cleaned!$A$2:$H$501,4,FALSE) -> Female | P52: =VLOOKUP(B52,Customer_Cleaned!$A$2:$H$501,8,FALSE) -> Bronze | Q52: =_xlfn.XLOOKUP('Sales_Fact cleaned'!B1520,Customer_Cleaned!$A$2:$A$501,Customer_Cleaned!$F$2:$F$501) -> Alaska | R52: =_xlfn.XLOOKUP(B52,Customer_Cleaned!$A$2:$A$501,Customer_Cleaned!$G$2:$G$501) -> USA | S52: 2 | T52: 42.97 | U52: 0.18 | V52: 70.4708 | W52: COD
A53: 45233 | B53: CUST1436 | C53: PROD52 | D53: =VLOOKUP(C53,Product_Cleaned!$A$2:$B$101,2,FALSE) -> Rugby Ball | E53: =VLOOKUP(C53,Product_Cleaned!$A$2:$C$101,3,FALSE) -> Sports | F53: =VLOOKUP(C53,Product_Cleaned!$A$2:$E$101,4,FALSE) -> Team Sports | G53: =VLOOKUP('Sales_Fact cleaned'!C573,Product_Cleaned!$A$2:$E$101,5, FALSE) -> Sims Inc | H53: STORE18 | I53: =_xlfn.XLOOKUP(H53,Store_Raw!$A$2:$A$21,Store_Raw!$B$2:$B$21) -> Guerrero-Schmitt | J53: =_xlfn.XLOOKUP(H53,Store_Raw!$A$2:$A$21,Store_Raw!$C$2:$C$21) -> East | K53: =_xlfn.XLOOKUP(H53,Store_Raw!$A$2:$A$21,Store_Raw!$D$2:$D$21) -> East Stevechester | L53: =_xlfn.XLOOKUP(H53,Store_Raw!$A$2:$A$21,Store_Raw!$E$2:$E$21) -> Flagship | M53: =VLOOKUP(B53,Customer_Cleaned!$A$2:$H$501,2,FALSE) -> Sharon Simpson | N53: =VLOOKUP(B53,Customer_Cleaned!$A$2:$H$501,3,FALSE) -> 61 | O53: =VLOOKUP(B53,Customer_Cleaned!$A$2:$H$501,4,FALSE) -> Male | P53: =VLOOKUP(B53,Customer_Cleaned!$A$2:$H$501,8,FALSE) -> Platinum | Q53: =_xlfn.XLOOKUP('Sales_Fact cleaned'!B573,Customer_Cleaned!$A$2:$A$501,Customer_Cleaned!$F$2:$F$501) -> Arizona | R53: =_xlfn.XLOOKUP(B53,Customer_Cleaned!$A$2:$A$501,Customer_Cleaned!$G$2:$G$501) -> USA | S53: 1 | T53: 73.88 | U53: 0.04 | V53: 70.9248 | W53: PayPal
A54: 45234 | B54: CUST1087 | C54: PROD14 | D54: =VLOOKUP(C54,Product_Cleaned!$A$2:$B$101,2,FALSE) -> Decorative Wall Mirror | E54: =VLOOKUP(C54,Product_Cleaned!$A$2:$C$101,3,FALSE) -> Home | F54: =VLOOKUP(C54,Product_Cleaned!$A$2:$E$101,4,FALSE) -> Decor | G54: =VLOOKUP('Sales_Fact cleaned'!C1546,Product_Cleaned!$A$2:$E$101,5, FALSE) -> Carroll, Long and Mendoza | H54: STORE3 | I54: =_xlfn.XLOOKUP(H54,Store_Raw!$A$2:$A$21,Store_Raw!$B$2:$B$21) -> Johnson-Wright | J54: =_xlfn.XLOOKUP(H54,Store_Raw!$A$2:$A$21,Store_Raw!$C$2:$C$21) -> North | K54: =_xlfn.XLOOKUP(H54,Store_Raw!$A$2:$A$21,Store_Raw!$D$2:$D$21) -> Hoodberg | L54: =_xlfn.XLOOKUP(H54,Store_Raw!$A$2:$A$21,Store_Raw!$E$2:$E$21) -> Outlet | M54: =VLOOKUP(B54,Customer_Cleaned!$A$2:$H$501,2,FALSE) -> Melissa Duffy Md | N54: =VLOOKUP(B54,Customer_Cleaned!$A$2:$H$501,3,FALSE) -> 58 | O54: =VLOOKUP(B54,Customer_Cleaned!$A$2:$H$501,4,FALSE) -> Female | P54: =VLOOKUP(B54,Customer_Cleaned!$A$2:$H$501,8,FALSE) -> Platinum | Q54: =_xlfn.XLOOKUP('Sales_Fact cleaned'!B1546,Customer_Cleaned!$A$2:$A$501,Customer_Cleaned!$F$2:$F$501) -> Pennsylvania | R54: =_xlfn.XLOOKUP(B54,Customer_Cleaned!$A$2:$A$501,Customer_Cleaned!$G$2:$G$501) -> USA | S54: 2 | T54: 44.35 | U54: 0.2 | V54: 70.96 | W54: Credit Card
A55: 45234 | B55: CUST1322 | C55: PROD6 | D55: =VLOOKUP(C55,Product_Cleaned!$A$2:$B$101,2,FALSE) -> Herbal Face Moisturizer | E55: =VLOOKUP(C55,Product_Cleaned!$A$2:$C$101,3,FALSE) -> Beauty | F55: =VLOOKUP(C55,Product_Cleaned!$A$2:$E$101,4,FALSE) -> Skincare | G55: =VLOOKUP('Sales_Fact cleaned'!C1488,Product_Cleaned!$A$2:$E$101,5, FALSE) -> Taylor, Dodson and Johnston | H55: STORE0 | I55: =_xlfn.XLOOKUP(H55,Store_Raw!$A$2:$A$21,Store_Raw!$B$2:$B$21) -> Rivera-Warner | J55: =_xlfn.XLOOKUP(H55,Store_Raw!$A$2:$A$21,Store_Raw!$C$2:$C$21) -> East | K55: =_xlfn.XLOOKUP(H55,Store_Raw!$A$2:$A$21,Store_Raw!$D$2:$D$21) -> Washingtonfurt | L55: =_xlfn.XLOOKUP(H55,Store_Raw!$A$2:$A$21,Store_Raw!$E$2:$E$21) -> Flagship | M55: =VLOOKUP(B55,Customer_Cleaned!$A$2:$H$501,2,FALSE) -> Samuel Arias | N55: =VLOOKUP(B55,Customer_Cleaned!$A$2:$H$501,3,FALSE) -> 54 | O55: =VLOOKUP(B55,Customer_Cleaned!$A$2:$H$501,4,FALSE) -> Male | P55: =VLOOKUP(B55,Customer_Cleaned!$A$2:$H$501,8,FALSE) -> Platinum | Q55: =_xlfn.XLOOKUP('Sales_Fact cleaned'!B1488,Customer_Cleaned!$A$2:$A$501,Customer_Cleaned!$F$2:$F$501) -> Ohio | R55: =_xlfn.XLOOKUP(B55,Customer_Cleaned!$A$2:$A$501,Customer_Cleaned!$G$2:$G$501) -> USA | S55: 4 | T55: 24.72 | U55: 0.28 | V55: 71.1936 | W55: COD
A56: 45235 | B56: CUST1304 | C56: PROD50 | D56: =VLOOKUP(C56,Product_Cleaned!$A$2:$B$101,2,FALSE) -> Boxing Hand Wraps | E56: =VLOOKUP(C56,Product_Cleaned!$A$2:$C$101,3,FALSE) -> Sports | F56: =VLOOKUP(C56,Product_Cleaned!$A$2:$E$101,4,FALSE) -> Fitness | G56: =VLOOKUP('Sales_Fact cleaned'!C497,Product_Cleaned!$A$2:$E$101,5, FALSE) -> Murray, Gould and Ware | H56: STORE2 | I56: =_xlfn.XLOOKUP(H56,Store_Raw!$A$2:$A$21,Store_Raw!$B$2:$B$21) -> Black-Horn | J56: =_xlfn.XLOOKUP(H56,Store_Raw!$A$2:$A$21,Store_Raw!$C$2:$C$21) -> South | K56: =_xlfn.XLOOKUP(H56,Store_Raw!$A$2:$A$21,Store_Raw!$D$2:$D$21) -> North Nancyview | L56: =_xlfn.XLOOKUP(H56,Store_Raw!$A$2:$A$21,Store_Raw!$E$2:$E$21) -> Outlet | M56: =VLOOKUP(B56,Customer_Cleaned!$A$2:$H$501,2,FALSE) -> Miss Alexandria Li Dvm | N56: =VLOOKUP(B56,Customer_Cleaned!$A$2:$H$501,3,FALSE) -> 41 | O56: =VLOOKUP(B56,Customer_Cleaned!$A$2:$H$501,4,FALSE) -> Male | P56: =VLOOKUP(B56,Customer_Cleaned!$A$2:$H$501,8,FALSE) -> Silver | Q56: =_xlfn.XLOOKUP('Sales_Fact cleaned'!B497,Customer_Cleaned!$A$2:$A$501,Customer_Cleaned!$F$2:$F$501) -> South Carolina | R56: =_xlfn.XLOOKUP(B56,Customer_Cleaned!$A$2:$A$501,Customer_Cleaned!$G$2:$G$501) -> USA | S56: 1 | T56: 88.92 | U56: 0.19 | V56: 72.0252 | W56: Credit Card
A57: 45235 | B57: CUST1344 | C57: PROD60 | D57: =VLOOKUP(C57,Product_Cleaned!$A$2:$B$101,2,FALSE) -> Luxury Perfume Spray | E57: =VLOOKUP(C57,Product_Cleaned!$A$2:$C$101,3,FALSE) -> Beauty | F57: =VLOOKUP(C57,Product_Cleaned!$A$2:$E$101,4,FALSE) -> Fragrance | G57: =VLOOKUP('Sales_Fact cleaned'!C288,Product_Cleaned!$A$2:$E$101,5, FALSE) -> Taylor-Elliott | H57: STORE4 | I57: =_xlfn.XLOOKUP(H57,Store_Raw!$A$2:$A$21,Store_Raw!$B$2:$B$21) -> Alexander Group | J57: =_xlfn.XLOOKUP(H57,Store_Raw!$A$2:$A$21,Store_Raw!$C$2:$C$21) -> South | K57: =_xlfn.XLOOKUP(H57,Store_Raw!$A$2:$A$21,Store_Raw!$D$2:$D$21) -> Port Sharon | L57: =_xlfn.XLOOKUP(H57,Store_Raw!$A$2:$A$21,Store_Raw!$E$2:$E$21) -> Online | M57: =VLOOKUP(B57,Customer_Cleaned!$A$2:$H$501,2,FALSE) -> Evelyn Brown | N57: =VLOOKUP(B57,Customer_Cleaned!$A$2:$H$501,3,FALSE) -> 39 | O57: =VLOOKUP(B57,Customer_Cleaned!$A$2:$H$501,4,FALSE) -> Male | P57: =VLOOKUP(B57,Customer_Cleaned!$A$2:$H$501,8,FALSE) -> Silver | Q57: =_xlfn.XLOOKUP('Sales_Fact cleaned'!B288,Customer_Cleaned!$A$2:$A$501,Customer_Cleaned!$F$2:$F$501) -> Ohio | R57: =_xlfn.XLOOKUP(B57,Customer_Cleaned!$A$2:$A$501,Customer_Cleaned!$G$2:$G$501) -> USA | S57: 1 | T57: 88.78 | U57: 0.18 | V57: 72.7996 | W57: Credit Card
A58: 45235 | B58: CUST1499 | C58: PROD55 | D58: =VLOOKUP(C58,Product_Cleaned!$A$2:$B$101,2,FALSE) -> Ceramic Plant Pot | E58: =VLOOKUP(C58,Product_Cleaned!$A$2:$C$101,3,FALSE) -> Home | F58: =VLOOKUP(C58,Product_Cleaned!$A$2:$E$101,4,FALSE) -> Decor | G58: =VLOOKUP('Sales_Fact cleaned'!C1248,Product_Cleaned!$A$2:$E$101,5, FALSE) -> Erickson-Green | H58: STORE8 | I58: =_xlfn.XLOOKUP(H58,Store_Raw!$A$2:$A$21,Store_Raw!$B$2:$B$21) -> Bean, Jones and Park | J58: =_xlfn.XLOOKUP(H58,Store_Raw!$A$2:$A$21,Store_Raw!$C$2:$C$21) -> West | K58: =_xlfn.XLOOKUP(H58,Store_Raw!$A$2:$A$21,Store_Raw!$D$2:$D$21) -> Thompsonborough | L58: =_xlfn.XLOOKUP(H58,Store_Raw!$A$2:$A$21,Store_Raw!$E$2:$E$21) -> Online | M58: =VLOOKUP(B58,Customer_Cleaned!$A$2:$H$501,2,FALSE) -> Philip Pennington | N58: =VLOOKUP(B58,Customer_Cleaned!$A$2:$H$501,3,FALSE) -> 27 | O58: =VLOOKUP(B58,Customer_Cleaned!$A$2:$H$501,4,FALSE) -> Female | P58: =VLOOKUP(B58,Customer_Cleaned!$A$2:$H$501,8,FALSE) -> Bronze | Q58: =_xlfn.XLOOKUP('Sales_Fact cleaned'!B1248,Customer_Cleaned!$A$2:$A$501,Customer_Cleaned!$F$2:$F$501) -> California | R58: =_xlfn.XLOOKUP(B58,Customer_Cleaned!$A$2:$A$501,Customer_Cleaned!$G$2:$G$501) -> USA | S58: 1 | T58: 79 | U58: 0.04 | V58: 75.84 | W58: PayPal
A59: 45235 | B59: CUST1310 | C59: PROD61 | D59: =VLOOKUP(C59,Product_Cleaned!$A$2:$B$101,2,FALSE) -> Tennis Ball 3-Pack | E59: =VLOOKUP(C59,Product_Cleaned!$A$2:$C$101,3,FALSE) -> Sports | F59: =VLOOKUP(C59,Product_Cleaned!$A$2:$E$101,4,FALSE) -> Equipment | G59: =VLOOKUP('Sales_Fact cleaned'!C805,Product_Cleaned!$A$2:$E$101,5, FALSE) -> Wilson Group | H59: STORE5 | I59: =_xlfn.XLOOKUP(H59,Store_Raw!$A$2:$A$21,Store_Raw!$B$2:$B$21) -> Gray Ltd | J59: =_xlfn.XLOOKUP(H59,Store_Raw!$A$2:$A$21,Store_Raw!$C$2:$C$21) -> North | K59: =_xlfn.XLOOKUP(H59,Store_Raw!$A$2:$A$21,Store_Raw!$D$2:$D$21) -> New Michaelchester | L59: =_xlfn.XLOOKUP(H59,Store_Raw!$A$2:$A$21,Store_Raw!$E$2:$E$21) -> Outlet | M59: =VLOOKUP(B59,Customer_Cleaned!$A$2:$H$501,2,FALSE) -> Kara Dodson | N59: =VLOOKUP(B59,Customer_Cleaned!$A$2:$H$501,3,FALSE) -> 20 | O59: =VLOOKUP(B59,Customer_Cleaned!$A$2:$H$501,4,FALSE) -> Male | P59: =VLOOKUP(B59,Customer_Cleaned!$A$2:$H$501,8,FALSE) -> Bronze | Q59: =_xlfn.XLOOKUP('Sales_Fact cleaned'!B805,Customer_Cleaned!$A$2:$A$501,Customer_Cleaned!$F$2:$F$501) -> West Virginia | R59: =_xlfn.XLOOKUP(B59,Customer_Cleaned!$A$2:$A$501,Customer_Cleaned!$G$2:$G$501) -> USA | S59: 1 | T59: 85.58 | U59: 0.1 | V59: 77.022 | W59: COD
A60: 45235 | B60: CUST1213 | C60: PROD1 | D60: =VLOOKUP(C60,Product_Cleaned!$A$2:$B$101,2,FALSE) -> Men's Graphic T-Shirt | E60: =VLOOKUP(C60,Product_Cleaned!$A$2:$C$101,3,FALSE) -> Clothing | F60: =VLOOKUP(C60,Product_Cleaned!$A$2:$E$101,4,FALSE) -> Tops | G60: =VLOOKUP('Sales_Fact cleaned'!C449,Product_Cleaned!$A$2:$E$101,5, FALSE) -> Gardner-Montes | H60: STORE3 | I60: =_xlfn.XLOOKUP(H60,Store_Raw!$A$2:$A$21,Store_Raw!$B$2:$B$21) -> Johnson-Wright | J60: =_xlfn.XLOOKUP(H60,Store_Raw!$A$2:$A$21,Store_Raw!$C$2:$C$21) -> North | K60: =_xlfn.XLOOKUP(H60,Store_Raw!$A$2:$A$21,Store_Raw!$D$2:$D$21) -> Hoodberg | L60: =_xlfn.XLOOKUP(H60,Store_Raw!$A$2:$A$21,Store_Raw!$E$2:$E$21) -> Outlet | M60: =VLOOKUP(B60,Customer_Cleaned!$A$2:$H$501,2,FALSE) -> Stuart Johnson | N60: =VLOOKUP(B60,Customer_Cleaned!$A$2:$H$501,3,FALSE) -> 42 | O60: =VLOOKUP(B60,Customer_Cleaned!$A$2:$H$501,4,FALSE) -> Female | P60: =VLOOKUP(B60,Customer_Cleaned!$A$2:$H$501,8,FALSE) -> Silver | Q60: =_xlfn.XLOOKUP('Sales_Fact cleaned'!B449,Customer_Cleaned!$A$2:$A$501,Customer_Cleaned!$F$2:$F$501) -> New York | R60: =_xlfn.XLOOKUP(B60,Customer_Cleaned!$A$2:$A$501,Customer_Cleaned!$G$2:$G$501) -> USA | S60: 1 | T60: 94.26 | U60: 0.18 | V60: 77.2932 | W60: COD
A61: 45235 | B61: CUST1043 | C61: PROD50 | D61: =VLOOKUP(C61,Product_Cleaned!$A$2:$B$101,2,FALSE) -> Boxing Hand Wraps | E61: =VLOOKUP(C61,Product_Cleaned!$A$2:$C$101,3,FALSE) -> Sports | F61: =VLOOKUP(C61,Product_Cleaned!$A$2:$E$101,4,FALSE) -> Fitness | G61: =VLOOKUP('Sales_Fact cleaned'!C219,Product_Cleaned!$A$2:$E$101,5, FALSE) -> Ramirez-Hanson | H61: STORE5 | I61: =_xlfn.XLOOKUP(H61,Store_Raw!$A$2:$A$21,Store_Raw!$B$2:$B$21) -> Gray Ltd | J61: =_xlfn.XLOOKUP(H61,Store_Raw!$A$2:$A$21,Store_Raw!$C$2:$C$21) -> North | K61: =_xlfn.XLOOKUP(H61,Store_Raw!$A$2:$A$21,Store_Raw!$D$2:$D$21) -> New Michaelchester | L61: =_xlfn.XLOOKUP(H61,Store_Raw!$A$2:$A$21,Store_Raw!$E$2:$E$21) -> Outlet | M61: =VLOOKUP(B61,Customer_Cleaned!$A$2:$H$501,2,FALSE) -> Joseph Snow | N61: =VLOOKUP(B61,Customer_Cleaned!$A$2:$H$501,3,FALSE) -> 45 | O61: =VLOOKUP(B61,Customer_Cleaned!$A$2:$H$501,4,FALSE) -> Male | P61: =VLOOKUP(B61,Customer_Cleaned!$A$2:$H$501,8,FALSE) -> Silver | Q61: =_xlfn.XLOOKUP('Sales_Fact cleaned'!B219,Customer_Cleaned!$A$2:$A$501,Customer_Cleaned!$F$2:$F$501) -> Arkansas | R61: =_xlfn.XLOOKUP(B61,Customer_Cleaned!$A$2:$A$501,Customer_Cleaned!$G$2:$G$501) -> USA | S61: 2 | T61: 42.04 | U61: 0.07 | V61: 78.1944 | W61: PayPal
A62: 45235 | B62: CUST1142 | C62: PROD38 | D62: =VLOOKUP(C62,Product_Cleaned!$A$2:$B$101,2,FALSE) -> Sports Water Hydration Pack | E62: =VLOOKUP(C62,Product_Cleaned!$A$2:$C$101,3,FALSE) -> Sports | F62: =VLOOKUP(C62,Product_Cleaned!$A$2:$E$101,4,FALSE) -> Outdoor | G62: =VLOOKUP('Sales_Fact cleaned'!C1589,Product_Cleaned!$A$2:$E$101,5, FALSE) -> Hernandez Inc | H62: STORE8 | I62: =_xlfn.XLOOKUP(H62,Store_Raw!$A$2:$A$21,Store_Raw!$B$2:$B$21) -> Bean, Jones and Park | J62: =_xlfn.XLOOKUP(H62,Store_Raw!$A$2:$A$21,Store_Raw!$C$2:$C$21) -> West | K62: =_xlfn.XLOOKUP(H62,Store_Raw!$A$2:$A$21,Store_Raw!$D$2:$D$21) -> Thompsonborough | L62: =_xlfn.XLOOKUP(H62,Store_Raw!$A$2:$A$21,Store_Raw!$E$2:$E$21) -> Online | M62: =VLOOKUP(B62,Customer_Cleaned!$A$2:$H$501,2,FALSE) -> Maria Ramirez | N62: =VLOOKUP(B62,Customer_Cleaned!$A$2:$H$501,3,FALSE) -> 37 | O62: =VLOOKUP(B62,Customer_Cleaned!$A$2:$H$501,4,FALSE) -> Male | P62: =VLOOKUP(B62,Customer_Cleaned!$A$2:$H$501,8,FALSE) -> Silver | Q62: =_xlfn.XLOOKUP('Sales_Fact cleaned'!B1589,Customer_Cleaned!$A$2:$A$501,Customer_Cleaned!$F$2:$F$501) -> Ohio | R62: =_xlfn.XLOOKUP(B62,Customer_Cleaned!$A$2:$A$501,Customer_Cleaned!$G$2:$G$501) -> USA | S62: 1 | T62: 91.38 | U62: 0.14 | V62: 78.5868 | W62: Credit Card
A63: 45236 | B63: CUST1405 | C63: PROD46 | D63: =VLOOKUP(C63,Product_Cleaned!$A$2:$B$101,2,FALSE) -> Men's Winter Jacket | E63: =VLOOKUP(C63,Product_Cleaned!$A$2:$C$101,3,FALSE) -> Clothing | F63: =VLOOKUP(C63,Product_Cleaned!$A$2:$E$101,4,FALSE) -> Outerwear | G63: =VLOOKUP('Sales_Fact cleaned'!C1357,Product_Cleaned!$A$2:$E$101,5, FALSE) -> Hill PLC | H63: STORE9 | I63: =_xlfn.XLOOKUP(H63,Store_Raw!$A$2:$A$21,Store_Raw!$B$2:$B$21) -> Moore, Padilla and Butler | J63: =_xlfn.XLOOKUP(H63,Store_Raw!$A$2:$A$21,Store_Raw!$C$2:$C$21) -> South | K63: =_xlfn.XLOOKUP(H63,Store_Raw!$A$2:$A$21,Store_Raw!$D$2:$D$21) -> East Johnstad | L63: =_xlfn.XLOOKUP(H63,Store_Raw!$A$2:$A$21,Store_Raw!$E$2:$E$21) -> Flagship | M63: =VLOOKUP(B63,Customer_Cleaned!$A$2:$H$501,2,FALSE) -> Eric Wolfe | N63: =VLOOKUP(B63,Customer_Cleaned!$A$2:$H$501,3,FALSE) -> 18 | O63: =VLOOKUP(B63,Customer_Cleaned!$A$2:$H$501,4,FALSE) -> Female | P63: =VLOOKUP(B63,Customer_Cleaned!$A$2:$H$501,8,FALSE) -> Bronze | Q63: =_xlfn.XLOOKUP('Sales_Fact cleaned'!B1357,Customer_Cleaned!$A$2:$A$501,Customer_Cleaned!$F$2:$F$501) -> Arizona | R63: =_xlfn.XLOOKUP(B63,Customer_Cleaned!$A$2:$A$501,Customer_Cleaned!$G$2:$G$501) -> USA | S63: 1 | T63: 83.83 | U63: 0.05 | V63: 79.6385 | W63: COD
A64: 45236 | B64: CUST1097 | C64: PROD55 | D64: =VLOOKUP(C64,Product_Cleaned!$A$2:$B$101,2,FALSE) -> Ceramic Plant Pot | E64: =VLOOKUP(C64,Product_Cleaned!$A$2:$C$101,3,FALSE) -> Home | F64: =VLOOKUP(C64,Product_Cleaned!$A$2:$E$101,4,FALSE) -> Decor | G64: =VLOOKUP('Sales_Fact cleaned'!C1844,Product_Cleaned!$A$2:$E$101,5, FALSE) -> Murray, Gould and Ware | H64: STORE5 | I64: =_xlfn.XLOOKUP(H64,Store_Raw!$A$2:$A$21,Store_Raw!$B$2:$B$21) -> Gray Ltd | J64: =_xlfn.XLOOKUP(H64,Store_Raw!$A$2:$A$21,Store_Raw!$C$2:$C$21) -> North | K64: =_xlfn.XLOOKUP(H64,Store_Raw!$A$2:$A$21,Store_Raw!$D$2:$D$21) -> New Michaelchester | L64: =_xlfn.XLOOKUP(H64,Store_Raw!$A$2:$A$21,Store_Raw!$E$2:$E$21) -> Outlet | M64: =VLOOKUP(B64,Customer_Cleaned!$A$2:$H$501,2,FALSE) -> David Cobb | N64: =VLOOKUP(B64,Customer_Cleaned!$A$2:$H$501,3,FALSE) -> 36 | O64: =VLOOKUP(B64,Customer_Cleaned!$A$2:$H$501,4,FALSE) -> Male | P64: =VLOOKUP(B64,Customer_Cleaned!$A$2:$H$501,8,FALSE) -> Silver | Q64: =_xlfn.XLOOKUP('Sales_Fact cleaned'!B1844,Customer_Cleaned!$A$2:$A$501,Customer_Cleaned!$F$2:$F$501) -> Florida | R64: =_xlfn.XLOOKUP(B64,Customer_Cleaned!$A$2:$A$501,Customer_Cleaned!$G$2:$G$501) -> USA | S64: 1 | T64: 83.1 | U64: 0.04 | V64: 79.776 | W64: COD
A65: 45237 | B65: CUST1175 | C65: PROD6 | D65: =VLOOKUP(C65,Product_Cleaned!$A$2:$B$101,2,FALSE) -> Herbal Face Moisturizer | E65: =VLOOKUP(C65,Product_Cleaned!$A$2:$C$101,3,FALSE) -> Beauty | F65: =VLOOKUP(C65,Product_Cleaned!$A$2:$E$101,4,FALSE) -> Skincare | G65: =VLOOKUP('Sales_Fact cleaned'!C169,Product_Cleaned!$A$2:$E$101,5, FALSE) -> Gardner-Montes | H65: STORE3 | I65: =_xlfn.XLOOKUP(H65,Store_Raw!$A$2:$A$21,Store_Raw!$B$2:$B$21) -> Johnson-Wright | J65: =_xlfn.XLOOKUP(H65,Store_Raw!$A$2:$A$21,Store_Raw!$C$2:$C$21) -> North | K65: =_xlfn.XLOOKUP(H65,Store_Raw!$A$2:$A$21,Store_Raw!$D$2:$D$21) -> Hoodberg | L65: =_xlfn.XLOOKUP(H65,Store_Raw!$A$2:$A$21,Store_Raw!$E$2:$E$21) -> Outlet | M65: =VLOOKUP(B65,Customer_Cleaned!$A$2:$H$501,2,FALSE) -> Michelle Rogers | N65: =VLOOKUP(B65,Customer_Cleaned!$A$2:$H$501,3,FALSE) -> 56 | O65: =VLOOKUP(B65,Customer_Cleaned!$A$2:$H$501,4,FALSE) -> Male | P65: =VLOOKUP(B65,Customer_Cleaned!$A$2:$H$501,8,FALSE) -> Platinum | Q65: =_xlfn.XLOOKUP('Sales_Fact cleaned'!B169,Customer_Cleaned!$A$2:$A$501,Customer_Cleaned!$F$2:$F$501) -> Vermont | R65: =_xlfn.XLOOKUP(B65,Customer_Cleaned!$A$2:$A$501,Customer_Cleaned!$G$2:$G$501) -> USA | S65: 2 | T65: 42.51 | U65: 0.04 | V65: 81.6192 | W65: COD
A66: 45237 | B66: CUST1494 | C66: PROD19 | D66: =VLOOKUP(C66,Product_Cleaned!$A$2:$B$101,2,FALSE) -> Knee Support Brace | E66: =VLOOKUP(C66,Product_Cleaned!$A$2:$C$101,3,FALSE) -> Sports | F66: =VLOOKUP(C66,Product_Cleaned!$A$2:$E$101,4,FALSE) -> Equipment | G66: =VLOOKUP('Sales_Fact cleaned'!C1390,Product_Cleaned!$A$2:$E$101,5, FALSE) -> White, Reeves and Woods | H66: STORE14 | I66: =_xlfn.XLOOKUP(H66,Store_Raw!$A$2:$A$21,Store_Raw!$B$2:$B$21) -> Mcdonald Inc | J66: =_xlfn.XLOOKUP(H66,Store_Raw!$A$2:$A$21,Store_Raw!$C$2:$C$21) -> South | K66: =_xlfn.XLOOKUP(H66,Store_Raw!$A$2:$A$21,Store_Raw!$D$2:$D$21) -> Christopherland | L66: =_xlfn.XLOOKUP(H66,Store_Raw!$A$2:$A$21,Store_Raw!$E$2:$E$21) -> Outlet | M66: =VLOOKUP(B66,Customer_Cleaned!$A$2:$H$501,2,FALSE) -> Justin Lopez | N66: =VLOOKUP(B66,Customer_Cleaned!$A$2:$H$501,3,FALSE) -> 21 | O66: =VLOOKUP(B66,Customer_Cleaned!$A$2:$H$501,4,FALSE) -> Male | P66: =VLOOKUP(B66,Customer_Cleaned!$A$2:$H$501,8,FALSE) -> Bronze | Q66: =_xlfn.XLOOKUP('Sales_Fact cleaned'!B1390,Customer_Cleaned!$A$2:$A$501,Customer_Cleaned!$F$2:$F$501) -> Vermont | R66: =_xlfn.XLOOKUP(B66,Customer_Cleaned!$A$2:$A$501,Customer_Cleaned!$G$2:$G$501) -> USA | S66: 1 | T66: 90.72 | U66: 0.1 | V66: 81.648 | W66: COD
A67: 45238 | B67: CUST1387 | C67: PROD76 | D67: =VLOOKUP(C67,Product_Cleaned!$A$2:$B$101,2,FALSE) -> Wireless Mouse | E67: =VLOOKUP(C67,Product_Cleaned!$A$2:$C$101,3,FALSE) -> Electronics | F67: =VLOOKUP(C67,Product_Cleaned!$A$2:$E$101,4,FALSE) -> Computer | G67: =VLOOKUP('Sales_Fact cleaned'!C109,Product_Cleaned!$A$2:$E$101,5, FALSE) -> Dawson-Perkins | H67: STORE4 | I67: =_xlfn.XLOOKUP(H67,Store_Raw!$A$2:$A$21,Store_Raw!$B$2:$B$21) -> Alexander Group | J67: =_xlfn.XLOOKUP(H67,Store_Raw!$A$2:$A$21,Store_Raw!$C$2:$C$21) -> South | K67: =_xlfn.XLOOKUP(H67,Store_Raw!$A$2:$A$21,Store_Raw!$D$2:$D$21) -> Port Sharon | L67: =_xlfn.XLOOKUP(H67,Store_Raw!$A$2:$A$21,Store_Raw!$E$2:$E$21) -> Online | M67: =VLOOKUP(B67,Customer_Cleaned!$A$2:$H$501,2,FALSE) -> Timothy Gardner | N67: =VLOOKUP(B67,Customer_Cleaned!$A$2:$H$501,3,FALSE) -> 28 | O67: =VLOOKUP(B67,Customer_Cleaned!$A$2:$H$501,4,FALSE) -> Female | P67: =VLOOKUP(B67,Customer_Cleaned!$A$2:$H$501,8,FALSE) -> Bronze | Q67: =_xlfn.XLOOKUP('Sales_Fact cleaned'!B109,Customer_Cleaned!$A$2:$A$501,Customer_Cleaned!$F$2:$F$501) -> Louisiana | R67: =_xlfn.XLOOKUP(B67,Customer_Cleaned!$A$2:$A$501,Customer_Cleaned!$G$2:$G$501) -> USA | S67: 1 | T67: 106.07 | U67: 0.23 | V67: 81.6739 | W67: COD
A68: 45238 | B68: CUST1185 | C68: PROD66 | D68: =VLOOKUP(C68,Product_Cleaned!$A$2:$B$101,2,FALSE) -> Women's Hair Dryer Brush | E68: =VLOOKUP(C68,Product_Cleaned!$A$2:$C$101,3,FALSE) -> Beauty | F68: =VLOOKUP(C68,Product_Cleaned!$A$2:$E$101,4,FALSE) -> Haircare | G68: =VLOOKUP('Sales_Fact cleaned'!C1787,Product_Cleaned!$A$2:$E$101,5, FALSE) -> White, Reeves and Woods | H68: STORE9 | I68: =_xlfn.XLOOKUP(H68,Store_Raw!$A$2:$A$21,Store_Raw!$B$2:$B$21) -> Moore, Padilla and Butler | J68: =_xlfn.XLOOKUP(H68,Store_Raw!$A$2:$A$21,Store_Raw!$C$2:$C$21) -> South | K68: =_xlfn.XLOOKUP(H68,Store_Raw!$A$2:$A$21,Store_Raw!$D$2:$D$21) -> East Johnstad | L68: =_xlfn.XLOOKUP(H68,Store_Raw!$A$2:$A$21,Store_Raw!$E$2:$E$21) -> Flagship | M68: =VLOOKUP(B68,Customer_Cleaned!$A$2:$H$501,2,FALSE) -> Brent Rivas | N68: =VLOOKUP(B68,Customer_Cleaned!$A$2:$H$501,3,FALSE) -> 54 | O68: =VLOOKUP(B68,Customer_Cleaned!$A$2:$H$501,4,FALSE) -> Female | P68: =VLOOKUP(B68,Customer_Cleaned!$A$2:$H$501,8,FALSE) -> Platinum | Q68: =_xlfn.XLOOKUP('Sales_Fact cleaned'!B1787,Customer_Cleaned!$A$2:$A$501,Customer_Cleaned!$F$2:$F$501) -> Kansas | R68: =_xlfn.XLOOKUP(B68,Customer_Cleaned!$A$2:$A$501,Customer_Cleaned!$G$2:$G$501) -> USA | S68: 1 | T68: 87.78 | U68: 0.06 | V68: 82.5132 | W68: Credit Card
A69: 45239 | B69: CUST1036 | C69: PROD6 | D69: =VLOOKUP(C69,Product_Cleaned!$A$2:$B$101,2,FALSE) -> Herbal Face Moisturizer | E69: =VLOOKUP(C69,Product_Cleaned!$A$2:$C$101,3,FALSE) -> Beauty | F69: =VLOOKUP(C69,Product_Cleaned!$A$2:$E$101,4,FALSE) -> Skincare | G69: =VLOOKUP('Sales_Fact cleaned'!C1735,Product_Cleaned!$A$2:$E$101,5, FALSE) -> Ramirez-Hanson | H69: STORE8 | I69: =_xlfn.XLOOKUP(H69,Store_Raw!$A$2:$A$21,Store_Raw!$B$2:$B$21) -> Bean, Jones and Park | J69: =_xlfn.XLOOKUP(H69,Store_Raw!$A$2:$A$21,Store_Raw!$C$2:$C$21) -> West | K69: =_xlfn.XLOOKUP(H69,Store_Raw!$A$2:$A$21,Store_Raw!$D$2:$D$21) -> Thompsonborough | L69: =_xlfn.XLOOKUP(H69,Store_Raw!$A$2:$A$21,Store_Raw!$E$2:$E$21) -> Online | M69: =VLOOKUP(B69,Customer_Cleaned!$A$2:$H$501,2,FALSE) -> Thomas Phillips | N69: =VLOOKUP(B69,Customer_Cleaned!$A$2:$H$501,3,FALSE) -> 20 | O69: =VLOOKUP(B69,Customer_Cleaned!$A$2:$H$501,4,FALSE) -> Female | P69: =VLOOKUP(B69,Customer_Cleaned!$A$2:$H$501,8,FALSE) -> Bronze | Q69: =_xlfn.XLOOKUP('Sales_Fact cleaned'!B1735,Customer_Cleaned!$A$2:$A$501,Customer_Cleaned!$F$2:$F$501) -> New Mexico | R69: =_xlfn.XLOOKUP(B69,Customer_Cleaned!$A$2:$A$501,Customer_Cleaned!$G$2:$G$501) -> USA | S69: 1 | T69: 98.27 | U69: 0.16 | V69: 82.5468 | W69: COD
A70: 45239 | B70: CUST1130 | C70: PROD41 | D70: =VLOOKUP(C70,Product_Cleaned!$A$2:$B$101,2,FALSE) -> Yoga Exercise Mat | E70: =VLOOKUP(C70,Product_Cleaned!$A$2:$C$101,3,FALSE) -> Sports | F70: =VLOOKUP(C70,Product_Cleaned!$A$2:$E$101,4,FALSE) -> Fitness | G70: =VLOOKUP('Sales_Fact cleaned'!C1172,Product_Cleaned!$A$2:$E$101,5, FALSE) -> Smith-Charles | H70: STORE11 | I70: =_xlfn.XLOOKUP(H70,Store_Raw!$A$2:$A$21,Store_Raw!$B$2:$B$21) -> Aguirre-Keller | J70: =_xlfn.XLOOKUP(H70,Store_Raw!$A$2:$A$21,Store_Raw!$C$2:$C$21) -> South | K70: =_xlfn.XLOOKUP(H70,Store_Raw!$A$2:$A$21,Store_Raw!$D$2:$D$21) -> Lake Michael | L70: =_xlfn.XLOOKUP(H70,Store_Raw!$A$2:$A$21,Store_Raw!$E$2:$E$21) -> Online | M70: =VLOOKUP(B70,Customer_Cleaned!$A$2:$H$501,2,FALSE) -> Jamie Reyes | N70: =VLOOKUP(B70,Customer_Cleaned!$A$2:$H$501,3,FALSE) -> 29 | O70: =VLOOKUP(B70,Customer_Cleaned!$A$2:$H$501,4,FALSE) -> Male | P70: =VLOOKUP(B70,Customer_Cleaned!$A$2:$H$501,8,FALSE) -> Bronze | Q70: =_xlfn.XLOOKUP('Sales_Fact cleaned'!B1172,Customer_Cleaned!$A$2:$A$501,Customer_Cleaned!$F$2:$F$501) -> Arizona | R70: =_xlfn.XLOOKUP(B70,Customer_Cleaned!$A$2:$A$501,Customer_Cleaned!$G$2:$G$501) -> USA | S70: 3 | T70: 28.69 | U70: 0.02 | V70: 84.3486 | W70: PayPal
A71: 45240 | B71: CUST1143 | C71: PROD30 | D71: =VLOOKUP(C71,Product_Cleaned!$A$2:$B$101,2,FALSE) -> Stainless Steel Cutlery Set | E71: =VLOOKUP(C71,Product_Cleaned!$A$2:$C$101,3,FALSE) -> Home | F71: =VLOOKUP(C71,Product_Cleaned!$A$2:$E$101,4,FALSE) -> Kitchen | G71: =VLOOKUP('Sales_Fact cleaned'!C397,Product_Cleaned!$A$2:$E$101,5, FALSE) -> Ford, Murphy and Wilson | H71: STORE16 | I71: =_xlfn.XLOOKUP(H71,Store_Raw!$A$2:$A$21,Store_Raw!$B$2:$B$21) -> Frederick-Wright | J71: =_xlfn.XLOOKUP(H71,Store_Raw!$A$2:$A$21,Store_Raw!$C$2:$C$21) -> West | K71: =_xlfn.XLOOKUP(H71,Store_Raw!$A$2:$A$21,Store_Raw!$D$2:$D$21) -> New Jimmymouth | L71: =_xlfn.XLOOKUP(H71,Store_Raw!$A$2:$A$21,Store_Raw!$E$2:$E$21) -> Flagship | M71: =VLOOKUP(B71,Customer_Cleaned!$A$2:$H$501,2,FALSE) -> Carlos Skinner | N71: =VLOOKUP(B71,Customer_Cleaned!$A$2:$H$501,3,FALSE) -> 46 | O71: =VLOOKUP(B71,Customer_Cleaned!$A$2:$H$501,4,FALSE) -> Male | P71: =VLOOKUP(B71,Customer_Cleaned!$A$2:$H$501,8,FALSE) -> Silver | Q71: =_xlfn.XLOOKUP('Sales_Fact cleaned'!B397,Customer_Cleaned!$A$2:$A$501,Customer_Cleaned!$F$2:$F$501) -> Nebraska | R71: =_xlfn.XLOOKUP(B71,Customer_Cleaned!$A$2:$A$501,Customer_Cleaned!$G$2:$G$501) -> USA | S71: 1 | T71: 101.84 | U71: 0.17 | V71: 84.5272 | W71: Credit Card
A72: 45240 | B72: CUST1235 | C72: PROD92 | D72: =VLOOKUP(C72,Product_Cleaned!$A$2:$B$101,2,FALSE) -> Microwave Oven | E72: =VLOOKUP(C72,Product_Cleaned!$A$2:$C$101,3,FALSE) -> Home | F72: =VLOOKUP(C72,Product_Cleaned!$A$2:$E$101,4,FALSE) -> Appliances | G72: =VLOOKUP('Sales_Fact cleaned'!C3,Product_Cleaned!$A$2:$E$101,5, FALSE) -> Soto-Ellis | H72: STORE11 | I72: =_xlfn.XLOOKUP(H72,Store_Raw!$A$2:$A$21,Store_Raw!$B$2:$B$21) -> Aguirre-Keller | J72: =_xlfn.XLOOKUP(H72,Store_Raw!$A$2:$A$21,Store_Raw!$C$2:$C$21) -> South | K72: =_xlfn.XLOOKUP(H72,Store_Raw!$A$2:$A$21,Store_Raw!$D$2:$D$21) -> Lake Michael | L72: =_xlfn.XLOOKUP(H72,Store_Raw!$A$2:$A$21,Store_Raw!$E$2:$E$21) -> Online | M72: =VLOOKUP(B72,Customer_Cleaned!$A$2:$H$501,2,FALSE) -> Jon Ortiz | N72: =VLOOKUP(B72,Customer_Cleaned!$A$2:$H$501,3,FALSE) -> 28 | O72: =VLOOKUP(B72,Customer_Cleaned!$A$2:$H$501,4,FALSE) -> Female | P72: =VLOOKUP(B72,Customer_Cleaned!$A$2:$H$501,8,FALSE) -> Bronze | Q72: =_xlfn.XLOOKUP('Sales_Fact cleaned'!B3,Customer_Cleaned!$A$2:$A$501,Customer_Cleaned!$F$2:$F$501) -> Wisconsin | R72: =_xlfn.XLOOKUP(B72,Customer_Cleaned!$A$2:$A$501,Customer_Cleaned!$G$2:$G$501) -> USA | S72: 4 | T72: 23.57 | U72: 0.1 | V72: 84.852 | W72: COD
A73: 45240 | B73: CUST1420 | C73: PROD15 | D73: =VLOOKUP(C73,Product_Cleaned!$A$2:$B$101,2,FALSE) -> 4K Home Projector | E73: =VLOOKUP(C73,Product_Cleaned!$A$2:$C$101,3,FALSE) -> Electronics | F73: =VLOOKUP(C73,Product_Cleaned!$A$2:$E$101,4,FALSE) -> Appliances | G73: =VLOOKUP('Sales_Fact cleaned'!C796,Product_Cleaned!$A$2:$E$101,5, FALSE) -> Khan, Jones and Paul | H73: STORE1 | I73: =_xlfn.XLOOKUP(H73,Store_Raw!$A$2:$A$21,Store_Raw!$B$2:$B$21) -> Martinez, Adkins and Johnson | J73: =_xlfn.XLOOKUP(H73,Store_Raw!$A$2:$A$21,Store_Raw!$C$2:$C$21) -> North | K73: =_xlfn.XLOOKUP(H73,Store_Raw!$A$2:$A$21,Store_Raw!$D$2:$D$21) -> Danielmouth | L73: =_xlfn.XLOOKUP(H73,Store_Raw!$A$2:$A$21,Store_Raw!$E$2:$E$21) -> Flagship | M73: =VLOOKUP(B73,Customer_Cleaned!$A$2:$H$501,2,FALSE) -> Dr. Tamara White Md | N73: =VLOOKUP(B73,Customer_Cleaned!$A$2:$H$501,3,FALSE) -> 60 | O73: =VLOOKUP(B73,Customer_Cleaned!$A$2:$H$501,4,FALSE) -> Male | P73: =VLOOKUP(B73,Customer_Cleaned!$A$2:$H$501,8,FALSE) -> Platinum | Q73: =_xlfn.XLOOKUP('Sales_Fact cleaned'!B796,Customer_Cleaned!$A$2:$A$501,Customer_Cleaned!$F$2:$F$501) -> Nevada | R73: =_xlfn.XLOOKUP(B73,Customer_Cleaned!$A$2:$A$501,Customer_Cleaned!$G$2:$G$501) -> USA | S73: 1 | T73: 86.03 | U73: 0.01 | V73: 85.1697 | W73: PayPal
A74: 45240 | B74: CUST1134 | C74: PROD83 | D74: =VLOOKUP(C74,Product_Cleaned!$A$2:$B$101,2,FALSE) -> Hydrating Face Cleanser | E74: =VLOOKUP(C74,Product_Cleaned!$A$2:$C$101,3,FALSE) -> Beauty | F74: =VLOOKUP(C74,Product_Cleaned!$A$2:$E$101,4,FALSE) -> Skincare | G74: =VLOOKUP('Sales_Fact cleaned'!C500,Product_Cleaned!$A$2:$E$101,5, FALSE) -> Khan LLC | H74: STORE3 | I74: =_xlfn.XLOOKUP(H74,Store_Raw!$A$2:$A$21,Store_Raw!$B$2:$B$21) -> Johnson-Wright | J74: =_xlfn.XLOOKUP(H74,Store_Raw!$A$2:$A$21,Store_Raw!$C$2:$C$21) -> North | K74: =_xlfn.XLOOKUP(H74,Store_Raw!$A$2:$A$21,Store_Raw!$D$2:$D$21) -> Hoodberg | L74: =_xlfn.XLOOKUP(H74,Store_Raw!$A$2:$A$21,Store_Raw!$E$2:$E$21) -> Outlet | M74: =VLOOKUP(B74,Customer_Cleaned!$A$2:$H$501,2,FALSE) -> Morgan Bowen | N74: =VLOOKUP(B74,Customer_Cleaned!$A$2:$H$501,3,FALSE) -> 54 | O74: =VLOOKUP(B74,Customer_Cleaned!$A$2:$H$501,4,FALSE) -> Male | P74: =VLOOKUP(B74,Customer_Cleaned!$A$2:$H$501,8,FALSE) -> Platinum | Q74: =_xlfn.XLOOKUP('Sales_Fact cleaned'!B500,Customer_Cleaned!$A$2:$A$501,Customer_Cleaned!$F$2:$F$501) -> Illinois | R74: =_xlfn.XLOOKUP(B74,Customer_Cleaned!$A$2:$A$501,Customer_Cleaned!$G$2:$G$501) -> USA | S74: 1 | T74: 113.07 | U74: 0.24 | V74: 85.9332 | W74: Credit Card
A75: 45241 | B75: CUST1069 | C75: PROD31 | D75: =VLOOKUP(C75,Product_Cleaned!$A$2:$B$101,2,FALSE) -> Basketball | E75: =VLOOKUP(C75,Product_Cleaned!$A$2:$C$101,3,FALSE) -> Sports | F75: =VLOOKUP(C75,Product_Cleaned!$A$2:$E$101,4,FALSE) -> Team Sports | G75: =VLOOKUP('Sales_Fact cleaned'!C1349,Product_Cleaned!$A$2:$E$101,5, FALSE) -> Cook Ltd | H75: STORE18 | I75: =_xlfn.XLOOKUP(H75,Store_Raw!$A$2:$A$21,Store_Raw!$B$2:$B$21) -> Guerrero-Schmitt | J75: =_xlfn.XLOOKUP(H75,Store_Raw!$A$2:$A$21,Store_Raw!$C$2:$C$21) -> East | K75: =_xlfn.XLOOKUP(H75,Store_Raw!$A$2:$A$21,Store_Raw!$D$2:$D$21) -> East Stevechester | L75: =_xlfn.XLOOKUP(H75,Store_Raw!$A$2:$A$21,Store_Raw!$E$2:$E$21) -> Flagship | M75: =VLOOKUP(B75,Customer_Cleaned!$A$2:$H$501,2,FALSE) -> Roy Cole | N75: =VLOOKUP(B75,Customer_Cleaned!$A$2:$H$501,3,FALSE) -> 24 | O75: =VLOOKUP(B75,Customer_Cleaned!$A$2:$H$501,4,FALSE) -> Female | P75: =VLOOKUP(B75,Customer_Cleaned!$A$2:$H$501,8,FALSE) -> Bronze | Q75: =_xlfn.XLOOKUP('Sales_Fact cleaned'!B1349,Customer_Cleaned!$A$2:$A$501,Customer_Cleaned!$F$2:$F$501) -> Utah | R75: =_xlfn.XLOOKUP(B75,Customer_Cleaned!$A$2:$A$501,Customer_Cleaned!$G$2:$G$501) -> USA | S75: 2 | T75: 46.39 | U75: 0.07 | V75: 86.2854 | W75: PayPal
A76: 45241 | B76: CUST1173 | C76: PROD14 | D76: =VLOOKUP(C76,Product_Cleaned!$A$2:$B$101,2,FALSE) -> Decorative Wall Mirror | E76: =VLOOKUP(C76,Product_Cleaned!$A$2:$C$101,3,FALSE) -> Home | F76: =VLOOKUP(C76,Product_Cleaned!$A$2:$E$101,4,FALSE) -> Decor | G76: =VLOOKUP('Sales_Fact cleaned'!C772,Product_Cleaned!$A$2:$E$101,5, FALSE) -> Bruce-Bowen | H76: STORE7 | I76: =_xlfn.XLOOKUP(H76,Store_Raw!$A$2:$A$21,Store_Raw!$B$2:$B$21) -> Martinez-Mullins | J76: =_xlfn.XLOOKUP(H76,Store_Raw!$A$2:$A$21,Store_Raw!$C$2:$C$21) -> South | K76: =_xlfn.XLOOKUP(H76,Store_Raw!$A$2:$A$21,Store_Raw!$D$2:$D$21) -> Williamsfurt | L76: =_xlfn.XLOOKUP(H76,Store_Raw!$A$2:$A$21,Store_Raw!$E$2:$E$21) -> Online | M76: =VLOOKUP(B76,Customer_Cleaned!$A$2:$H$501,2,FALSE) -> Teresa Stokes | N76: =VLOOKUP(B76,Customer_Cleaned!$A$2:$H$501,3,FALSE) -> 41 | O76: =VLOOKUP(B76,Customer_Cleaned!$A$2:$H$501,4,FALSE) -> Female | P76: =VLOOKUP(B76,Customer_Cleaned!$A$2:$H$501,8,FALSE) -> Silver | Q76: =_xlfn.XLOOKUP('Sales_Fact cleaned'!B772,Customer_Cleaned!$A$2:$A$501,Customer_Cleaned!$F$2:$F$501) -> Georgia | R76: =_xlfn.XLOOKUP(B76,Customer_Cleaned!$A$2:$A$501,Customer_Cleaned!$G$2:$G$501) -> usa | S76: 2 | T76: 44.65 | U76: 0.03 | V76: 86.621 | W76: COD
A77: 45241 | B77: CUST1449 | C77: PROD57 | D77: =VLOOKUP(C77,Product_Cleaned!$A$2:$B$101,2,FALSE) -> Foam Roller | E77: =VLOOKUP(C77,Product_Cleaned!$A$2:$C$101,3,FALSE) -> Sports | F77: =VLOOKUP(C77,Product_Cleaned!$A$2:$E$101,4,FALSE) -> Fitness | G77: =VLOOKUP('Sales_Fact cleaned'!C1858,Product_Cleaned!$A$2:$E$101,5, FALSE) -> Cummings and Sons | H77: STORE19 | I77: =_xlfn.XLOOKUP(H77,Store_Raw!$A$2:$A$21,Store_Raw!$B$2:$B$21) -> Mann-Austin | J77: =_xlfn.XLOOKUP(H77,Store_Raw!$A$2:$A$21,Store_Raw!$C$2:$C$21) -> East | K77: =_xlfn.XLOOKUP(H77,Store_Raw!$A$2:$A$21,Store_Raw!$D$2:$D$21) -> Vasquezborough | L77: =_xlfn.XLOOKUP(H77,Store_Raw!$A$2:$A$21,Store_Raw!$E$2:$E$21) -> Online | M77: =VLOOKUP(B77,Customer_Cleaned!$A$2:$H$501,2,FALSE) -> William Cortez | N77: =VLOOKUP(B77,Customer_Cleaned!$A$2:$H$501,3,FALSE) -> 29 | O77: =VLOOKUP(B77,Customer_Cleaned!$A$2:$H$501,4,FALSE) -> Male | P77: =VLOOKUP(B77,Customer_Cleaned!$A$2:$H$501,8,FALSE) -> Bronze | Q77: =_xlfn.XLOOKUP('Sales_Fact cleaned'!B1858,Customer_Cleaned!$A$2:$A$501,Customer_Cleaned!$F$2:$F$501) -> Florida | R77: =_xlfn.XLOOKUP(B77,Customer_Cleaned!$A$2:$A$501,Customer_Cleaned!$G$2:$G$501) -> USA | S77: 1 | T77: 120.02 | U77: 0.26 | V77: 88.8148 | W77: COD
A78: 45242 | B78: CUST1335 | C78: PROD89 | D78: =VLOOKUP(C78,Product_Cleaned!$A$2:$B$101,2,FALSE) -> Face Foundation Kit | E78: =VLOOKUP(C78,Product_Cleaned!$A$2:$C$101,3,FALSE) -> Beauty | F78: =VLOOKUP(C78,Product_Cleaned!$A$2:$E$101,4,FALSE) -> Makeup | G78: =VLOOKUP('Sales_Fact cleaned'!C73,Product_Cleaned!$A$2:$E$101,5, FALSE) -> Thomas LLC | H78: STORE1 | I78: =_xlfn.XLOOKUP(H78,Store_Raw!$A$2:$A$21,Store_Raw!$B$2:$B$21) -> Martinez, Adkins and Johnson | J78: =_xlfn.XLOOKUP(H78,Store_Raw!$A$2:$A$21,Store_Raw!$C$2:$C$21) -> North | K78: =_xlfn.XLOOKUP(H78,Store_Raw!$A$2:$A$21,Store_Raw!$D$2:$D$21) -> Danielmouth | L78: =_xlfn.XLOOKUP(H78,Store_Raw!$A$2:$A$21,Store_Raw!$E$2:$E$21) -> Flagship | M78: =VLOOKUP(B78,Customer_Cleaned!$A$2:$H$501,2,FALSE) -> Jennifer Woods | N78: =VLOOKUP(B78,Customer_Cleaned!$A$2:$H$501,3,FALSE) -> 37 | O78: =VLOOKUP(B78,Customer_Cleaned!$A$2:$H$501,4,FALSE) -> Male | P78: =VLOOKUP(B78,Customer_Cleaned!$A$2:$H$501,8,FALSE) -> Silver | Q78: =_xlfn.XLOOKUP('Sales_Fact cleaned'!B73,Customer_Cleaned!$A$2:$A$501,Customer_Cleaned!$F$2:$F$501) -> North Carolina | R78: =_xlfn.XLOOKUP(B78,Customer_Cleaned!$A$2:$A$501,Customer_Cleaned!$G$2:$G$501) -> USA | S78: 1 | T78: 122.27 | U78: 0.26 | V78: 90.4798 | W78: COD
A79: 45242 | B79: CUST1266 | C79: PROD20 | D79: =VLOOKUP(C79,Product_Cleaned!$A$2:$B$101,2,FALSE) -> Outdoor Sports Water Bottle | E79: =VLOOKUP(C79,Product_Cleaned!$A$2:$C$101,3,FALSE) -> Sports | F79: =VLOOKUP(C79,Product_Cleaned!$A$2:$E$101,4,FALSE) -> Accessories | G79: =VLOOKUP('Sales_Fact cleaned'!C1315,Product_Cleaned!$A$2:$E$101,5, FALSE) -> Sims Inc | H79: STORE12 | I79: =_xlfn.XLOOKUP(H79,Store_Raw!$A$2:$A$21,Store_Raw!$B$2:$B$21) -> Thomas, Bridges and Harris | J79: =_xlfn.XLOOKUP(H79,Store_Raw!$A$2:$A$21,Store_Raw!$C$2:$C$21) -> North | K79: =_xlfn.XLOOKUP(H79,Store_Raw!$A$2:$A$21,Store_Raw!$D$2:$D$21) -> Sabrinatown | L79: =_xlfn.XLOOKUP(H79,Store_Raw!$A$2:$A$21,Store_Raw!$E$2:$E$21) -> Online | M79: =VLOOKUP(B79,Customer_Cleaned!$A$2:$H$501,2,FALSE) -> Cynthia Payne | N79: =VLOOKUP(B79,Customer_Cleaned!$A$2:$H$501,3,FALSE) -> 32 | O79: =VLOOKUP(B79,Customer_Cleaned!$A$2:$H$501,4,FALSE) -> Female | P79: =VLOOKUP(B79,Customer_Cleaned!$A$2:$H$501,8,FALSE) -> Bronze | Q79: =_xlfn.XLOOKUP('Sales_Fact cleaned'!B1315,Customer_Cleaned!$A$2:$A$501,Customer_Cleaned!$F$2:$F$501) -> New Hampshire | R79: =_xlfn.XLOOKUP(B79,Customer_Cleaned!$A$2:$A$501,Customer_Cleaned!$G$2:$G$501) -> USA | S79: 1 | T79: 99.35 | U79: 0.08 | V79: 91.402 | W79: COD
A80: 45243 | B80: CUST1255 | C80: PROD92 | D80: =VLOOKUP(C80,Product_Cleaned!$A$2:$B$101,2,FALSE) -> Microwave Oven | E80: =VLOOKUP(C80,Product_Cleaned!$A$2:$C$101,3,FALSE) -> Home | F80: =VLOOKUP(C80,Product_Cleaned!$A$2:$E$101,4,FALSE) -> Appliances | G80: =VLOOKUP('Sales_Fact cleaned'!C529,Product_Cleaned!$A$2:$E$101,5, FALSE) -> Holmes LLC | H80: STORE6 | I80: =_xlfn.XLOOKUP(H80,Store_Raw!$A$2:$A$21,Store_Raw!$B$2:$B$21) -> Benson-Elliott | J80: =_xlfn.XLOOKUP(H80,Store_Raw!$A$2:$A$21,Store_Raw!$C$2:$C$21) -> East | K80: =_xlfn.XLOOKUP(H80,Store_Raw!$A$2:$A$21,Store_Raw!$D$2:$D$21) -> Port Josephberg | L80: =_xlfn.XLOOKUP(H80,Store_Raw!$A$2:$A$21,Store_Raw!$E$2:$E$21) -> Online | M80: =VLOOKUP(B80,Customer_Cleaned!$A$2:$H$501,2,FALSE) -> Damon Perez | N80: =VLOOKUP(B80,Customer_Cleaned!$A$2:$H$501,3,FALSE) -> 21 | O80: =VLOOKUP(B80,Customer_Cleaned!$A$2:$H$501,4,FALSE) -> Male | P80: =VLOOKUP(B80,Customer_Cleaned!$A$2:$H$501,8,FALSE) -> Bronze | Q80: =_xlfn.XLOOKUP('Sales_Fact cleaned'!B529,Customer_Cleaned!$A$2:$A$501,Customer_Cleaned!$F$2:$F$501) -> Kansas | R80: =_xlfn.XLOOKUP(B80,Customer_Cleaned!$A$2:$A$501,Customer_Cleaned!$G$2:$G$501) -> USA | S80: 1 | T80: 117.37 | U80: 0.21 | V80: 92.7223 | W80: PayPal
A81: 45243 | B81: CUST1483 | C81: PROD30 | D81: =VLOOKUP(C81,Product_Cleaned!$A$2:$B$101,2,FALSE) -> Stainless Steel Cutlery Set | E81: =VLOOKUP(C81,Product_Cleaned!$A$2:$C$101,3,FALSE) -> Home | F81: =VLOOKUP(C81,Product_Cleaned!$A$2:$E$101,4,FALSE) -> Kitchen | G81: =VLOOKUP('Sales_Fact cleaned'!C1664,Product_Cleaned!$A$2:$E$101,5, FALSE) -> Cummings and Sons | H81: STORE10 | I81: =_xlfn.XLOOKUP(H81,Store_Raw!$A$2:$A$21,Store_Raw!$B$2:$B$21) -> Hill, Wagner and Ballard | J81: =_xlfn.XLOOKUP(H81,Store_Raw!$A$2:$A$21,Store_Raw!$C$2:$C$21) -> East | K81: =_xlfn.XLOOKUP(H81,Store_Raw!$A$2:$A$21,Store_Raw!$D$2:$D$21) -> East Davidville | L81: =_xlfn.XLOOKUP(H81,Store_Raw!$A$2:$A$21,Store_Raw!$E$2:$E$21) -> Online | M81: =VLOOKUP(B81,Customer_Cleaned!$A$2:$H$501,2,FALSE) -> Sarah Smith | N81: =VLOOKUP(B81,Customer_Cleaned!$A$2:$H$501,3,FALSE) -> 48 | O81: =VLOOKUP(B81,Customer_Cleaned!$A$2:$H$501,4,FALSE) -> Male | P81: =VLOOKUP(B81,Customer_Cleaned!$A$2:$H$501,8,FALSE) -> Silver | Q81: =_xlfn.XLOOKUP('Sales_Fact cleaned'!B1664,Customer_Cleaned!$A$2:$A$501,Customer_Cleaned!$F$2:$F$501) -> Vermont | R81: =_xlfn.XLOOKUP(B81,Customer_Cleaned!$A$2:$A$501,Customer_Cleaned!$G$2:$G$501) -> USA | S81: 2 | T81: 47.86 | U81: 0.03 | V81: 92.8484 | W81: Credit Card
A82: 45243 | B82: CUST1059 | C82: PROD70 | D82: =VLOOKUP(C82,Product_Cleaned!$A$2:$B$101,2,FALSE) -> Kitchen Storage Rack | E82: =VLOOKUP(C82,Product_Cleaned!$A$2:$C$101,3,FALSE) -> Home | F82: =VLOOKUP(C82,Product_Cleaned!$A$2:$E$101,4,FALSE) -> Storage | G82: =VLOOKUP('Sales_Fact cleaned'!C161,Product_Cleaned!$A$2:$E$101,5, FALSE) -> May-Reese | H82: STORE14 | I82: =_xlfn.XLOOKUP(H82,Store_Raw!$A$2:$A$21,Store_Raw!$B$2:$B$21) -> Mcdonald Inc | J82: =_xlfn.XLOOKUP(H82,Store_Raw!$A$2:$A$21,Store_Raw!$C$2:$C$21) -> South | K82: =_xlfn.XLOOKUP(H82,Store_Raw!$A$2:$A$21,Store_Raw!$D$2:$D$21) -> Christopherland | L82: =_xlfn.XLOOKUP(H82,Store_Raw!$A$2:$A$21,Store_Raw!$E$2:$E$21) -> Outlet | M82: =VLOOKUP(B82,Customer_Cleaned!$A$2:$H$501,2,FALSE) -> Alyssa Vargas | N82: =VLOOKUP(B82,Customer_Cleaned!$A$2:$H$501,3,FALSE) -> 53 | O82: =VLOOKUP(B82,Customer_Cleaned!$A$2:$H$501,4,FALSE) -> Male | P82: =VLOOKUP(B82,Customer_Cleaned!$A$2:$H$501,8,FALSE) -> Platinum | Q82: =_xlfn.XLOOKUP('Sales_Fact cleaned'!B161,Customer_Cleaned!$A$2:$A$501,Customer_Cleaned!$F$2:$F$501) -> New York | R82: =_xlfn.XLOOKUP(B82,Customer_Cleaned!$A$2:$A$501,Customer_Cleaned!$G$2:$G$501) -> USA | S82: 2 | T82: 47.3 | U82: 0.01 | V82: 93.654 | W82: PayPal
A83: 45244 | B83: CUST1067 | C83: PROD41 | D83: =VLOOKUP(C83,Product_Cleaned!$A$2:$B$101,2,FALSE) -> Yoga Exercise Mat | E83: =VLOOKUP(C83,Product_Cleaned!$A$2:$C$101,3,FALSE) -> Sports | F83: =VLOOKUP(C83,Product_Cleaned!$A$2:$E$101,4,FALSE) -> Fitness | G83: =VLOOKUP('Sales_Fact cleaned'!C800,Product_Cleaned!$A$2:$E$101,5, FALSE) -> Collins-Stephenson | H83: STORE19 | I83: =_xlfn.XLOOKUP(H83,Store_Raw!$A$2:$A$21,Store_Raw!$B$2:$B$21) -> Mann-Austin | J83: =_xlfn.XLOOKUP(H83,Store_Raw!$A$2:$A$21,Store_Raw!$C$2:$C$21) -> East | K83: =_xlfn.XLOOKUP(H83,Store_Raw!$A$2:$A$21,Store_Raw!$D$2:$D$21) -> Vasquezborough | L83: =_xlfn.XLOOKUP(H83,Store_Raw!$A$2:$A$21,Store_Raw!$E$2:$E$21) -> Online | M83: =VLOOKUP(B83,Customer_Cleaned!$A$2:$H$501,2,FALSE) -> Amber Mcclain | N83: =VLOOKUP(B83,Customer_Cleaned!$A$2:$H$501,3,FALSE) -> 58 | O83: =VLOOKUP(B83,Customer_Cleaned!$A$2:$H$501,4,FALSE) -> Male | P83: =VLOOKUP(B83,Customer_Cleaned!$A$2:$H$501,8,FALSE) -> Platinum | Q83: =_xlfn.XLOOKUP('Sales_Fact cleaned'!B800,Customer_Cleaned!$A$2:$A$501,Customer_Cleaned!$F$2:$F$501) -> Alabama | R83: =_xlfn.XLOOKUP(B83,Customer_Cleaned!$A$2:$A$501,Customer_Cleaned!$G$2:$G$501) -> USA | S83: 2 | T83: 56.52 | U83: 0.17 | V83: 93.8232 | W83: COD
A84: 45244 | B84: CUST1369 | C84: PROD28 | D84: =VLOOKUP(C84,Product_Cleaned!$A$2:$B$101,2,FALSE) -> Sports Stopwatch Timer | E84: =VLOOKUP(C84,Product_Cleaned!$A$2:$C$101,3,FALSE) -> Sports | F84: =VLOOKUP(C84,Product_Cleaned!$A$2:$E$101,4,FALSE) -> Accessories | G84: =VLOOKUP('Sales_Fact cleaned'!C1065,Product_Cleaned!$A$2:$E$101,5, FALSE) -> Sharp, Taylor and Rodriguez | H84: STORE11 | I84: =_xlfn.XLOOKUP(H84,Store_Raw!$A$2:$A$21,Store_Raw!$B$2:$B$21) -> Aguirre-Keller | J84: =_xlfn.XLOOKUP(H84,Store_Raw!$A$2:$A$21,Store_Raw!$C$2:$C$21) -> South | K84: =_xlfn.XLOOKUP(H84,Store_Raw!$A$2:$A$21,Store_Raw!$D$2:$D$21) -> Lake Michael | L84: =_xlfn.XLOOKUP(H84,Store_Raw!$A$2:$A$21,Store_Raw!$E$2:$E$21) -> Online | M84: =VLOOKUP(B84,Customer_Cleaned!$A$2:$H$501,2,FALSE) -> Gregory Allen | N84: =VLOOKUP(B84,Customer_Cleaned!$A$2:$H$501,3,FALSE) -> 20 | O84: =VLOOKUP(B84,Customer_Cleaned!$A$2:$H$501,4,FALSE) -> Female | P84: =VLOOKUP(B84,Customer_Cleaned!$A$2:$H$501,8,FALSE) -> Bronze | Q84: =_xlfn.XLOOKUP('Sales_Fact cleaned'!B1065,Customer_Cleaned!$A$2:$A$501,Customer_Cleaned!$F$2:$F$501) -> Indiana | R84: =_xlfn.XLOOKUP(B84,Customer_Cleaned!$A$2:$A$501,Customer_Cleaned!$G$2:$G$501) -> USA | S84: 2 | T84: 60.98 | U84: 0.23 | V84: 93.9092 | W84: PayPal
A85: 45244 | B85: CUST1371 | C85: PROD95 | D85: =VLOOKUP(C85,Product_Cleaned!$A$2:$B$101,2,FALSE) -> Sports Stopwatch Basic | E85: =VLOOKUP(C85,Product_Cleaned!$A$2:$C$101,3,FALSE) -> Sports | F85: =VLOOKUP(C85,Product_Cleaned!$A$2:$E$101,4,FALSE) -> Accessories | G85: =VLOOKUP('Sales_Fact cleaned'!C778,Product_Cleaned!$A$2:$E$101,5, FALSE) -> Bruce-Bowen | H85: STORE1 | I85: =_xlfn.XLOOKUP(H85,Store_Raw!$A$2:$A$21,Store_Raw!$B$2:$B$21) -> Martinez, Adkins and Johnson | J85: =_xlfn.XLOOKUP(H85,Store_Raw!$A$2:$A$21,Store_Raw!$C$2:$C$21) -> North | K85: =_xlfn.XLOOKUP(H85,Store_Raw!$A$2:$A$21,Store_Raw!$D$2:$D$21) -> Danielmouth | L85: =_xlfn.XLOOKUP(H85,Store_Raw!$A$2:$A$21,Store_Raw!$E$2:$E$21) -> Flagship | M85: =VLOOKUP(B85,Customer_Cleaned!$A$2:$H$501,2,FALSE) -> Michael Garner | N85: =VLOOKUP(B85,Customer_Cleaned!$A$2:$H$501,3,FALSE) -> 21 | O85: =VLOOKUP(B85,Customer_Cleaned!$A$2:$H$501,4,FALSE) -> Female | P85: =VLOOKUP(B85,Customer_Cleaned!$A$2:$H$501,8,FALSE) -> Bronze | Q85: =_xlfn.XLOOKUP('Sales_Fact cleaned'!B778,Customer_Cleaned!$A$2:$A$501,Customer_Cleaned!$F$2:$F$501) -> Michigan | R85: =_xlfn.XLOOKUP(B85,Customer_Cleaned!$A$2:$A$501,Customer_Cleaned!$G$2:$G$501) -> USA | S85: 1 | T85: 128.93 | U85: 0.26 | V85: 95.4082 | W85: Credit Card
A86: 45244 | B86: CUST1087 | C86: PROD8 | D86: =VLOOKUP(C86,Product_Cleaned!$A$2:$B$101,2,FALSE) -> Wireless Bluetooth Earbuds | E86: =VLOOKUP(C86,Product_Cleaned!$A$2:$C$101,3,FALSE) -> Electronics | F86: =VLOOKUP(C86,Product_Cleaned!$A$2:$E$101,4,FALSE) -> Audio | G86: =VLOOKUP('Sales_Fact cleaned'!C1942,Product_Cleaned!$A$2:$E$101,5, FALSE) -> Harrell LLC | H86: STORE9 | I86: =_xlfn.XLOOKUP(H86,Store_Raw!$A$2:$A$21,Store_Raw!$B$2:$B$21) -> Moore, Padilla and Butler | J86: =_xlfn.XLOOKUP(H86,Store_Raw!$A$2:$A$21,Store_Raw!$C$2:$C$21) -> South | K86: =_xlfn.XLOOKUP(H86,Store_Raw!$A$2:$A$21,Store_Raw!$D$2:$D$21) -> East Johnstad | L86: =_xlfn.XLOOKUP(H86,Store_Raw!$A$2:$A$21,Store_Raw!$E$2:$E$21) -> Flagship | M86: =VLOOKUP(B86,Customer_Cleaned!$A$2:$H$501,2,FALSE) -> Melissa Duffy Md | N86: =VLOOKUP(B86,Customer_Cleaned!$A$2:$H$501,3,FALSE) -> 58 | O86: =VLOOKUP(B86,Customer_Cleaned!$A$2:$H$501,4,FALSE) -> Female | P86: =VLOOKUP(B86,Customer_Cleaned!$A$2:$H$501,8,FALSE) -> Platinum | Q86: =_xlfn.XLOOKUP('Sales_Fact cleaned'!B1942,Customer_Cleaned!$A$2:$A$501,Customer_Cleaned!$F$2:$F$501) -> Louisiana | R86: =_xlfn.XLOOKUP(B86,Customer_Cleaned!$A$2:$A$501,Customer_Cleaned!$G$2:$G$501) -> USA | S86: 1 | T86: 125 | U86: 0.23 | V86: 96.25 | W86: Credit Card
A87: 45247 | B87: CUST1119 | C87: PROD66 | D87: =VLOOKUP(C87,Product_Cleaned!$A$2:$B$101,2,FALSE) -> Women's Hair Dryer Brush | E87: =VLOOKUP(C87,Product_Cleaned!$A$2:$C$101,3,FALSE) -> Beauty | F87: =VLOOKUP(C87,Product_Cleaned!$A$2:$E$101,4,FALSE) -> Haircare | G87: =VLOOKUP('Sales_Fact cleaned'!C1897,Product_Cleaned!$A$2:$E$101,5, FALSE) -> Sims Inc | H87: STORE6 | I87: =_xlfn.XLOOKUP(H87,Store_Raw!$A$2:$A$21,Store_Raw!$B$2:$B$21) -> Benson-Elliott | J87: =_xlfn.XLOOKUP(H87,Store_Raw!$A$2:$A$21,Store_Raw!$C$2:$C$21) -> East | K87: =_xlfn.XLOOKUP(H87,Store_Raw!$A$2:$A$21,Store_Raw!$D$2:$D$21) -> Port Josephberg | L87: =_xlfn.XLOOKUP(H87,Store_Raw!$A$2:$A$21,Store_Raw!$E$2:$E$21) -> Online | M87: =VLOOKUP(B87,Customer_Cleaned!$A$2:$H$501,2,FALSE) -> Michael Jones | N87: =VLOOKUP(B87,Customer_Cleaned!$A$2:$H$501,3,FALSE) -> 40 | O87: =VLOOKUP(B87,Customer_Cleaned!$A$2:$H$501,4,FALSE) -> Male | P87: =VLOOKUP(B87,Customer_Cleaned!$A$2:$H$501,8,FALSE) -> Silver | Q87: =_xlfn.XLOOKUP('Sales_Fact cleaned'!B1897,Customer_Cleaned!$A$2:$A$501,Customer_Cleaned!$F$2:$F$501) -> Montana | R87: =_xlfn.XLOOKUP(B87,Customer_Cleaned!$A$2:$A$501,Customer_Cleaned!$G$2:$G$501) -> USA | S87: 1 | T87: 126.92 | U87: 0.24 | V87: 96.4592 | W87: COD
A88: 45248 | B88: CUST1399 | C88: PROD77 | D88: =VLOOKUP(C88,Product_Cleaned!$A$2:$B$101,2,FALSE) -> WiFi Mesh Router | E88: =VLOOKUP(C88,Product_Cleaned!$A$2:$C$101,3,FALSE) -> Electronics | F88: =VLOOKUP(C88,Product_Cleaned!$A$2:$E$101,4,FALSE) -> Appliances | G88: =VLOOKUP('Sales_Fact cleaned'!C513,Product_Cleaned!$A$2:$E$101,5, FALSE) -> Lucero LLC | H88: STORE18 | I88: =_xlfn.XLOOKUP(H88,Store_Raw!$A$2:$A$21,Store_Raw!$B$2:$B$21) -> Guerrero-Schmitt | J88: =_xlfn.XLOOKUP(H88,Store_Raw!$A$2:$A$21,Store_Raw!$C$2:$C$21) -> East | K88: =_xlfn.XLOOKUP(H88,Store_Raw!$A$2:$A$21,Store_Raw!$D$2:$D$21) -> East Stevechester | L88: =_xlfn.XLOOKUP(H88,Store_Raw!$A$2:$A$21,Store_Raw!$E$2:$E$21) -> Flagship | M88: =VLOOKUP(B88,Customer_Cleaned!$A$2:$H$501,2,FALSE) -> John Donaldson | N88: =VLOOKUP(B88,Customer_Cleaned!$A$2:$H$501,3,FALSE) -> 27 | O88: =VLOOKUP(B88,Customer_Cleaned!$A$2:$H$501,4,FALSE) -> Male | P88: =VLOOKUP(B88,Customer_Cleaned!$A$2:$H$501,8,FALSE) -> Bronze | Q88: =_xlfn.XLOOKUP('Sales_Fact cleaned'!B513,Customer_Cleaned!$A$2:$A$501,Customer_Cleaned!$F$2:$F$501) -> Texas | R88: =_xlfn.XLOOKUP(B88,Customer_Cleaned!$A$2:$A$501,Customer_Cleaned!$G$2:$G$501) -> USA | S88: 2 | T88: 68.31 | U88: 0.29 | V88: 97.0002 | W88: PayPal
A89: 45248 | B89: CUST1047 | C89: PROD70 | D89: =VLOOKUP(C89,Product_Cleaned!$A$2:$B$101,2,FALSE) -> Kitchen Storage Rack | E89: =VLOOKUP(C89,Product_Cleaned!$A$2:$C$101,3,FALSE) -> Home | F89: =VLOOKUP(C89,Product_Cleaned!$A$2:$E$101,4,FALSE) -> Storage | G89: =VLOOKUP('Sales_Fact cleaned'!C1656,Product_Cleaned!$A$2:$E$101,5, FALSE) -> Hogan-Lee | H89: STORE14 | I89: =_xlfn.XLOOKUP(H89,Store_Raw!$A$2:$A$21,Store_Raw!$B$2:$B$21) -> Mcdonald Inc | J89: =_xlfn.XLOOKUP(H89,Store_Raw!$A$2:$A$21,Store_Raw!$C$2:$C$21) -> South | K89: =_xlfn.XLOOKUP(H89,Store_Raw!$A$2:$A$21,Store_Raw!$D$2:$D$21) -> Christopherland | L89: =_xlfn.XLOOKUP(H89,Store_Raw!$A$2:$A$21,Store_Raw!$E$2:$E$21) -> Outlet | M89: =VLOOKUP(B89,Customer_Cleaned!$A$2:$H$501,2,FALSE) -> Gina Knight | N89: =VLOOKUP(B89,Customer_Cleaned!$A$2:$H$501,3,FALSE) -> 54 | O89: =VLOOKUP(B89,Customer_Cleaned!$A$2:$H$501,4,FALSE) -> Female | P89: =VLOOKUP(B89,Customer_Cleaned!$A$2:$H$501,8,FALSE) -> Platinum | Q89: =_xlfn.XLOOKUP('Sales_Fact cleaned'!B1656,Customer_Cleaned!$A$2:$A$501,Customer_Cleaned!$F$2:$F$501) -> Missouri | R89: =_xlfn.XLOOKUP(B89,Customer_Cleaned!$A$2:$A$501,Customer_Cleaned!$G$2:$G$501) -> USA | S89: 1 | T89: 108.27 | U89: 0.1 | V89: 97.443 | W89: PayPal
A90: 45249 | B90: CUST1255 | C90: PROD79 | D90: =VLOOKUP(C90,Product_Cleaned!$A$2:$B$101,2,FALSE) -> Decorative Lamp Shade | E90: =VLOOKUP(C90,Product_Cleaned!$A$2:$C$101,3,FALSE) -> Home | F90: =VLOOKUP(C90,Product_Cleaned!$A$2:$E$101,4,FALSE) -> Lighting | G90: =VLOOKUP('Sales_Fact cleaned'!C1021,Product_Cleaned!$A$2:$E$101,5, FALSE) -> Wilson Group | H90: STORE19 | I90: =_xlfn.XLOOKUP(H90,Store_Raw!$A$2:$A$21,Store_Raw!$B$2:$B$21) -> Mann-Austin | J90: =_xlfn.XLOOKUP(H90,Store_Raw!$A$2:$A$21,Store_Raw!$C$2:$C$21) -> East | K90: =_xlfn.XLOOKUP(H90,Store_Raw!$A$2:$A$21,Store_Raw!$D$2:$D$21) -> Vasquezborough | L90: =_xlfn.XLOOKUP(H90,Store_Raw!$A$2:$A$21,Store_Raw!$E$2:$E$21) -> Online | M90: =VLOOKUP(B90,Customer_Cleaned!$A$2:$H$501,2,FALSE) -> Damon Perez | N90: =VLOOKUP(B90,Customer_Cleaned!$A$2:$H$501,3,FALSE) -> 21 | O90: =VLOOKUP(B90,Customer_Cleaned!$A$2:$H$501,4,FALSE) -> Male | P90: =VLOOKUP(B90,Customer_Cleaned!$A$2:$H$501,8,FALSE) -> Bronze | Q90: =_xlfn.XLOOKUP('Sales_Fact cleaned'!B1021,Customer_Cleaned!$A$2:$A$501,Customer_Cleaned!$F$2:$F$501) -> Virginia | R90: =_xlfn.XLOOKUP(B90,Customer_Cleaned!$A$2:$A$501,Customer_Cleaned!$G$2:$G$501) -> USA | S90: 2 | T90: 60.53 | U90: 0.18 | V90: 99.2692 | W90: Credit Card
A91: 45249 | B91: CUST1248 | C91: PROD34 | D91: =VLOOKUP(C91,Product_Cleaned!$A$2:$B$101,2,FALSE) -> Gaming Mechanical Keyboard | E91: =VLOOKUP(C91,Product_Cleaned!$A$2:$C$101,3,FALSE) -> Electronics | F91: =VLOOKUP(C91,Product_Cleaned!$A$2:$E$101,4,FALSE) -> Computer | G91: =VLOOKUP('Sales_Fact cleaned'!C1549,Product_Cleaned!$A$2:$E$101,5, FALSE) -> Olsen-Daniels | H91: STORE3 | I91: =_xlfn.XLOOKUP(H91,Store_Raw!$A$2:$A$21,Store_Raw!$B$2:$B$21) -> Johnson-Wright | J91: =_xlfn.XLOOKUP(H91,Store_Raw!$A$2:$A$21,Store_Raw!$C$2:$C$21) -> North | K91: =_xlfn.XLOOKUP(H91,Store_Raw!$A$2:$A$21,Store_Raw!$D$2:$D$21) -> Hoodberg | L91: =_xlfn.XLOOKUP(H91,Store_Raw!$A$2:$A$21,Store_Raw!$E$2:$E$21) -> Outlet | M91: =VLOOKUP(B91,Customer_Cleaned!$A$2:$H$501,2,FALSE) -> Nicholas Webb | N91: =VLOOKUP(B91,Customer_Cleaned!$A$2:$H$501,3,FALSE) -> 19 | O91: =VLOOKUP(B91,Customer_Cleaned!$A$2:$H$501,4,FALSE) -> Male | P91: =VLOOKUP(B91,Customer_Cleaned!$A$2:$H$501,8,FALSE) -> Bronze | Q91: =_xlfn.XLOOKUP('Sales_Fact cleaned'!B1549,Customer_Cleaned!$A$2:$A$501,Customer_Cleaned!$F$2:$F$501) -> Texas | R91: =_xlfn.XLOOKUP(B91,Customer_Cleaned!$A$2:$A$501,Customer_Cleaned!$G$2:$G$501) -> USA | S91: 3 | T91: 35.16 | U91: 0.04 | V91: 101.2608 | W91: Credit Card
A92: 45249 | B92: CUST1059 | C92: PROD23 | D92: =VLOOKUP(C92,Product_Cleaned!$A$2:$B$101,2,FALSE) -> Men's Formal Shirt | E92: =VLOOKUP(C92,Product_Cleaned!$A$2:$C$101,3,FALSE) -> Clothing | F92: =VLOOKUP(C92,Product_Cleaned!$A$2:$E$101,4,FALSE) -> Tops | G92: =VLOOKUP('Sales_Fact cleaned'!C253,Product_Cleaned!$A$2:$E$101,5, FALSE) -> Butler Group | H92: STORE1 | I92: =_xlfn.XLOOKUP(H92,Store_Raw!$A$2:$A$21,Store_Raw!$B$2:$B$21) -> Martinez, Adkins and Johnson | J92: =_xlfn.XLOOKUP(H92,Store_Raw!$A$2:$A$21,Store_Raw!$C$2:$C$21) -> North | K92: =_xlfn.XLOOKUP(H92,Store_Raw!$A$2:$A$21,Store_Raw!$D$2:$D$21) -> Danielmouth | L92: =_xlfn.XLOOKUP(H92,Store_Raw!$A$2:$A$21,Store_Raw!$E$2:$E$21) -> Flagship | M92: =VLOOKUP(B92,Customer_Cleaned!$A$2:$H$501,2,FALSE) -> Alyssa Vargas | N92: =VLOOKUP(B92,Customer_Cleaned!$A$2:$H$501,3,FALSE) -> 53 | O92: =VLOOKUP(B92,Customer_Cleaned!$A$2:$H$501,4,FALSE) -> Male | P92: =VLOOKUP(B92,Customer_Cleaned!$A$2:$H$501,8,FALSE) -> Platinum | Q92: =_xlfn.XLOOKUP('Sales_Fact cleaned'!B253,Customer_Cleaned!$A$2:$A$501,Customer_Cleaned!$F$2:$F$501) -> Illinois | R92: =_xlfn.XLOOKUP(B92,Customer_Cleaned!$A$2:$A$501,Customer_Cleaned!$G$2:$G$501) -> USA | S92: 2 | T92: 54.51 | U92: 0.07 | V92: 101.3886 | W92: COD
A93: 45250 | B93: CUST1288 | C93: PROD60 | D93: =VLOOKUP(C93,Product_Cleaned!$A$2:$B$101,2,FALSE) -> Luxury Perfume Spray | E93: =VLOOKUP(C93,Product_Cleaned!$A$2:$C$101,3,FALSE) -> Beauty | F93: =VLOOKUP(C93,Product_Cleaned!$A$2:$E$101,4,FALSE) -> Fragrance | G93: =VLOOKUP('Sales_Fact cleaned'!C1789,Product_Cleaned!$A$2:$E$101,5, FALSE) -> Poole PLC | H93: STORE15 | I93: =_xlfn.XLOOKUP(H93,Store_Raw!$A$2:$A$21,Store_Raw!$B$2:$B$21) -> Shelton PLC | J93: =_xlfn.XLOOKUP(H93,Store_Raw!$A$2:$A$21,Store_Raw!$C$2:$C$21) -> North | K93: =_xlfn.XLOOKUP(H93,Store_Raw!$A$2:$A$21,Store_Raw!$D$2:$D$21) -> East Jenniferstad | L93: =_xlfn.XLOOKUP(H93,Store_Raw!$A$2:$A$21,Store_Raw!$E$2:$E$21) -> Flagship | M93: =VLOOKUP(B93,Customer_Cleaned!$A$2:$H$501,2,FALSE) -> Misty Ferguson | N93: =VLOOKUP(B93,Customer_Cleaned!$A$2:$H$501,3,FALSE) -> 58 | O93: =VLOOKUP(B93,Customer_Cleaned!$A$2:$H$501,4,FALSE) -> Male | P93: =VLOOKUP(B93,Customer_Cleaned!$A$2:$H$501,8,FALSE) -> Platinum | Q93: =_xlfn.XLOOKUP('Sales_Fact cleaned'!B1789,Customer_Cleaned!$A$2:$A$501,Customer_Cleaned!$F$2:$F$501) -> Alabama | R93: =_xlfn.XLOOKUP(B93,Customer_Cleaned!$A$2:$A$501,Customer_Cleaned!$G$2:$G$501) -> USA | S93: 1 | T93: 145.96 | U93: 0.3 | V93: 102.172 | W93: PayPal
A94: 45250 | B94: CUST1149 | C94: PROD0 | D94: =VLOOKUP(C94,Product_Cleaned!$A$2:$B$101,2,FALSE) -> Brother Laser Printer | E94: =VLOOKUP(C94,Product_Cleaned!$A$2:$C$101,3,FALSE) -> Electronics | F94: =VLOOKUP(C94,Product_Cleaned!$A$2:$E$101,4,FALSE) -> Computer | G94: =VLOOKUP('Sales_Fact cleaned'!C468,Product_Cleaned!$A$2:$E$101,5, FALSE) -> Hogan-Lee | H94: STORE3 | I94: =_xlfn.XLOOKUP(H94,Store_Raw!$A$2:$A$21,Store_Raw!$B$2:$B$21) -> Johnson-Wright | J94: =_xlfn.XLOOKUP(H94,Store_Raw!$A$2:$A$21,Store_Raw!$C$2:$C$21) -> North | K94: =_xlfn.XLOOKUP(H94,Store_Raw!$A$2:$A$21,Store_Raw!$D$2:$D$21) -> Hoodberg | L94: =_xlfn.XLOOKUP(H94,Store_Raw!$A$2:$A$21,Store_Raw!$E$2:$E$21) -> Outlet | M94: =VLOOKUP(B94,Customer_Cleaned!$A$2:$H$501,2,FALSE) -> Denise Griffin | N94: =VLOOKUP(B94,Customer_Cleaned!$A$2:$H$501,3,FALSE) -> 33 | O94: =VLOOKUP(B94,Customer_Cleaned!$A$2:$H$501,4,FALSE) -> Male | P94: =VLOOKUP(B94,Customer_Cleaned!$A$2:$H$501,8,FALSE) -> Bronze | Q94: =_xlfn.XLOOKUP('Sales_Fact cleaned'!B468,Customer_Cleaned!$A$2:$A$501,Customer_Cleaned!$F$2:$F$501) -> Nevada | R94: =_xlfn.XLOOKUP(B94,Customer_Cleaned!$A$2:$A$501,Customer_Cleaned!$G$2:$G$501) -> USA | S94: 1 | T94: 140.24 | U94: 0.27 | V94: 102.3752 | W94: COD
A95: 45250 | B95: CUST1312 | C95: PROD86 | D95: =VLOOKUP(C95,Product_Cleaned!$A$2:$B$101,2,FALSE) -> Kitchen Cutting Board | E95: =VLOOKUP(C95,Product_Cleaned!$A$2:$C$101,3,FALSE) -> Home | F95: =VLOOKUP(C95,Product_Cleaned!$A$2:$E$101,4,FALSE) -> Kitchen | G95: =VLOOKUP('Sales_Fact cleaned'!C1774,Product_Cleaned!$A$2:$E$101,5, FALSE) -> Hopkins Ltd | H95: STORE1 | I95: =_xlfn.XLOOKUP(H95,Store_Raw!$A$2:$A$21,Store_Raw!$B$2:$B$21) -> Martinez, Adkins and Johnson | J95: =_xlfn.XLOOKUP(H95,Store_Raw!$A$2:$A$21,Store_Raw!$C$2:$C$21) -> North | K95: =_xlfn.XLOOKUP(H95,Store_Raw!$A$2:$A$21,Store_Raw!$D$2:$D$21) -> Danielmouth | L95: =_xlfn.XLOOKUP(H95,Store_Raw!$A$2:$A$21,Store_Raw!$E$2:$E$21) -> Flagship | M95: =VLOOKUP(B95,Customer_Cleaned!$A$2:$H$501,2,FALSE) -> Jason Mullins | N95: =VLOOKUP(B95,Customer_Cleaned!$A$2:$H$501,3,FALSE) -> 47 | O95: =VLOOKUP(B95,Customer_Cleaned!$A$2:$H$501,4,FALSE) -> Female | P95: =VLOOKUP(B95,Customer_Cleaned!$A$2:$H$501,8,FALSE) -> Silver | Q95: =_xlfn.XLOOKUP('Sales_Fact cleaned'!B1774,Customer_Cleaned!$A$2:$A$501,Customer_Cleaned!$F$2:$F$501) -> New Jersey | R95: =_xlfn.XLOOKUP(B95,Customer_Cleaned!$A$2:$A$501,Customer_Cleaned!$G$2:$G$501) -> USA | S95: 1 | T95: 119.04 | U95: 0.13 | V95: 103.5648 | W95: COD
A96: 45250 | B96: CUST1020 | C96: PROD98 | D96: =VLOOKUP(C96,Product_Cleaned!$A$2:$B$101,2,FALSE) -> Portable Bluetooth Speaker | E96: =VLOOKUP(C96,Product_Cleaned!$A$2:$C$101,3,FALSE) -> Electronics | F96: =VLOOKUP(C96,Product_Cleaned!$A$2:$E$101,4,FALSE) -> Audio | G96: =VLOOKUP('Sales_Fact cleaned'!C1210,Product_Cleaned!$A$2:$E$101,5, FALSE) -> Robinson Inc | H96: STORE19 | I96: =_xlfn.XLOOKUP(H96,Store_Raw!$A$2:$A$21,Store_Raw!$B$2:$B$21) -> Mann-Austin | J96: =_xlfn.XLOOKUP(H96,Store_Raw!$A$2:$A$21,Store_Raw!$C$2:$C$21) -> East | K96: =_xlfn.XLOOKUP(H96,Store_Raw!$A$2:$A$21,Store_Raw!$D$2:$D$21) -> Vasquezborough | L96: =_xlfn.XLOOKUP(H96,Store_Raw!$A$2:$A$21,Store_Raw!$E$2:$E$21) -> Online | M96: =VLOOKUP(B96,Customer_Cleaned!$A$2:$H$501,2,FALSE) -> Bridget Allen | N96: =VLOOKUP(B96,Customer_Cleaned!$A$2:$H$501,3,FALSE) -> 59 | O96: =VLOOKUP(B96,Customer_Cleaned!$A$2:$H$501,4,FALSE) -> Male | P96: =VLOOKUP(B96,Customer_Cleaned!$A$2:$H$501,8,FALSE) -> Platinum | Q96: =_xlfn.XLOOKUP('Sales_Fact cleaned'!B1210,Customer_Cleaned!$A$2:$A$501,Customer_Cleaned!$F$2:$F$501) -> South Carolina | R96: =_xlfn.XLOOKUP(B96,Customer_Cleaned!$A$2:$A$501,Customer_Cleaned!$G$2:$G$501) -> USA | S96: 3 | T96: 34.97 | U96: 0.01 | V96: 103.8609 | W96: PayPal
A97: 45250 | B97: CUST1028 | C97: PROD61 | D97: =VLOOKUP(C97,Product_Cleaned!$A$2:$B$101,2,FALSE) -> Tennis Ball 3-Pack | E97: =VLOOKUP(C97,Product_Cleaned!$A$2:$C$101,3,FALSE) -> Sports | F97: =VLOOKUP(C97,Product_Cleaned!$A$2:$E$101,4,FALSE) -> Equipment | G97: =VLOOKUP('Sales_Fact cleaned'!C1197,Product_Cleaned!$A$2:$E$101,5, FALSE) -> Smith-Charles | H97: STORE5 | I97: =_xlfn.XLOOKUP(H97,Store_Raw!$A$2:$A$21,Store_Raw!$B$2:$B$21) -> Gray Ltd | J97: =_xlfn.XLOOKUP(H97,Store_Raw!$A$2:$A$21,Store_Raw!$C$2:$C$21) -> North | K97: =_xlfn.XLOOKUP(H97,Store_Raw!$A$2:$A$21,Store_Raw!$D$2:$D$21) -> New Michaelchester | L97: =_xlfn.XLOOKUP(H97,Store_Raw!$A$2:$A$21,Store_Raw!$E$2:$E$21) -> Outlet | M97: =VLOOKUP(B97,Customer_Cleaned!$A$2:$H$501,2,FALSE) -> Joshua Ryan | N97: =VLOOKUP(B97,Customer_Cleaned!$A$2:$H$501,3,FALSE) -> 27 | O97: =VLOOKUP(B97,Customer_Cleaned!$A$2:$H$501,4,FALSE) -> Female | P97: =VLOOKUP(B97,Customer_Cleaned!$A$2:$H$501,8,FALSE) -> Bronze | Q97: =_xlfn.XLOOKUP('Sales_Fact cleaned'!B1197,Customer_Cleaned!$A$2:$A$501,Customer_Cleaned!$F$2:$F$501) -> Georgia | R97: =_xlfn.XLOOKUP(B97,Customer_Cleaned!$A$2:$A$501,Customer_Cleaned!$G$2:$G$501) -> USA | S97: 3 | T97: 38.07 | U97: 0.09 | V97: 103.9311 | W97: COD
A98: 45250 | B98: CUST1235 | C98: PROD80 | D98: =VLOOKUP(C98,Product_Cleaned!$A$2:$B$101,2,FALSE) -> Wall-Mounted Spice Rack | E98: =VLOOKUP(C98,Product_Cleaned!$A$2:$C$101,3,FALSE) -> Home | F98: =VLOOKUP(C98,Product_Cleaned!$A$2:$E$101,4,FALSE) -> Kitchen | G98: =VLOOKUP('Sales_Fact cleaned'!C972,Product_Cleaned!$A$2:$E$101,5, FALSE) -> Baldwin, Garza and Gonzalez | H98: STORE10 | I98: =_xlfn.XLOOKUP(H98,Store_Raw!$A$2:$A$21,Store_Raw!$B$2:$B$21) -> Hill, Wagner and Ballard | J98: =_xlfn.XLOOKUP(H98,Store_Raw!$A$2:$A$21,Store_Raw!$C$2:$C$21) -> East | K98: =_xlfn.XLOOKUP(H98,Store_Raw!$A$2:$A$21,Store_Raw!$D$2:$D$21) -> East Davidville | L98: =_xlfn.XLOOKUP(H98,Store_Raw!$A$2:$A$21,Store_Raw!$E$2:$E$21) -> Online | M98: =VLOOKUP(B98,Customer_Cleaned!$A$2:$H$501,2,FALSE) -> Jon Ortiz | N98: =VLOOKUP(B98,Customer_Cleaned!$A$2:$H$501,3,FALSE) -> 28 | O98: =VLOOKUP(B98,Customer_Cleaned!$A$2:$H$501,4,FALSE) -> Female | P98: =VLOOKUP(B98,Customer_Cleaned!$A$2:$H$501,8,FALSE) -> Bronze | Q98: =_xlfn.XLOOKUP('Sales_Fact cleaned'!B972,Customer_Cleaned!$A$2:$A$501,Customer_Cleaned!$F$2:$F$501) -> Tennessee | R98: =_xlfn.XLOOKUP(B98,Customer_Cleaned!$A$2:$A$501,Customer_Cleaned!$G$2:$G$501) -> USA | S98: 2 | T98: 61.31 | U98: 0.15 | V98: 104.227 | W98: COD
A99: 45251 | B99: CUST1471 | C99: PROD43 | D99: =VLOOKUP(C99,Product_Cleaned!$A$2:$B$101,2,FALSE) -> USB External Hard Drive | E99: =VLOOKUP(C99,Product_Cleaned!$A$2:$C$101,3,FALSE) -> Electronics | F99: =VLOOKUP(C99,Product_Cleaned!$A$2:$E$101,4,FALSE) -> Computer | G99: =VLOOKUP('Sales_Fact cleaned'!C1744,Product_Cleaned!$A$2:$E$101,5, FALSE) -> Davis PLC | H99: STORE1 | I99: =_xlfn.XLOOKUP(H99,Store_Raw!$A$2:$A$21,Store_Raw!$B$2:$B$21) -> Martinez, Adkins and Johnson | J99: =_xlfn.XLOOKUP(H99,Store_Raw!$A$2:$A$21,Store_Raw!$C$2:$C$21) -> North | K99: =_xlfn.XLOOKUP(H99,Store_Raw!$A$2:$A$21,Store_Raw!$D$2:$D$21) -> Danielmouth | L99: =_xlfn.XLOOKUP(H99,Store_Raw!$A$2:$A$21,Store_Raw!$E$2:$E$21) -> Flagship | M99: =VLOOKUP(B99,Customer_Cleaned!$A$2:$H$501,2,FALSE) -> Debra Mccullough | N99: =VLOOKUP(B99,Customer_Cleaned!$A$2:$H$501,3,FALSE) -> 42 | O99: =VLOOKUP(B99,Customer_Cleaned!$A$2:$H$501,4,FALSE) -> Male | P99: =VLOOKUP(B99,Customer_Cleaned!$A$2:$H$501,8,FALSE) -> Silver | Q99: =_xlfn.XLOOKUP('Sales_Fact cleaned'!B1744,Customer_Cleaned!$A$2:$A$501,Customer_Cleaned!$F$2:$F$501) -> Nevada | R99: =_xlfn.XLOOKUP(B99,Customer_Cleaned!$A$2:$A$501,Customer_Cleaned!$G$2:$G$501) -> USA | S99: 1 | T99: 135.87 | U99: 0.23 | V99: 104.6199 | W99: Credit Card
A100: 45251 | B100: CUST1208 | C100: PROD34 | D100: =VLOOKUP(C100,Product_Cleaned!$A$2:$B$101,2,FALSE) -> Gaming Mechanical Keyboard | E100: =VLOOKUP(C100,Product_Cleaned!$A$2:$C$101,3,FALSE) -> Electronics | F100: =VLOOKUP(C100,Product_Cleaned!$A$2:$E$101,4,FALSE) -> Computer | G100: =VLOOKUP('Sales_Fact cleaned'!C301,Product_Cleaned!$A$2:$E$101,5, FALSE) -> Robinson-Brown | H100: STORE4 | I100: =_xlfn.XLOOKUP(H100,Store_Raw!$A$2:$A$21,Store_Raw!$B$2:$B$21) -> Alexander Group | J100: =_xlfn.XLOOKUP(H100,Store_Raw!$A$2:$A$21,Store_Raw!$C$2:$C$21) -> South | K100: =_xlfn.XLOOKUP(H100,Store_Raw!$A$2:$A$21,Store_Raw!$D$2:$D$21) -> Port Sharon | L100: =_xlfn.XLOOKUP(H100,Store_Raw!$A$2:$A$21,Store_Raw!$E$2:$E$21) -> Online | M100: =VLOOKUP(B100,Customer_Cleaned!$A$2:$H$501,2,FALSE) -> John Perez | N100: =VLOOKUP(B100,Customer_Cleaned!$A$2:$H$501,3,FALSE) -> 54 | O100: =VLOOKUP(B100,Customer_Cleaned!$A$2:$H$501,4,FALSE) -> Male | P100: =VLOOKUP(B100,Customer_Cleaned!$A$2:$H$501,8,FALSE) -> Platinum | Q100: =_xlfn.XLOOKUP('Sales_Fact cleaned'!B301,Customer_Cleaned!$A$2:$A$501,Customer_Cleaned!$F$2:$F$501) -> Hawaii | R100: =_xlfn.XLOOKUP(B100,Customer_Cleaned!$A$2:$A$501,Customer_Cleaned!$G$2:$G$501) -> USA | S100: 2 | T100: 56.91 | U100: 0.08 | V100: 104.7144 | W100: COD
...

Sheet Descriptive statistics of Sales
G1: Descriptive statistics of Sales_fact cleaned
B5: Quantity | E5: Unit_Price | H5: Discount | K5: Total_Amount
B7: Mean | C7: 2.474 | E7: Mean | F7: 513.58229 | H7: Mean | I7: 0.14779 | K7: Mean | L7: 1087.1973
B8: Standard Error | C8: 0.024989483 | E8: Standard Error | F8: 6.313512 | H8: Standard Error | I8: 0.0019632461 | K8: Standard Error | L8: 18.327237
B9: Median | C9: 2 | E9: Median | F9: 522.43 | H9: Median | I9: 0.14 | K9: Median | L9: 868.7182
B10: Mode | C10: 2 | E10: Mode | F10: 213.69 | H10: Mode | I10: 0.1 | K10: Mode | L10: #N/A
B11: Standard Deviation | C11: 1.1175636 | E11: Standard Deviation | F11: 282.34884 | H11: Standard Deviation | I11: 0.087799033 | K11: Standard Deviation | L11: 819.61896
B12: Sample Variance | C12: 1.2489485 | E12: Sample Variance | F12: 79720.869 | H12: Sample Variance | I12: 0.0077086702 | K12: Sample Variance | L12: 671775.25
B13: Kurtosis | C13: -1.3208847 | E13: Kurtosis | F13: -1.1931872 | H13: Kurtosis | I13: -1.2089461 | K13: Kurtosis | L13: 0.045826153
B14: Skewness | C14: 0.014628002 | E14: Skewness | F14: -0.03481715 | H14: Skewness | I14: 0.06217785 | K14: Skewness | L14: 0.87904704
B15: Range | C15: 4 | E15: Range | F15: 979.8 | H15: Range | I15: 0.3 | K15: Range | L15: 3889.7838
B16: Minimum | C16: 0 | E16: Minimum | F16: 20.09 | H16: Minimum | I16: 0 | K16: Minimum | L16: 18.459
B17: Maximum | C17: 4 | E17: Maximum | F17: 999.89 | H17: Maximum | I17: 0.3 | K17: Maximum | L17: 3908.2428
B18: Sum | C18: 4948 | E18: Sum | F18: 1027164.6 | H18: Sum | I18: 295.58 | K18: Sum | L18: 2174394.7
B19: Count | C19: 2000 | E19: Count | F19: 2000 | H19: Count | I19: 2000 | K19: Count | L19: 2000
B20: Largest(1) | C20: 4 | E20: Largest(1) | F20: 999.89 | H20: Largest(1) | I20: 0.3 | K20: Largest(1) | L20: 3908.2428
B21: Smallest(1) | C21: 0 | E21: Smallest(1) | F21: 20.09 | H21: Smallest(1) | I21: 0 | K21: Smallest(1) | L21: 18.459
B22: Confidence Level(95.0%) | C22: 0.049008159 | E22: Confidence Level(95.0%) | F22: 12.381753 | H22: Confidence Level(95.0%) | I22: 0.0038502228 | K22: Confidence Level(95.0%) | L22: 35.942487

Sheet Detail1
A3: Order_Date | B3: Customer_ID | C3: Product_ID | D3: Product_Name | E3: Category | F3: Sub_Category | G3: Brand | H3: Store_ID | I3: Store_Name | J3: Region | K3: City | L3: Store_Type | M3: Name | N3: Age | O3: Gender | P3: Loyalty_Level | Q3: State | R3: Country | S3: Quantity | T3: Unit_Price | U3: Discount | V3: Total_Amount | W3: Payment_Type
A4: 45213 | B4: CUST1181 | C4: PROD81 | D4: Badminton Racket Set | E4: Sports | F4: Equipment | G4: Green, Powell and Palmer | H4: STORE7 | I4: Martinez-Mullins | J4: South | K4: Williamsfurt | L4: Online | M4: Erin Ward | N4: 60 | O4: Male | P4: Platinum | Q4: Missouri | R4: USA | S4: 1 | T4: 26.37 | U4: 0.3 | V4: 18.459 | W4: Credit Card
A5: 45213 | B5: CUST1089 | C5: PROD20 | D5: Outdoor Sports Water Bottle | E5: Sports | F5: Accessories | G5: Harris Inc | H5: STORE18 | I5: Guerrero-Schmitt | J5: East | K5: East Stevechester | L5: Flagship | M5: Jamie Yoder | N5: 43 | O5: Male | P5: Silver | Q5: Pennsylvania | R5: USA | S5: 1 | T5: 27.83 | U5: 0.3 | V5: 19.481 | W5: Credit Card
A6: 45213 | B6: CUST1343 | C6: PROD38 | D6: Sports Water Hydration Pack | E6: Sports | F6: Outdoor | G6: Larson Ltd | H6: STORE12 | I6: Thomas, Bridges and Harris | J6: North | K6: Sabrinatown | L6: Online | M6: Ryan Moore | N6: 38 | O6: Male | P6: Silver | Q6: North Dakota | R6: USA | S6: 1 | T6: 21.14 | U6: 0.06 | V6: 19.8716 | W6: PayPal
A7: 45214 | B7: CUST1293 | C7: PROD73 | D7: Shin Guards – Adult | E7: Sports | F7: Team Sports | G7: Montgomery, Benton and Miller | H7: STORE3 | I7: Johnson-Wright | J7: North | K7: Hoodberg | L7: Outlet | M7: Gloria Taylor | N7: 56 | O7: Female | P7: Platinum | Q7: Kansas | R7: USA | S7: 1 | T7: 24.13 | U7: 0 | V7: 24.13 | W7: Credit Card
A8: 45214 | B8: CUST1384 | C8: PROD74 | D8: Bluetooth Car Audio System | E8: Electronics | F8: Audio | G8: Anderson-Riley | H8: STORE10 | I8: Hill, Wagner and Ballard | J8: East | K8: East Davidville | L8: Online | M8: Andrew Mason | N8: 52 | O8: Female | P8: Platinum | Q8: Nebraska | R8: USA | S8: 1 | T8: 30.94 | U8: 0.21 | V8: 24.4426 | W8: COD
A9: 45215 | B9: CUST1241 | C9: PROD15 | D9: 4K Home Projector | E9: Electronics | F9: Appliances | G9: Hernandez Inc | H9: STORE14 | I9: Mcdonald Inc | J9: South | K9: Christopherland | L9: Outlet | M9: Mr. William Horton | N9: 31 | O9: Male | P9: Bronze | Q9: New Mexico | R9: USA | S9: 1 | T9: 31.36 | U9: 0.21 | V9: 24.7744 | W9: Credit Card
A10: 45215 | B10: CUST1105 | C10: PROD57 | D10: Foam Roller | E10: Sports | F10: Fitness | G10: Robinson-Brown | H10: STORE3 | I10: Johnson-Wright | J10: North | K10: Hoodberg | L10: Outlet | M10: Lance Baker | N10: 50 | O10: Female | P10: Platinum | Q10: New Hampshire | R10: USA | S10: 1 | T10: 38.95 | U10: 0.28 | V10: 28.044 | W10: Credit Card
A11: 45216 | B11: CUST1104 | C11: PROD31 | D11: Basketball | E11: Sports | F11: Team Sports | G11: Allison Ltd | H11: STORE3 | I11: Johnson-Wright | J11: North | K11: Hoodberg | L11: Outlet | M11: Christopher Lester | N11: 64 | O11: Male | P11: Platinum | Q11: Pennsylvania | R11: USA | S11: 1 | T11: 36.8 | U11: 0.18 | V11: 30.176 | W11: COD
A12: 45216 | B12: CUST1377 | C12: PROD78 | D12: Essential Oil Diffuser | E12: Home | F12: Decor | G12: Moon, Mora and Santos | H12: STORE4 | I12: Alexander Group | J12: South | K12: Port Sharon | L12: Online | M12: Charles Conley | N12: 39 | O12: Female | P12: Silver | Q12: Arkansas | R12: USA | S12: 1 | T12: 34.71 | U12: 0.1 | V12: 31.239 | W12: COD
A13: 45217 | B13: CUST1007 | C13: PROD5 | D13: Men's Leather Belt | E13: Clothing | F13: Accessories | G13: Dawson-Perkins | H13: STORE14 | I13: Mcdonald Inc | J13: South | K13: Christopherland | L13: Outlet | M13: Daniel Boyd | N13: 29 | O13: Female | P13: Bronze | Q13: Kansas | R13: USA | S13: 1 | T13: 38.88 | U13: 0.16 | V13: 32.6592 | W13: PayPal
A14: 45217 | B14: CUST1274 | C14: PROD44 | D14: Adjustable Jump Rope | E14: Sports | F14: Fitness | G14: Zhang Inc | H14: STORE4 | I14: Alexander Group | J14: South | K14: Port Sharon | L14: Online | M14: Sarah Lane | N14: 38 | O14: Male | P14: Silver | Q14: Georgia | R14: USA | S14: 1 | T14: 34.51 | U14: 0.04 | V14: 33.1296 | W14: PayPal
A15: 45217 | B15: CUST1305 | C15: PROD5 | D15: Men's Leather Belt | E15: Clothing | F15: Accessories | G15: Khan, Jones and Paul | H15: STORE4 | I15: Alexander Group | J15: South | K15: Port Sharon | L15: Online | M15: Roberta Green | N15: 64 | O15: Male | P15: Platinum | Q15: Kansas | R15: USA | S15: 1 | T15: 47.47 | U15: 0.28 | V15: 34.1784 | W15: PayPal
... A2003: 45943 | B2003: CUST1376 | C2003: PROD85 | D2003: Women's Beanie Hat | E2003: Clothing | F2003: Accessories | G2003: Wolfe, Ross and Hester | H2003: STORE3 | I2003: Johnson-Wright | J2003: North | K2003: Hoodberg | L2003: Outlet | M2003: Michele Burke | N2003: 30 | O2003: Male | P2003: Bronze | Q2003: Ohio | R2003: USA | S2003: 4 | T2003: 986.93 | U2003: 0.01 | V2003: 3908.2428 | W2003: COD

Sheet Detail2
A1: Details for Sum of Total_Amount - Gender: Female (+)
A3: Order_Date | B3: Customer_ID | C3: Product_ID | D3: Product_Name | E3: Category | F3: Sub_Category | G3: Brand | H3: Store_ID | I3: Store_Name | J3: Region | K3: City | L3: Store_Type | M3: Name | N3: Age | O3: Gender | P3: Loyalty_Level | Q3: State | R3: Country | S3: Quantity | T3: Unit_Price | U3: Discount | V3: Total_Amount | W3: Payment_Type
A4: 45215 | B4: CUST1241 | C4: PROD15 | D4: 4K Home Projector | E4: Electronics | F4: Appliances | G4: Hernandez Inc | H4: STORE14 | I4: Mcdonald Inc | J4: South | K4: Christopherland | L4: Outlet | M4: Mr. William Horton | N4: 31 | O4: Male | P4: Bronze | Q4: New Mexico | R4: USA | S4: 1 | T4: 31.36 | U4: 0.21 | V4: 24.7744 | W4: Credit Card
A5: 45217 | B5: CUST1007 | C5: PROD5 | D5: Men's Leather Belt | E5: Clothing | F5: Accessories | G5: Dawson-Perkins | H5: STORE14 | I5: Mcdonald Inc | J5: South | K5: Christopherland | L5: Outlet | M5: Daniel Boyd | N5: 29 | O5: Female | P5: Bronze | Q5: Kansas | R5: USA | S5: 1 | T5: 38.88 | U5: 0.16 | V5: 32.6592 | W5: PayPal
A6: 45217 | B6: CUST1340 | C6: PROD41 | D6: Yoga Exercise Mat | E6: Sports | F6: Fitness | G6: Stevens, Fernandez and Martin | H6: STORE5 | I6: Gray Ltd | J6: North | K6: New Michaelchester | L6: Outlet | M6: Eric Davis | N6: 27 | O6: Male | P6: Bronze | Q6: Oregon | R6: USA | S6: 2 | T6: 20.47 | U6: 0.12 | V6: 36.0272 | W6: COD
A7: 45218 | B7: CUST1275 | C7: PROD38 | D7: Sports Water Hydration Pack | E7: Sports | F7: Outdoor | G7: Sharp, Taylor and Rodriguez | H7: STORE9 | I7: Moore, Padilla and Butler | J7: South | K7: East Johnstad | L7: Flagship | M7: Shannon Miller | N7: 22 | O7: Male | P7: Bronze | Q7: Iowa | R7: USA | S7: 1 | T7: 40.25 | U7: 0.1 | V7: 36.225 | W7: Credit Card
A8: 45218 | B8: CUST1490 | C8: PROD84 | D8: Wooden Bookshelf | E8: Home | F8: Furniture | G8: Fitzpatrick Ltd | H8: STORE14 | I8: Mcdonald Inc | J8: South | K8: Christopherland | L8: Outlet | M8: Scott Harris | N8: 23 | O8: Male | P8: Bronze | Q8: Minnesota | R8: USA | S8: 1 | T8: 46.66 | U8: 0.2 | V8: 37.328 | W8: COD
A9: 45219 | B9: CUST1431 | C9: PROD25 | D9: Women's Scarf Set | E9: Clothing | F9: Accessories | G9: Lopez LLC | H9: STORE8 | I9: Bean, Jones and Park | J9: West | K9: Thompsonborough | L9: Online | M9: John Smith | N9: 27 | O9: Male | P9: Bronze | Q9: New Jersey | R9: USA | S9: 1 | T9: 52.06 | U9: 0.27 | V9: 38.0038 | W9: PayPal
A10: 45222 | B10: CUST1036 | C10: PROD59 | D10: Men's Hair Styling Gel | E10: Beauty | F10: Haircare | G10: Wilson Group | H10: STORE11 | I10: Aguirre-Keller | J10: South | K10: Lake Michael | L10: Online | M10: Thomas Phillips | N10: 20 | O10: Female | P10: Bronze | Q10: South Carolina | R10: USA | S10: 2 | T10: 23.58 | U10: 0.02 | V10: 46.2168 | W10: PayPal
A11: 45222 | B11: CUST1207 | C11: PROD84 | D11: Wooden Bookshelf | E11: Home | F11: Furniture | G11: Hatfield, Baird and Torres | H11: STORE8 | I11: Bean, Jones and Park | J11: West | K11: Thompsonborough | L11: Online | M11: Jacqueline Pacheco | N11: 28 | O11: Female | P11: Bronze | Q11: Washington | R11: USA | S11: 2 | T11: 30.14 | U11: 0.21 | V11: 47.6212 | W11: PayPal
A12: 45224 | B12: CUST1206 | C12: PROD56 | D12: Premium Blanket Throw | E12: Home | F12: Decor | G12: Ford, Murphy and Wilson | H12: STORE18 | I12: Guerrero-Schmitt | J12: East | K12: East Stevechester | L12: Flagship | M12: Ronald Jones | N12: 26 | O12: Female | P12: Bronze | Q12: Wyoming | R12: USA | S12: 1 | T12: 75.8 | U12: 0.29 | V12: 53.818 | W12: COD
A13: 45225 | B13: CUST1042 | C13: PROD89 | D13: Face Foundation Kit | E13: Beauty | F13: Makeup | G13: Burns-Hansen | H13: STORE2 | I13: Black-Horn | J13: South | K13: North Nancyview | L13: Outlet | M13: William Martin | N13: 19 | O13: Male | P13: Bronze | Q13: Ohio | R13: USA | S13: 3 | T13: 21.59 | U13: 0.16 | V13: 54.4068 | W13: COD
A14: 45225 | B14: CUST1444 | C14: PROD17 | D14: Soccer Training Cone Set | E14: Sports | F14: Accessories | G14: Khan, Jones and Paul | H14: STORE6 | I14: Benson-Elliott | J14: East | K14: Port Josephberg | L14: Online | M14: Cheryl Carr | N14: 19 | O14: Male | P14: Bronze | Q14: Alaska | R14: USA | S14: 1 | T14: 55.04 | U14: 0.01 | V14: 54.4896 | W14: PayPal
A15: 45228 | B15: CUST1190 | C15: PROD44 | D15: Adjustable Jump Rope | E15: Sports | F15: Fitness | G15: Ramirez-Hanson | H15: STORE6 | I15: Benson-Elliott | J15: East | K15: Port Josephberg | L15: Online | M15: Christopher Stewart | N15: 21 | O15: Male | P15: Bronze | Q15: West Virginia | R15: USA | S15: 1 | T15: 62.38 | U15: 0.08 | V15: 57.3896 | W15: Credit Card
... A2003: 45943 | B2003: CUST1238 | C2003: PROD43 | D2003: USB External Hard Drive | E2003: Electronics | F2003: Computer | G2003: Luna, Anderson and Bowman | H2003: STORE18 | I2003: Guerrero-Schmitt | J2003: East | K2003: East Stevechester | L2003: Flagship | M2003: Steven Smith | N2003: 40 | O2003: Male | P2003: Silver | Q2003: Florida | R2003: USA | S2003: 4 | T2003: 975.47 | U2003: 0.04 | V2003: 3745.8048 | W2003: Credit Card

Sheet E-COMMERCE SALESDATA ANALYSIS
E2: E-COMMERCE SALESDATA ANALYSIS
A6: KPI
A7: Total Revenue | B7: Total Quantity Sold | C7: Average Revenue per Customer (ARPC)
A8: 2174394.7 | B8: 4948 | C8: 4419.5014
A9: 2174394.7 | C9: 4419.5
A14: Category-wise Revenue Contribution
A15: Row Labels | B15: Sum of Total_Amount
A16: Sports | B16: 0.24926945
A17: Electronics | B17: 0.23193183
A18: Home | B18: 0.19651253
A19: Clothing | B19: 0.17440074
A20: Beauty | B20: 0.14788545
A21: Grand Total | B21: 1
A31: Revenue by Store Type
A32: Row Labels | B32: Sum of Total_Amount
A33: Online | B33: 914253.52
A34: Flagship | B34: 848576.67
A35: Outlet | B35: 411564.51
A36: Grand Total | B36: 2174394.7
B44: Price vs volume insight
A45: Row Labels | B45: Sub-category Quantity | C45: Average of Unit_Price
A46: Accessories | B46: 837 | C46: 508.1488
A47: Appliances | B47: 170 | C47: 520.87614
A48: Audio | B48: 265 | C48: 460.75098
A49: Bottoms | B49: 162 | C49: 514.46106
A50: Computer | B50: 360 | C50: 488.41096
A51: Decor | B51: 333 | C51: 539.66424
A52: Equipment | B52: 203 | C52: 515.68391
A53: Fitness | B53: 335 | C53: 479.28522
A54: Footwear | B54: 202 | C54: 552.02375
A55: Fragrance | B55: 99 | C55: 526.88263
A56: Furniture | B56: 85 | C56: 542.94457
A57: Grooming | B57: 62 | C57: 445.72636
... A69: Grand Total | B69: 4948 | C69: 513.58229
A77: Gender | B77: (All)
A78: Loyalty Level vs Sales
A79: Row Labels | B79: Sum of Total_Amount | C79: Count of Customer_ID
A80: Bronze | B80: 774300.31 | C80: 711
A81: Platinum | B81: 706428.79 | C81: 677
A82: Silver | B82: 693665.59 | C82: 612
A92: Category | B92: (All)
A93: Region-wise Sales Performance
A94: Row Labels | B94: Sum of Total_Amount
A95: West | B95: 270676.41
A96: South | B96: 635213.1
A97: North | B97: 646100.88
A98: East | B98: 622404.32
A108: Years (Order_Date) | B108: (All)
A110: Monthly sales | B110: Sum of Total_Amount
A111: Jan | B111: 112930.63
A112: Feb | B112: 126935.84
A113: Mar | B113: 168062
A114: Apr | B114: 168120.31
A115: May | B115: 198290.93
A116: Jun | B116: 181012.74
A117: Jul | B117: 265219.27
A118: Aug | B118: 278113.96
A119: Sep | B119: 294731.28
A120: Oct | B120: 190241.9
A121: Nov | B121: 86467.22
A122: Dec | B122: 104268.62

Sheet Sheet2
D7: Average of Unit_Price | E7: Sum of Quantity
D8: 508.1488 | E8: 837
D9: 520.87614 | E9: 170
D10: 460.75098 | E10: 265
D11: 514.46106 | E11: 162
D12: 488.41096 | E12: 360
D13: 539.66424 | E13: 333
D14: 515.68391 | E14: 203
D15: 479.28522 | E15: 335
D16: 552.02375 | E16: 202
D17: 526.88263 | E17: 99
D18: 542.94457 | E18: 85
D19: 445.72636 | E19: 62
... D30: 473.95277 | E30: 109

Sheet PIVOT DASHBOARD

Sheet Sheet3
